Workbook

Sheet Read Me
B1: Global Communications Calendar — FIRST DRAFT
B2: One shared place for every outbound communication across AMER, EMEA and APAC — webinars, emails, social, events, PR, in-app and customer notices — so every team knows what goes out, when, to whom, and whether it's ready.
B4: Tabs
B5: Comms Calendar | C5: The master list. One row per communication. This is the only tab most people edit.
B6: Month View | C6: Calendar grid for any month, filterable by region. Read-only.
B7: Week View | C7: Rolling 26 weeks: volume per region & channel, plus red flags. Use it in the weekly sync.
B8: Dashboard | C8: Headline numbers, region × channel, readiness by region, next 6 months.
B9: Audience Lists | C9: Official segment & list names, owners, consent basis, suppressions.
B10: Owners & RACI | C10: Who's who, who does what, and the proposed meeting rhythm & rules.
B11: Rules & Guardrails | C11: Frequency cap, content-lock, at-risk window, channel lead times, blackout dates.
B12: Change Log | C12: Record of changes after content lock or anything that moves another team's dates.
B13: Dropdowns | C13: Values behind every dropdown. Edit here to add a team, owner, time zone, etc.
B15: How to add a comm
B16: 1. Add a row | C16: On Comms Calendar, fill the white cells. Minimum: ID, Region, Channel, Target Segment, Launch Date, Owner, Overall Status.
B17: 2. Pick the audience | C17: Use segment / list names from Audience Lists so the frequency and clash checks can match them.
B18: 3. Ops involved? | C18: If Marketing Ops needs to build, pull lists or send: set 'Ops Involved? = Yes', raise a ticket, add the ticket #.
B19: 4. Track readiness | C19: Update Content Status, Assets Ready?, List Ready?, Ops Ready? as work progresses. Readiness updates itself.
B20: 5. Watch the flags | C20: Fix anything red: Over cap, Clash, Blackout, At Risk, Overdue, or a red 'Brief Due By' date.
B21: 6. After launch | C21: Set Overall Status = Launched. Never delete rows — use Cancelled so history is kept.
B23: Colour key
B24: White cell | C24: Input — type or pick from the dropdown.
B25: Grey cell | C25: Automatic formula — don't type over it.
B26: Yellow cell | C26: Setting / filter you can change (Rules & Guardrails, Month View, Week View).
B27: Blue text | C27: Editable assumption (e.g. lead times).
B28: Readiness colours | C28: Green = Ready · Yellow = In Progress · Orange = At Risk (inside the at-risk window) · Red = Overdue (date passed, not ready) · Blue = Launched.
B30: How Readiness works
B31: Ready | C31: Content Approved AND Assets Yes/N/A AND List Yes/N/A AND (Ops not involved OR Ops Ready = Yes).
B32: At Risk | C32: Not ready and launching within the at-risk window (default 7 days).
B33: Overdue | C33: Not ready and launch date has passed (and status isn't Launched).
B34: What's Missing | C34: Lists exactly what still blocks the comm — use it to chase the right person.
B36: Before rolling out
B37: Example data | C37: The rows dated Oct–Dec 2026 are illustrative examples (incl. a deliberate clash, cap breach and blackout). Replace them with real plans.
B38: To confirm together | C38: Owner names & emails · APAC owner · frequency cap · lead times · content-lock rule · blackout dates per region · RACI split.
B39: Sharing | C39: Put the file on SharePoint/OneDrive or upload to Google Sheets so everyone edits the same copy. Restrict Rules & Dropdowns edits to the calendar owners.

Sheet Comms Calendar
A1: Global Communications Calendar — AMER · EMEA · APAC
A2: One row per communication (webinar, email, social post, event, customer notice...). White cells = fill in · Grey cells = automatic, don't type over them · Hover a header for guidance. Example rows are illustrative — replace them with real plans.
A3: IDENTIFY | G3: CONTENT | K3: AUDIENCE & LISTS | O3: TIMING | U3: OWNERSHIP | Y3: READINESS | AI3: AUTO CHECKS | AO3: NOTES | AR3: HELPERS
A4: ID | B4: Region | C4: Country / Market | D4: Channel | E4: Audience Type | F4: Campaign / Program | G4: Title / Subject Line | H4: Key Message | I4: CTA / Landing Page | J4: Language | K4: Target Segment | L4: Lists Included | M4: Lists Excluded / Suppression | N4: Est. Reach (#) | O4: Launch Date | P4: Launch Time (local) | Q4: Time Zone | R4: Frequency / Cadence | S4: Touch # in Sequence | T4: Brief Due By | U4: Owner | V4: Owning Team | W4: Approver | X4: Collaborators / Keep Informed | Y4: Content Status | Z4: Assets Ready? | AA4: List Ready? | AB4: Ops Involved? | AC4: Ops Ticket # | AD4: Ops Ready? | AE4: Overall Status | AF4: Readiness | AG4: What's Missing | AH4: Days to Launch | AI4: Week Commencing | AJ4: Month | AK4: Same-Week Touches | AL4: Frequency Flag | AM4: Date Clash | AN4: Blackout Flag | AO4: Dependencies / Notes | AP4: Last Updated | AQ4: Updated By | AR4: Channel Group | AS4: _Key
A5: AM-001 | B5: AMER | C5: US & Canada | D5: Email - Webinar Invite / Reminder | E5: Customer | F5: Q4 Roadmap Webinar | G5: You're invited: What's next on our Q4 roadmap | H5: Preview Q4 releases and get answers live from Product. | I5: Register - /webinars/q4-roadmap | J5: EN | K5: AMER Customers - Active | L5: AMER Customers - Active; AMER Champions | M5: Unsubscribed; Open support escalations | N5: 4800 | O5: 46308 | P5: 10:00 | Q5: ET | R5: Sequence (multi-touch) | S5: 1 of 3 | T5: =IF(OR($O5="",$D5=""),"",WORKDAY($O5,-IFERROR(VLOOKUP($D5,'Rules & Guardrails'!$A$9:$D$24,3,0),10))) -> 46294 | U5: Head of Mkt AMER | V5: Digital | W5: Head of Marketing (Global) | X5: CS leadership; AMER Sales | Y5: Approved | Z5: Yes | AA5: Yes | AB5: Yes | AC5: OPS-1042 | AD5: Yes | AE5: Scheduled | AF5: =IF($O5="","",IF(OR($AE5="Cancelled",$AE5="On hold",$AE5="Launched"),$AE5,IF(AND($Y5="Approved",OR($Z5="Yes",$Z5="N/A"),OR($AA5="Yes",$AA5="N/A"),OR($AB5="No",$AB5="N/A",AND($AB5="Yes",$AD5="Yes"))),"Ready",IF($O5<TODAY(),"Overdue",IF($O5-TODAY()<='Rules & Guardrails'!$C$5,"At Risk","In Progress"))))) -> Ready | AG5: =IF($O5="","",IF(OR($AE5="Launched",$AE5="Cancelled"),"",MID(IF($Y5<>"Approved",", Content approval","")&IF(NOT(OR($Z5="Yes",$Z5="N/A")),", Assets","")&IF(NOT(OR($AA5="Yes",$AA5="N/A")),", List","")&IF($AB5="",", Ops decision",IF(AND($AB5="Yes",$AD5<>"Yes"),", Ops",""))&IF($U5="",", Owner","")&IF($K5="",", Segment",""),3,200))) | AH5: =IF($O5="","",$O5-TODAY()) -> 5 | AI5: =IF($O5="","",$O5-WEEKDAY($O5,3)) -> 46307 | AJ5: =IF($O5="","",DATE(YEAR($O5),MONTH($O5),1)) -> 46296 | AK5: =IF(OR($O5="",$K5=""),"",COUNTIFS('Comms Calendar'!$K$5:$K$504,$K5,'Comms Calendar'!$B$5:$B$504,$B5,'Comms Calendar'!$AI$5:$AI$504,$AI5,'Comms Calendar'!$AE$5:$AE$504,"<>Cancelled")) -> 3 | AL5: =IF($AK5="","",IF($AK5>'Rules & Guardrails'!$C$3,"Over cap","OK")) -> Over cap | AM5: =IF(OR($O5="",$K5=""),"",IF(COUNTIFS('Comms Calendar'!$K$5:$K$504,$K5,'Comms Calendar'!$B$5:$B$504,$B5,'Comms Calendar'!$O$5:$O$504,$O5,'Comms Calendar'!$AE$5:$AE$504,"<>Cancelled")>1,"Clash","")) -> Clash | AN5: =IF($O5="","",IF(IF($B5="Global",COUNTIF('Rules & Guardrails'!$F$9:$F$60,$O5),COUNTIFS('Rules & Guardrails'!$F$9:$F$60,$O5,'Rules & Guardrails'!$G$9:$G$60,$B5)+COUNTIFS('Rules & Guardrails'!$F$9:$F$60,$O5,'Rules & Guardrails'!$G$9:$G$60,"Global"))>0,"Blackout","")) | AO5: Depends on webinar landing page (Digital). | AP5: 46303 | AQ5: Draft (example) | AR5: =IF($D5="","",IFERROR(VLOOKUP($D5,'Rules & Guardrails'!$A$9:$D$24,2,0),"Other")) -> Email | AS5: =IF($O5="","",$O5&"|"&$B5) -> 46308|AMER
A6: AM-002 | B6: AMER | C6: US & Canada | D6: Email - Customer Notice | E6: Customer | F6: Platform Update | G6: Important: upcoming maintenance window | H6: Planned maintenance on 24 Oct, 2-4am ET. No action needed. | I6: Status page | J6: EN | K6: AMER Customers - Active | L6: AMER Customers - Active; AMER Admin Contacts | M6: Unsubscribed (service msg - legal check) | N6: 5200 | O6: 46308 | P6: 14:00 | Q6: ET | R6: One-off | T6: =IF(OR($O6="",$D6=""),"",WORKDAY($O6,-IFERROR(VLOOKUP($D6,'Rules & Guardrails'!$A$9:$D$24,3,0),10))) -> 46287 | U6: Customer Success | V6: Customer Success | W6: Head of Mkt AMER | X6: Support; Product | Y6: In review | Z6: Yes | AA6: No | AB6: Yes | AC6: OPS-1051 | AD6: No | AE6: In production | AF6: =IF($O6="","",IF(OR($AE6="Cancelled",$AE6="On hold",$AE6="Launched"),$AE6,IF(AND($Y6="Approved",OR($Z6="Yes",$Z6="N/A"),OR($AA6="Yes",$AA6="N/A"),OR($AB6="No",$AB6="N/A",AND($AB6="Yes",$AD6="Yes"))),"Ready",IF($O6<TODAY(),"Overdue",IF($O6-TODAY()<='Rules & Guardrails'!$C$5,"At Risk","In Progress"))))) -> At Risk | AG6: =IF($O6="","",IF(OR($AE6="Launched",$AE6="Cancelled"),"",MID(IF($Y6<>"Approved",", Content approval","")&IF(NOT(OR($Z6="Yes",$Z6="N/A")),", Assets","")&IF(NOT(OR($AA6="Yes",$AA6="N/A")),", List","")&IF($AB6="",", Ops decision",IF(AND($AB6="Yes",$AD6<>"Yes"),", Ops",""))&IF($U6="",", Owner","")&IF($K6="",", Segment",""),3,200))) -> Content approval, List, Ops | AH6: =IF($O6="","",$O6-TODAY()) -> 5 | AI6: =IF($O6="","",$O6-WEEKDAY($O6,3)) -> 46307 | AJ6: =IF($O6="","",DATE(YEAR($O6),MONTH($O6),1)) -> 46296 | AK6: =IF(OR($O6="",$K6=""),"",COUNTIFS('Comms Calendar'!$K$5:$K$504,$K6,'Comms Calendar'!$B$5:$B$504,$B6,'Comms Calendar'!$AI$5:$AI$504,$AI6,'Comms Calendar'!$AE$5:$AE$504,"<>Cancelled")) -> 3 | AL6: =IF($AK6="","",IF($AK6>'Rules & Guardrails'!$C$3,"Over cap","OK")) -> Over cap | AM6: =IF(OR($O6="",$K6=""),"",IF(COUNTIFS('Comms Calendar'!$K$5:$K$504,$K6,'Comms Calendar'!$B$5:$B$504,$B6,'Comms Calendar'!$O$5:$O$504,$O6,'Comms Calendar'!$AE$5:$AE$504,"<>Cancelled")>1,"Clash","")) -> Clash | AN6: =IF($O6="","",IF(IF($B6="Global",COUNTIF('Rules & Guardrails'!$F$9:$F$60,$O6),COUNTIFS('Rules & Guardrails'!$F$9:$F$60,$O6,'Rules & Guardrails'!$G$9:$G$60,$B6)+COUNTIFS('Rules & Guardrails'!$F$9:$F$60,$O6,'Rules & Guardrails'!$G$9:$G$60,"Global"))>0,"Blackout","")) | AO6: EXAMPLE CLASH: same segment, same day as AM-001 - move one of them. | AP6: 46303 | AQ6: Draft (example) | AR6: =IF($D6="","",IFERROR(VLOOKUP($D6,'Rules & Guardrails'!$A$9:$D$24,2,0),"Other")) -> Email | AS6: =IF($O6="","",$O6&"|"&$B6) -> 46308|AMER
A7: AM-003 | B7: AMER | C7: US & Canada | D7: Email - Webinar Invite / Reminder | E7: Customer | F7: Q4 Roadmap Webinar | G7: Reminder: Q4 roadmap webinar is next week | H7: Last chance to save your seat. | I7: Register - /webinars/q4-roadmap | J7: EN | K7: AMER Customers - Active | L7: AMER Customers - Active; AMER Champions | M7: Already registered; Unsubscribed | N7: 4500 | O7: 46310 | P7: 10:00 | Q7: ET | R7: Sequence (multi-touch) | S7: 2 of 3 | T7: =IF(OR($O7="",$D7=""),"",WORKDAY($O7,-IFERROR(VLOOKUP($D7,'Rules & Guardrails'!$A$9:$D$24,3,0),10))) -> 46296 | U7: Head of Mkt AMER | V7: Digital | W7: Head of Marketing (Global) | Y7: Approved | Z7: Yes | AA7: Yes | AB7: Yes | AC7: OPS-1042 | AD7: Yes | AE7: Scheduled | AF7: =IF($O7="","",IF(OR($AE7="Cancelled",$AE7="On hold",$AE7="Launched"),$AE7,IF(AND($Y7="Approved",OR($Z7="Yes",$Z7="N/A"),OR($AA7="Yes",$AA7="N/A"),OR($AB7="No",$AB7="N/A",AND($AB7="Yes",$AD7="Yes"))),"Ready",IF($O7<TODAY(),"Overdue",IF($O7-TODAY()<='Rules & Guardrails'!$C$5,"At Risk","In Progress"))))) -> Ready | AG7: =IF($O7="","",IF(OR($AE7="Launched",$AE7="Cancelled"),"",MID(IF($Y7<>"Approved",", Content approval","")&IF(NOT(OR($Z7="Yes",$Z7="N/A")),", Assets","")&IF(NOT(OR($AA7="Yes",$AA7="N/A")),", List","")&IF($AB7="",", Ops decision",IF(AND($AB7="Yes",$AD7<>"Yes"),", Ops",""))&IF($U7="",", Owner","")&IF($K7="",", Segment",""),3,200))) | AH7: =IF($O7="","",$O7-TODAY()) -> 7 | AI7: =IF($O7="","",$O7-WEEKDAY($O7,3)) -> 46307 | AJ7: =IF($O7="","",DATE(YEAR($O7),MONTH($O7),1)) -> 46296 | AK7: =IF(OR($O7="",$K7=""),"",COUNTIFS('Comms Calendar'!$K$5:$K$504,$K7,'Comms Calendar'!$B$5:$B$504,$B7,'Comms Calendar'!$AI$5:$AI$504,$AI7,'Comms Calendar'!$AE$5:$AE$504,"<>Cancelled")) -> 3 | AL7: =IF($AK7="","",IF($AK7>'Rules & Guardrails'!$C$3,"Over cap","OK")) -> Over cap | AM7: =IF(OR($O7="",$K7=""),"",IF(COUNTIFS('Comms Calendar'!$K$5:$K$504,$K7,'Comms Calendar'!$B$5:$B$504,$B7,'Comms Calendar'!$O$5:$O$504,$O7,'Comms Calendar'!$AE$5:$AE$504,"<>Cancelled")>1,"Clash","")) | AN7: =IF($O7="","",IF(IF($B7="Global",COUNTIF('Rules & Guardrails'!$F$9:$F$60,$O7),COUNTIFS('Rules & Guardrails'!$F$9:$F$60,$O7,'Rules & Guardrails'!$G$9:$G$60,$B7)+COUNTIFS('Rules & Guardrails'!$F$9:$F$60,$O7,'Rules & Guardrails'!$G$9:$G$60,"Global"))>0,"Blackout","")) | AO7: EXAMPLE: 3rd touch to this segment this week -> Over cap. | AP7: 46303 | AQ7: Draft (example) | AR7: =IF($D7="","",IFERROR(VLOOKUP($D7,'Rules & Guardrails'!$A$9:$D$24,2,0),"Other")) -> Email | AS7: =IF($O7="","",$O7&"|"&$B7) -> 46310|AMER
A8: AM-004 | B8: AMER | C8: US & Canada | D8: Webinar | E8: Customer | F8: Q4 Roadmap Webinar | G8: Q4 Product Roadmap - Live Webinar | H8: Live roadmap walkthrough + Q&A with Product leaders. | I8: /webinars/q4-roadmap | J8: EN | K8: AMER Customers - Active | L8: Registrants | N8: 600 | O8: 46317 | P8: 11:00 | Q8: ET | R8: One-off | T8: =IF(OR($O8="",$D8=""),"",WORKDAY($O8,-IFERROR(VLOOKUP($D8,'Rules & Guardrails'!$A$9:$D$24,3,0),10))) -> 46275 | U8: Head of Mkt AMER | V8: Field Marketing | W8: Head of Marketing (Global) | X8: Product (speakers); AMER Sales | Y8: Approved | Z8: Yes | AA8: Yes | AB8: Yes | AC8: OPS-1040 | AD8: Yes | AE8: Scheduled | AF8: =IF($O8="","",IF(OR($AE8="Cancelled",$AE8="On hold",$AE8="Launched"),$AE8,IF(AND($Y8="Approved",OR($Z8="Yes",$Z8="N/A"),OR($AA8="Yes",$AA8="N/A"),OR($AB8="No",$AB8="N/A",AND($AB8="Yes",$AD8="Yes"))),"Ready",IF($O8<TODAY(),"Overdue",IF($O8-TODAY()<='Rules & Guardrails'!$C$5,"At Risk","In Progress"))))) -> Ready | AG8: =IF($O8="","",IF(OR($AE8="Launched",$AE8="Cancelled"),"",MID(IF($Y8<>"Approved",", Content approval","")&IF(NOT(OR($Z8="Yes",$Z8="N/A")),", Assets","")&IF(NOT(OR($AA8="Yes",$AA8="N/A")),", List","")&IF($AB8="",", Ops decision",IF(AND($AB8="Yes",$AD8<>"Yes"),", Ops",""))&IF($U8="",", Owner","")&IF($K8="",", Segment",""),3,200))) | AH8: =IF($O8="","",$O8-TODAY()) -> 14 | AI8: =IF($O8="","",$O8-WEEKDAY($O8,3)) -> 46314 | AJ8: =IF($O8="","",DATE(YEAR($O8),MONTH($O8),1)) -> 46296 | AK8: =IF(OR($O8="",$K8=""),"",COUNTIFS('Comms Calendar'!$K$5:$K$504,$K8,'Comms Calendar'!$B$5:$B$504,$B8,'Comms Calendar'!$AI$5:$AI$504,$AI8,'Comms Calendar'!$AE$5:$AE$504,"<>Cancelled")) -> 1 | AL8: =IF($AK8="","",IF($AK8>'Rules & Guardrails'!$C$3,"Over cap","OK")) -> OK | AM8: =IF(OR($O8="",$K8=""),"",IF(COUNTIFS('Comms Calendar'!$K$5:$K$504,$K8,'Comms Calendar'!$B$5:$B$504,$B8,'Comms Calendar'!$O$5:$O$504,$O8,'Comms Calendar'!$AE$5:$AE$504,"<>Cancelled")>1,"Clash","")) | AN8: =IF($O8="","",IF(IF($B8="Global",COUNTIF('Rules & Guardrails'!$F$9:$F$60,$O8),COUNTIFS('Rules & Guardrails'!$F$9:$F$60,$O8,'Rules & Guardrails'!$G$9:$G$60,$B8)+COUNTIFS('Rules & Guardrails'!$F$9:$F$60,$O8,'Rules & Guardrails'!$G$9:$G$60,"Global"))>0,"Blackout","")) | AO8: Speakers confirmed. Dry run 20 Oct. | AP8: 46303 | AQ8: Draft (example) | AR8: =IF($D8="","",IFERROR(VLOOKUP($D8,'Rules & Guardrails'!$A$9:$D$24,2,0),"Other")) -> Webinar | AS8: =IF($O8="","",$O8&"|"&$B8) -> 46317|AMER
A9: EM-001 | B9: EMEA | C9: UK & I, DACH, France | D9: Email - Webinar Invite / Reminder | E9: Customer + Prospect | F9: Q4 Roadmap Webinar | G9: Join us: Q4 roadmap live (EN/DE/FR) | H9: Same story as AMER, localised for EMEA. | I9: Register - /webinars/q4-roadmap-emea | J9: Multi | K9: EMEA Customers + Engaged Prospects | L9: EMEA Customers - Active; EMEA Prospects - Engaged 90d | M9: No GDPR consent; Unsubscribed | N9: 9100 | O9: 46309 | P9: 09:00 | Q9: CET | R9: Sequence (multi-touch) | S9: 1 of 3 | T9: =IF(OR($O9="",$D9=""),"",WORKDAY($O9,-IFERROR(VLOOKUP($D9,'Rules & Guardrails'!$A$9:$D$24,3,0),10))) -> 46295 | U9: Head of Mkt EMEA | V9: Digital | W9: Head of Marketing (Global) | X9: EMEA Sales; Localisation | Y9: In review | Z9: No | AA9: Yes | AB9: Yes | AC9: OPS-1047 | AD9: No | AE9: In production | AF9: =IF($O9="","",IF(OR($AE9="Cancelled",$AE9="On hold",$AE9="Launched"),$AE9,IF(AND($Y9="Approved",OR($Z9="Yes",$Z9="N/A"),OR($AA9="Yes",$AA9="N/A"),OR($AB9="No",$AB9="N/A",AND($AB9="Yes",$AD9="Yes"))),"Ready",IF($O9<TODAY(),"Overdue",IF($O9-TODAY()<='Rules & Guardrails'!$C$5,"At Risk","In Progress"))))) -> At Risk | AG9: =IF($O9="","",IF(OR($AE9="Launched",$AE9="Cancelled"),"",MID(IF($Y9<>"Approved",", Content approval","")&IF(NOT(OR($Z9="Yes",$Z9="N/A")),", Assets","")&IF(NOT(OR($AA9="Yes",$AA9="N/A")),", List","")&IF($AB9="",", Ops decision",IF(AND($AB9="Yes",$AD9<>"Yes"),", Ops",""))&IF($U9="",", Owner","")&IF($K9="",", Segment",""),3,200))) -> Content approval, Assets, Ops | AH9: =IF($O9="","",$O9-TODAY()) -> 6 | AI9: =IF($O9="","",$O9-WEEKDAY($O9,3)) -> 46307 | AJ9: =IF($O9="","",DATE(YEAR($O9),MONTH($O9),1)) -> 46296 | AK9: =IF(OR($O9="",$K9=""),"",COUNTIFS('Comms Calendar'!$K$5:$K$504,$K9,'Comms Calendar'!$B$5:$B$504,$B9,'Comms Calendar'!$AI$5:$AI$504,$AI9,'Comms Calendar'!$AE$5:$AE$504,"<>Cancelled")) -> 1 | AL9: =IF($AK9="","",IF($AK9>'Rules & Guardrails'!$C$3,"Over cap","OK")) -> OK | AM9: =IF(OR($O9="",$K9=""),"",IF(COUNTIFS('Comms Calendar'!$K$5:$K$504,$K9,'Comms Calendar'!$B$5:$B$504,$B9,'Comms Calendar'!$O$5:$O$504,$O9,'Comms Calendar'!$AE$5:$AE$504,"<>Cancelled")>1,"Clash","")) | AN9: =IF($O9="","",IF(IF($B9="Global",COUNTIF('Rules & Guardrails'!$F$9:$F$60,$O9),COUNTIFS('Rules & Guardrails'!$F$9:$F$60,$O9,'Rules & Guardrails'!$G$9:$G$60,$B9)+COUNTIFS('Rules & Guardrails'!$F$9:$F$60,$O9,'Rules & Guardrails'!$G$9:$G$60,"Global"))>0,"Blackout","")) | AO9: Waiting on DE/FR translations. | AP9: 46303 | AQ9: Draft (example) | AR9: =IF($D9="","",IFERROR(VLOOKUP($D9,'Rules & Guardrails'!$A$9:$D$24,2,0),"Other")) -> Email | AS9: =IF($O9="","",$O9&"|"&$B9) -> 46309|EMEA
A10: EM-002 | B10: EMEA | C10: UK & I, DACH, France | D10: Webinar | E10: Customer + Prospect | F10: Q4 Roadmap Webinar | G10: Q4 Product Roadmap - EMEA session | H10: Live roadmap + EMEA customer guest speaker. | I10: /webinars/q4-roadmap-emea | J10: EN | K10: EMEA Customers + Engaged Prospects | L10: Registrants | N10: 750 | O10: 46318 | P10: 10:00 | Q10: CET | R10: One-off | T10: =IF(OR($O10="",$D10=""),"",WORKDAY($O10,-IFERROR(VLOOKUP($D10,'Rules & Guardrails'!$A$9:$D$24,3,0),10))) -> 46276 | U10: Head of Mkt EMEA | V10: Field Marketing | W10: Head of Marketing (Global) | X10: Product; EMEA Sales | Y10: Drafting | Z10: No | AA10: N/A | AB10: Yes | AD10: No | AE10: Planned | AF10: =IF($O10="","",IF(OR($AE10="Cancelled",$AE10="On hold",$AE10="Launched"),$AE10,IF(AND($Y10="Approved",OR($Z10="Yes",$Z10="N/A"),OR($AA10="Yes",$AA10="N/A"),OR($AB10="No",$AB10="N/A",AND($AB10="Yes",$AD10="Yes"))),"Ready",IF($O10<TODAY(),"Overdue",IF($O10-TODAY()<='Rules & Guardrails'!$C$5,"At Risk","In Progress"))))) -> In Progress | AG10: =IF($O10="","",IF(OR($AE10="Launched",$AE10="Cancelled"),"",MID(IF($Y10<>"Approved",", Content approval","")&IF(NOT(OR($Z10="Yes",$Z10="N/A")),", Assets","")&IF(NOT(OR($AA10="Yes",$AA10="N/A")),", List","")&IF($AB10="",", Ops decision",IF(AND($AB10="Yes",$AD10<>"Yes"),", Ops",""))&IF($U10="",", Owner","")&IF($K10="",", Segment",""),3,200))) -> Content approval, Assets, Ops | AH10: =IF($O10="","",$O10-TODAY()) -> 15 | AI10: =IF($O10="","",$O10-WEEKDAY($O10,3)) -> 46314 | AJ10: =IF($O10="","",DATE(YEAR($O10),MONTH($O10),1)) -> 46296 | AK10: =IF(OR($O10="",$K10=""),"",COUNTIFS('Comms Calendar'!$K$5:$K$504,$K10,'Comms Calendar'!$B$5:$B$504,$B10,'Comms Calendar'!$AI$5:$AI$504,$AI10,'Comms Calendar'!$AE$5:$AE$504,"<>Cancelled")) -> 1 | AL10: =IF($AK10="","",IF($AK10>'Rules & Guardrails'!$C$3,"Over cap","OK")) -> OK | AM10: =IF(OR($O10="",$K10=""),"",IF(COUNTIFS('Comms Calendar'!$K$5:$K$504,$K10,'Comms Calendar'!$B$5:$B$504,$B10,'Comms Calendar'!$O$5:$O$504,$O10,'Comms Calendar'!$AE$5:$AE$504,"<>Cancelled")>1,"Clash","")) | AN10: =IF($O10="","",IF(IF($B10="Global",COUNTIF('Rules & Guardrails'!$F$9:$F$60,$O10),COUNTIFS('Rules & Guardrails'!$F$9:$F$60,$O10,'Rules & Guardrails'!$G$9:$G$60,$B10)+COUNTIFS('Rules & Guardrails'!$F$9:$F$60,$O10,'Rules & Guardrails'!$G$9:$G$60,"Global"))>0,"Blackout","")) | AO10: Guest speaker TBC. | AP10: 46303 | AQ10: Draft (example) | AR10: =IF($D10="","",IFERROR(VLOOKUP($D10,'Rules & Guardrails'!$A$9:$D$24,2,0),"Other")) -> Webinar | AS10: =IF($O10="","",$O10&"|"&$B10) -> 46318|EMEA
A11: EM-003 | B11: EMEA | C11: UK | D11: Event - In-person | E11: Customer | F11: Customer Roundtables | G11: Executive Customer Roundtable - London | H11: Invite-only dinner with 20 strategic accounts. | I11: RSVP | J11: EN | K11: EMEA Strategic Accounts | L11: EMEA Strategic Accounts - Execs | N11: 40 | O11: 46338 | P11: 18:30 | Q11: GMT/BST | R11: One-off | T11: =IF(OR($O11="",$D11=""),"",WORKDAY($O11,-IFERROR(VLOOKUP($D11,'Rules & Guardrails'!$A$9:$D$24,3,0),10))) -> 46282 | U11: Field Marketing | V11: Field Marketing | W11: Head of Mkt EMEA | X11: Account Execs; CS | Y11: Approved | Z11: Yes | AA11: Yes | AB11: No | AE11: Planned | AF11: =IF($O11="","",IF(OR($AE11="Cancelled",$AE11="On hold",$AE11="Launched"),$AE11,IF(AND($Y11="Approved",OR($Z11="Yes",$Z11="N/A"),OR($AA11="Yes",$AA11="N/A"),OR($AB11="No",$AB11="N/A",AND($AB11="Yes",$AD11="Yes"))),"Ready",IF($O11<TODAY(),"Overdue",IF($O11-TODAY()<='Rules & Guardrails'!$C$5,"At Risk","In Progress"))))) -> Ready | AG11: =IF($O11="","",IF(OR($AE11="Launched",$AE11="Cancelled"),"",MID(IF($Y11<>"Approved",", Content approval","")&IF(NOT(OR($Z11="Yes",$Z11="N/A")),", Assets","")&IF(NOT(OR($AA11="Yes",$AA11="N/A")),", List","")&IF($AB11="",", Ops decision",IF(AND($AB11="Yes",$AD11<>"Yes"),", Ops",""))&IF($U11="",", Owner","")&IF($K11="",", Segment",""),3,200))) | AH11: =IF($O11="","",$O11-TODAY()) -> 35 | AI11: =IF($O11="","",$O11-WEEKDAY($O11,3)) -> 46335 | AJ11: =IF($O11="","",DATE(YEAR($O11),MONTH($O11),1)) -> 46327 | AK11: =IF(OR($O11="",$K11=""),"",COUNTIFS('Comms Calendar'!$K$5:$K$504,$K11,'Comms Calendar'!$B$5:$B$504,$B11,'Comms Calendar'!$AI$5:$AI$504,$AI11,'Comms Calendar'!$AE$5:$AE$504,"<>Cancelled")) -> 1 | AL11: =IF($AK11="","",IF($AK11>'Rules & Guardrails'!$C$3,"Over cap","OK")) -> OK | AM11: =IF(OR($O11="",$K11=""),"",IF(COUNTIFS('Comms Calendar'!$K$5:$K$504,$K11,'Comms Calendar'!$B$5:$B$504,$B11,'Comms Calendar'!$O$5:$O$504,$O11,'Comms Calendar'!$AE$5:$AE$504,"<>Cancelled")>1,"Clash","")) | AN11: =IF($O11="","",IF(IF($B11="Global",COUNTIF('Rules & Guardrails'!$F$9:$F$60,$O11),COUNTIFS('Rules & Guardrails'!$F$9:$F$60,$O11,'Rules & Guardrails'!$G$9:$G$60,$B11)+COUNTIFS('Rules & Guardrails'!$F$9:$F$60,$O11,'Rules & Guardrails'!$G$9:$G$60,"Global"))>0,"Blackout","")) | AO11: Venue booked. | AP11: 46303 | AQ11: Draft (example) | AR11: =IF($D11="","",IFERROR(VLOOKUP($D11,'Rules & Guardrails'!$A$9:$D$24,2,0),"Other")) -> Event | AS11: =IF($O11="","",$O11&"|"&$B11) -> 46338|EMEA
A12: AP-001 | B12: APAC | C12: ANZ, SG, JP | D12: Webinar | E12: Customer + Prospect | F12: Q4 Roadmap Webinar | G12: Q4 Product Roadmap - APAC session | H12: APAC-timed session of the roadmap webinar. | I12: /webinars/q4-roadmap-apac | J12: EN | K12: APAC Customers + Engaged Prospects | L12: APAC Customers - Active; APAC Prospects - Engaged 90d | M12: Unsubscribed | N12: 3000 | O12: 46323 | P12: 14:00 | Q12: SGT | R12: One-off | T12: =IF(OR($O12="",$D12=""),"",WORKDAY($O12,-IFERROR(VLOOKUP($D12,'Rules & Guardrails'!$A$9:$D$24,3,0),10))) -> 46281 | U12: APAC Marketing Lead | V12: Field Marketing | W12: Head of Marketing (Global) | X12: APAC Sales | Y12: Drafting | Z12: No | AA12: No | AB12: Yes | AE12: Planned | AF12: =IF($O12="","",IF(OR($AE12="Cancelled",$AE12="On hold",$AE12="Launched"),$AE12,IF(AND($Y12="Approved",OR($Z12="Yes",$Z12="N/A"),OR($AA12="Yes",$AA12="N/A"),OR($AB12="No",$AB12="N/A",AND($AB12="Yes",$AD12="Yes"))),"Ready",IF($O12<TODAY(),"Overdue",IF($O12-TODAY()<='Rules & Guardrails'!$C$5,"At Risk","In Progress"))))) -> In Progress | AG12: =IF($O12="","",IF(OR($AE12="Launched",$AE12="Cancelled"),"",MID(IF($Y12<>"Approved",", Content approval","")&IF(NOT(OR($Z12="Yes",$Z12="N/A")),", Assets","")&IF(NOT(OR($AA12="Yes",$AA12="N/A")),", List","")&IF($AB12="",", Ops decision",IF(AND($AB12="Yes",$AD12<>"Yes"),", Ops",""))&IF($U12="",", Owner","")&IF($K12="",", Segment",""),3,200))) -> Content approval, Assets, List, Ops | AH12: =IF($O12="","",$O12-TODAY()) -> 20 | AI12: =IF($O12="","",$O12-WEEKDAY($O12,3)) -> 46321 | AJ12: =IF($O12="","",DATE(YEAR($O12),MONTH($O12),1)) -> 46296 | AK12: =IF(OR($O12="",$K12=""),"",COUNTIFS('Comms Calendar'!$K$5:$K$504,$K12,'Comms Calendar'!$B$5:$B$504,$B12,'Comms Calendar'!$AI$5:$AI$504,$AI12,'Comms Calendar'!$AE$5:$AE$504,"<>Cancelled")) -> 1 | AL12: =IF($AK12="","",IF($AK12>'Rules & Guardrails'!$C$3,"Over cap","OK")) -> OK | AM12: =IF(OR($O12="",$K12=""),"",IF(COUNTIFS('Comms Calendar'!$K$5:$K$504,$K12,'Comms Calendar'!$B$5:$B$504,$B12,'Comms Calendar'!$O$5:$O$504,$O12,'Comms Calendar'!$AE$5:$AE$504,"<>Cancelled")>1,"Clash","")) | AN12: =IF($O12="","",IF(IF($B12="Global",COUNTIF('Rules & Guardrails'!$F$9:$F$60,$O12),COUNTIFS('Rules & Guardrails'!$F$9:$F$60,$O12,'Rules & Guardrails'!$G$9:$G$60,$B12)+COUNTIFS('Rules & Guardrails'!$F$9:$F$60,$O12,'Rules & Guardrails'!$G$9:$G$60,"Global"))>0,"Blackout","")) | AO12: Japanese subtitles for recording? | AP12: 46303 | AQ12: Draft (example) | AR12: =IF($D12="","",IFERROR(VLOOKUP($D12,'Rules & Guardrails'!$A$9:$D$24,2,0),"Other")) -> Webinar | AS12: =IF($O12="","",$O12&"|"&$B12) -> 46323|APAC
A13: AP-002 | B13: APAC | C13: ANZ | D13: Email - Campaign / Nurture | E13: Prospect | F13: APAC Nurture Q4 | G13: 3 ways teams in ANZ cut reporting time | H13: Value-led nurture, case study from a local customer. | I13: Read the case study | J13: EN | K13: APAC Prospects - Engaged 90d | L13: APAC Prospects - Engaged 90d | M13: Customers; Open opportunities | N13: 2100 | O13: 46331 | P13: 09:00 | Q13: AEST | R13: Bi-weekly | S13: 1 of 4 | T13: =IF(OR($O13="",$D13=""),"",WORKDAY($O13,-IFERROR(VLOOKUP($D13,'Rules & Guardrails'!$A$9:$D$24,3,0),10))) -> 46317 | U13: APAC Marketing Lead | V13: Digital | W13: Dean (Digital) | X13: APAC SDRs | Y13: Not started | Z13: No | AA13: No | AB13: Yes | AE13: Planned | AF13: =IF($O13="","",IF(OR($AE13="Cancelled",$AE13="On hold",$AE13="Launched"),$AE13,IF(AND($Y13="Approved",OR($Z13="Yes",$Z13="N/A"),OR($AA13="Yes",$AA13="N/A"),OR($AB13="No",$AB13="N/A",AND($AB13="Yes",$AD13="Yes"))),"Ready",IF($O13<TODAY(),"Overdue",IF($O13-TODAY()<='Rules & Guardrails'!$C$5,"At Risk","In Progress"))))) -> In Progress | AG13: =IF($O13="","",IF(OR($AE13="Launched",$AE13="Cancelled"),"",MID(IF($Y13<>"Approved",", Content approval","")&IF(NOT(OR($Z13="Yes",$Z13="N/A")),", Assets","")&IF(NOT(OR($AA13="Yes",$AA13="N/A")),", List","")&IF($AB13="",", Ops decision",IF(AND($AB13="Yes",$AD13<>"Yes"),", Ops",""))&IF($U13="",", Owner","")&IF($K13="",", Segment",""),3,200))) -> Content approval, Assets, List, Ops | AH13: =IF($O13="","",$O13-TODAY()) -> 28 | AI13: =IF($O13="","",$O13-WEEKDAY($O13,3)) -> 46328 | AJ13: =IF($O13="","",DATE(YEAR($O13),MONTH($O13),1)) -> 46327 | AK13: =IF(OR($O13="",$K13=""),"",COUNTIFS('Comms Calendar'!$K$5:$K$504,$K13,'Comms Calendar'!$B$5:$B$504,$B13,'Comms Calendar'!$AI$5:$AI$504,$AI13,'Comms Calendar'!$AE$5:$AE$504,"<>Cancelled")) -> 1 | AL13: =IF($AK13="","",IF($AK13>'Rules & Guardrails'!$C$3,"Over cap","OK")) -> OK | AM13: =IF(OR($O13="",$K13=""),"",IF(COUNTIFS('Comms Calendar'!$K$5:$K$504,$K13,'Comms Calendar'!$B$5:$B$504,$B13,'Comms Calendar'!$O$5:$O$504,$O13,'Comms Calendar'!$AE$5:$AE$504,"<>Cancelled")>1,"Clash","")) | AN13: =IF($O13="","",IF(IF($B13="Global",COUNTIF('Rules & Guardrails'!$F$9:$F$60,$O13),COUNTIFS('Rules & Guardrails'!$F$9:$F$60,$O13,'Rules & Guardrails'!$G$9:$G$60,$B13)+COUNTIFS('Rules & Guardrails'!$F$9:$F$60,$O13,'Rules & Guardrails'!$G$9:$G$60,"Global"))>0,"Blackout","")) | AP13: 46303 | AQ13: Draft (example) | AR13: =IF($D13="","",IFERROR(VLOOKUP($D13,'Rules & Guardrails'!$A$9:$D$24,2,0),"Other")) -> Email | AS13: =IF($O13="","",$O13&"|"&$B13) -> 46331|APAC
A14: GL-001 | B14: Global | C14: All | D14: Email - Newsletter | E14: Customer | F14: Customer Newsletter | G14: October customer newsletter | H14: Product highlights, upcoming webinars by region, community spotlight. | I14: Newsletter hub | J14: EN | K14: All Customers | L14: All Customers - Active | M14: Unsubscribed | N14: 21000 | O14: 46324 | P14: 10:00 | Q14: ET | R14: Monthly | T14: =IF(OR($O14="",$D14=""),"",WORKDAY($O14,-IFERROR(VLOOKUP($D14,'Rules & Guardrails'!$A$9:$D$24,3,0),10))) -> 46310 | U14: Dean (Digital) | V14: Digital | W14: Head of Marketing (Global) | X14: Regional Heads (content inputs due 20 Oct) | Y14: Drafting | Z14: No | AA14: Yes | AB14: Yes | AC14: OPS-1055 | AD14: No | AE14: In production | AF14: =IF($O14="","",IF(OR($AE14="Cancelled",$AE14="On hold",$AE14="Launched"),$AE14,IF(AND($Y14="Approved",OR($Z14="Yes",$Z14="N/A"),OR($AA14="Yes",$AA14="N/A"),OR($AB14="No",$AB14="N/A",AND($AB14="Yes",$AD14="Yes"))),"Ready",IF($O14<TODAY(),"Overdue",IF($O14-TODAY()<='Rules & Guardrails'!$C$5,"At Risk","In Progress"))))) -> In Progress | AG14: =IF($O14="","",IF(OR($AE14="Launched",$AE14="Cancelled"),"",MID(IF($Y14<>"Approved",", Content approval","")&IF(NOT(OR($Z14="Yes",$Z14="N/A")),", Assets","")&IF(NOT(OR($AA14="Yes",$AA14="N/A")),", List","")&IF($AB14="",", Ops decision",IF(AND($AB14="Yes",$AD14<>"Yes"),", Ops",""))&IF($U14="",", Owner","")&IF($K14="",", Segment",""),3,200))) -> Content approval, Assets, Ops | AH14: =IF($O14="","",$O14-TODAY()) -> 21 | AI14: =IF($O14="","",$O14-WEEKDAY($O14,3)) -> 46321 | AJ14: =IF($O14="","",DATE(YEAR($O14),MONTH($O14),1)) -> 46296 | AK14: =IF(OR($O14="",$K14=""),"",COUNTIFS('Comms Calendar'!$K$5:$K$504,$K14,'Comms Calendar'!$B$5:$B$504,$B14,'Comms Calendar'!$AI$5:$AI$504,$AI14,'Comms Calendar'!$AE$5:$AE$504,"<>Cancelled")) -> 1 | AL14: =IF($AK14="","",IF($AK14>'Rules & Guardrails'!$C$3,"Over cap","OK")) -> OK | AM14: =IF(OR($O14="",$K14=""),"",IF(COUNTIFS('Comms Calendar'!$K$5:$K$504,$K14,'Comms Calendar'!$B$5:$B$504,$B14,'Comms Calendar'!$O$5:$O$504,$O14,'Comms Calendar'!$AE$5:$AE$504,"<>Cancelled")>1,"Clash","")) | AN14: =IF($O14="","",IF(IF($B14="Global",COUNTIF('Rules & Guardrails'!$F$9:$F$60,$O14),COUNTIFS('Rules & Guardrails'!$F$9:$F$60,$O14,'Rules & Guardrails'!$G$9:$G$60,$B14)+COUNTIFS('Rules & Guardrails'!$F$9:$F$60,$O14,'Rules & Guardrails'!$G$9:$G$60,"Global"))>0,"Blackout","")) | AO14: Each region sends 1-2 items by 20 Oct. | AP14: 46303 | AQ14: Draft (example) | AR14: =IF($D14="","",IFERROR(VLOOKUP($D14,'Rules & Guardrails'!$A$9:$D$24,2,0),"Other")) -> Email | AS14: =IF($O14="","",$O14&"|"&$B14) -> 46324|Global
A15: GL-002 | B15: Global | C15: All | D15: Social - LinkedIn | E15: Customer + Prospect | F15: Q4 Roadmap Webinar | G15: Webinar promo post series | H15: Promote all three regional sessions. | I15: Regional registration pages | J15: EN | K15: Social followers | L15: N/A | M15: N/A | O15: 46310 | P15: 12:00 | Q15: ET | R15: Weekly | S15: 1 of 3 | T15: =IF(OR($O15="",$D15=""),"",WORKDAY($O15,-IFERROR(VLOOKUP($D15,'Rules & Guardrails'!$A$9:$D$24,3,0),10))) -> 46307 | U15: Dean (Digital) | V15: Digital | W15: Head of Marketing (Global) | X15: Regional Heads | Y15: Approved | Z15: Yes | AA15: N/A | AB15: No | AE15: Scheduled | AF15: =IF($O15="","",IF(OR($AE15="Cancelled",$AE15="On hold",$AE15="Launched"),$AE15,IF(AND($Y15="Approved",OR($Z15="Yes",$Z15="N/A"),OR($AA15="Yes",$AA15="N/A"),OR($AB15="No",$AB15="N/A",AND($AB15="Yes",$AD15="Yes"))),"Ready",IF($O15<TODAY(),"Overdue",IF($O15-TODAY()<='Rules & Guardrails'!$C$5,"At Risk","In Progress"))))) -> Ready | AG15: =IF($O15="","",IF(OR($AE15="Launched",$AE15="Cancelled"),"",MID(IF($Y15<>"Approved",", Content approval","")&IF(NOT(OR($Z15="Yes",$Z15="N/A")),", Assets","")&IF(NOT(OR($AA15="Yes",$AA15="N/A")),", List","")&IF($AB15="",", Ops decision",IF(AND($AB15="Yes",$AD15<>"Yes"),", Ops",""))&IF($U15="",", Owner","")&IF($K15="",", Segment",""),3,200))) | AH15: =IF($O15="","",$O15-TODAY()) -> 7 | AI15: =IF($O15="","",$O15-WEEKDAY($O15,3)) -> 46307 | AJ15: =IF($O15="","",DATE(YEAR($O15),MONTH($O15),1)) -> 46296 | AK15: =IF(OR($O15="",$K15=""),"",COUNTIFS('Comms Calendar'!$K$5:$K$504,$K15,'Comms Calendar'!$B$5:$B$504,$B15,'Comms Calendar'!$AI$5:$AI$504,$AI15,'Comms Calendar'!$AE$5:$AE$504,"<>Cancelled")) -> 1 | AL15: =IF($AK15="","",IF($AK15>'Rules & Guardrails'!$C$3,"Over cap","OK")) -> OK | AM15: =IF(OR($O15="",$K15=""),"",IF(COUNTIFS('Comms Calendar'!$K$5:$K$504,$K15,'Comms Calendar'!$B$5:$B$504,$B15,'Comms Calendar'!$O$5:$O$504,$O15,'Comms Calendar'!$AE$5:$AE$504,"<>Cancelled")>1,"Clash","")) | AN15: =IF($O15="","",IF(IF($B15="Global",COUNTIF('Rules & Guardrails'!$F$9:$F$60,$O15),COUNTIFS('Rules & Guardrails'!$F$9:$F$60,$O15,'Rules & Guardrails'!$G$9:$G$60,$B15)+COUNTIFS('Rules & Guardrails'!$F$9:$F$60,$O15,'Rules & Guardrails'!$G$9:$G$60,"Global"))>0,"Blackout","")) | AO15: Regional versions posted in local time zones. | AP15: 46303 | AQ15: Draft (example) | AR15: =IF($D15="","",IFERROR(VLOOKUP($D15,'Rules & Guardrails'!$A$9:$D$24,2,0),"Other")) -> Social | AS15: =IF($O15="","",$O15&"|"&$B15) -> 46310|Global
A16: GL-003 | B16: Global | C16: All | D16: Press Release / PR | E16: Customer + Prospect | F16: Winter Product Launch | G16: Announcing our Winter release | H16: Headline launch - embargo until 17 Nov 08:00 ET. | I16: /winter-release | J16: EN | K16: Media + public | L16: Press list | O16: 46343 | P16: 08:00 | Q16: ET | R16: One-off | T16: =IF(OR($O16="",$D16=""),"",WORKDAY($O16,-IFERROR(VLOOKUP($D16,'Rules & Guardrails'!$A$9:$D$24,3,0),10))) -> 46322 | U16: Head of Marketing (Global) | V16: Comms / PR | W16: Head of Marketing (Global) | X16: All regions; Sales; CS; Exec team | Y16: Drafting | Z16: No | AA16: N/A | AB16: No | AE16: Planned | AF16: =IF($O16="","",IF(OR($AE16="Cancelled",$AE16="On hold",$AE16="Launched"),$AE16,IF(AND($Y16="Approved",OR($Z16="Yes",$Z16="N/A"),OR($AA16="Yes",$AA16="N/A"),OR($AB16="No",$AB16="N/A",AND($AB16="Yes",$AD16="Yes"))),"Ready",IF($O16<TODAY(),"Overdue",IF($O16-TODAY()<='Rules & Guardrails'!$C$5,"At Risk","In Progress"))))) -> In Progress | AG16: =IF($O16="","",IF(OR($AE16="Launched",$AE16="Cancelled"),"",MID(IF($Y16<>"Approved",", Content approval","")&IF(NOT(OR($Z16="Yes",$Z16="N/A")),", Assets","")&IF(NOT(OR($AA16="Yes",$AA16="N/A")),", List","")&IF($AB16="",", Ops decision",IF(AND($AB16="Yes",$AD16<>"Yes"),", Ops",""))&IF($U16="",", Owner","")&IF($K16="",", Segment",""),3,200))) -> Content approval, Assets | AH16: =IF($O16="","",$O16-TODAY()) -> 40 | AI16: =IF($O16="","",$O16-WEEKDAY($O16,3)) -> 46342 | AJ16: =IF($O16="","",DATE(YEAR($O16),MONTH($O16),1)) -> 46327 | AK16: =IF(OR($O16="",$K16=""),"",COUNTIFS('Comms Calendar'!$K$5:$K$504,$K16,'Comms Calendar'!$B$5:$B$504,$B16,'Comms Calendar'!$AI$5:$AI$504,$AI16,'Comms Calendar'!$AE$5:$AE$504,"<>Cancelled")) -> 1 | AL16: =IF($AK16="","",IF($AK16>'Rules & Guardrails'!$C$3,"Over cap","OK")) -> OK | AM16: =IF(OR($O16="",$K16=""),"",IF(COUNTIFS('Comms Calendar'!$K$5:$K$504,$K16,'Comms Calendar'!$B$5:$B$504,$B16,'Comms Calendar'!$O$5:$O$504,$O16,'Comms Calendar'!$AE$5:$AE$504,"<>Cancelled")>1,"Clash","")) | AN16: =IF($O16="","",IF(IF($B16="Global",COUNTIF('Rules & Guardrails'!$F$9:$F$60,$O16),COUNTIFS('Rules & Guardrails'!$F$9:$F$60,$O16,'Rules & Guardrails'!$G$9:$G$60,$B16)+COUNTIFS('Rules & Guardrails'!$F$9:$F$60,$O16,'Rules & Guardrails'!$G$9:$G$60,"Global"))>0,"Blackout","")) | AO16: All launch comms on 17 Nov must wait for the embargo. | AP16: 46303 | AQ16: Draft (example) | AR16: =IF($D16="","",IFERROR(VLOOKUP($D16,'Rules & Guardrails'!$A$9:$D$24,2,0),"Other")) -> PR | AS16: =IF($O16="","",$O16&"|"&$B16) -> 46343|Global
A17: GL-004 | B17: Global | C17: All | D17: In-app / Product Message | E17: Customer | F17: Winter Product Launch | G17: What's new: Winter release | H17: In-product banner pointing to the release notes. | I17: Release notes | J17: Multi | K17: All Customers | L17: All active users | N17: 60000 | O17: 46343 | P17: 09:00 | Q17: ET | R17: One-off | T17: =IF(OR($O17="",$D17=""),"",WORKDAY($O17,-IFERROR(VLOOKUP($D17,'Rules & Guardrails'!$A$9:$D$24,3,0),10))) -> 46329 | U17: Product Marketing | V17: Product Marketing | W17: Head of Marketing (Global) | X17: Product; Support | Y17: Not started | Z17: No | AA17: N/A | AB17: No | AE17: Planned | AF17: =IF($O17="","",IF(OR($AE17="Cancelled",$AE17="On hold",$AE17="Launched"),$AE17,IF(AND($Y17="Approved",OR($Z17="Yes",$Z17="N/A"),OR($AA17="Yes",$AA17="N/A"),OR($AB17="No",$AB17="N/A",AND($AB17="Yes",$AD17="Yes"))),"Ready",IF($O17<TODAY(),"Overdue",IF($O17-TODAY()<='Rules & Guardrails'!$C$5,"At Risk","In Progress"))))) -> In Progress | AG17: =IF($O17="","",IF(OR($AE17="Launched",$AE17="Cancelled"),"",MID(IF($Y17<>"Approved",", Content approval","")&IF(NOT(OR($Z17="Yes",$Z17="N/A")),", Assets","")&IF(NOT(OR($AA17="Yes",$AA17="N/A")),", List","")&IF($AB17="",", Ops decision",IF(AND($AB17="Yes",$AD17<>"Yes"),", Ops",""))&IF($U17="",", Owner","")&IF($K17="",", Segment",""),3,200))) -> Content approval, Assets | AH17: =IF($O17="","",$O17-TODAY()) -> 40 | AI17: =IF($O17="","",$O17-WEEKDAY($O17,3)) -> 46342 | AJ17: =IF($O17="","",DATE(YEAR($O17),MONTH($O17),1)) -> 46327 | AK17: =IF(OR($O17="",$K17=""),"",COUNTIFS('Comms Calendar'!$K$5:$K$504,$K17,'Comms Calendar'!$B$5:$B$504,$B17,'Comms Calendar'!$AI$5:$AI$504,$AI17,'Comms Calendar'!$AE$5:$AE$504,"<>Cancelled")) -> 1 | AL17: =IF($AK17="","",IF($AK17>'Rules & Guardrails'!$C$3,"Over cap","OK")) -> OK | AM17: =IF(OR($O17="",$K17=""),"",IF(COUNTIFS('Comms Calendar'!$K$5:$K$504,$K17,'Comms Calendar'!$B$5:$B$504,$B17,'Comms Calendar'!$O$5:$O$504,$O17,'Comms Calendar'!$AE$5:$AE$504,"<>Cancelled")>1,"Clash","")) | AN17: =IF($O17="","",IF(IF($B17="Global",COUNTIF('Rules & Guardrails'!$F$9:$F$60,$O17),COUNTIFS('Rules & Guardrails'!$F$9:$F$60,$O17,'Rules & Guardrails'!$G$9:$G$60,$B17)+COUNTIFS('Rules & Guardrails'!$F$9:$F$60,$O17,'Rules & Guardrails'!$G$9:$G$60,"Global"))>0,"Blackout","")) | AP17: 46303 | AQ17: Draft (example) | AR17: =IF($D17="","",IFERROR(VLOOKUP($D17,'Rules & Guardrails'!$A$9:$D$24,2,0),"Other")) -> In-app | AS17: =IF($O17="","",$O17&"|"&$B17) -> 46343|Global
A18: AM-005 | B18: AMER | C18: US | D18: Email - Campaign / Nurture | E18: Prospect | F18: Holiday Promo | G18: Year-end offer for new teams | H18: Annual plan incentive before 31 Dec. | I18: Talk to sales | J18: EN | K18: AMER Prospects - Engaged 90d | L18: AMER Prospects - Engaged 90d | M18: Customers; Open opportunities | N18: 6400 | O18: 46353 | P18: 10:00 | Q18: ET | R18: One-off | T18: =IF(OR($O18="",$D18=""),"",WORKDAY($O18,-IFERROR(VLOOKUP($D18,'Rules & Guardrails'!$A$9:$D$24,3,0),10))) -> 46339 | U18: Head of Mkt AMER | V18: Digital | W18: Head of Marketing (Global) | X18: AMER Sales | Y18: Not started | Z18: No | AA18: No | AB18: Yes | AE18: Planned | AF18: =IF($O18="","",IF(OR($AE18="Cancelled",$AE18="On hold",$AE18="Launched"),$AE18,IF(AND($Y18="Approved",OR($Z18="Yes",$Z18="N/A"),OR($AA18="Yes",$AA18="N/A"),OR($AB18="No",$AB18="N/A",AND($AB18="Yes",$AD18="Yes"))),"Ready",IF($O18<TODAY(),"Overdue",IF($O18-TODAY()<='Rules & Guardrails'!$C$5,"At Risk","In Progress"))))) -> In Progress | AG18: =IF($O18="","",IF(OR($AE18="Launched",$AE18="Cancelled"),"",MID(IF($Y18<>"Approved",", Content approval","")&IF(NOT(OR($Z18="Yes",$Z18="N/A")),", Assets","")&IF(NOT(OR($AA18="Yes",$AA18="N/A")),", List","")&IF($AB18="",", Ops decision",IF(AND($AB18="Yes",$AD18<>"Yes"),", Ops",""))&IF($U18="",", Owner","")&IF($K18="",", Segment",""),3,200))) -> Content approval, Assets, List, Ops | AH18: =IF($O18="","",$O18-TODAY()) -> 50 | AI18: =IF($O18="","",$O18-WEEKDAY($O18,3)) -> 46349 | AJ18: =IF($O18="","",DATE(YEAR($O18),MONTH($O18),1)) -> 46327 | AK18: =IF(OR($O18="",$K18=""),"",COUNTIFS('Comms Calendar'!$K$5:$K$504,$K18,'Comms Calendar'!$B$5:$B$504,$B18,'Comms Calendar'!$AI$5:$AI$504,$AI18,'Comms Calendar'!$AE$5:$AE$504,"<>Cancelled")) -> 1 | AL18: =IF($AK18="","",IF($AK18>'Rules & Guardrails'!$C$3,"Over cap","OK")) -> OK | AM18: =IF(OR($O18="",$K18=""),"",IF(COUNTIFS('Comms Calendar'!$K$5:$K$504,$K18,'Comms Calendar'!$B$5:$B$504,$B18,'Comms Calendar'!$O$5:$O$504,$O18,'Comms Calendar'!$AE$5:$AE$504,"<>Cancelled")>1,"Clash","")) | AN18: =IF($O18="","",IF(IF($B18="Global",COUNTIF('Rules & Guardrails'!$F$9:$F$60,$O18),COUNTIFS('Rules & Guardrails'!$F$9:$F$60,$O18,'Rules & Guardrails'!$G$9:$G$60,$B18)+COUNTIFS('Rules & Guardrails'!$F$9:$F$60,$O18,'Rules & Guardrails'!$G$9:$G$60,"Global"))>0,"Blackout","")) -> Blackout | AO18: EXAMPLE: falls on a blackout date. | AP18: 46303 | AQ18: Draft (example) | AR18: =IF($D18="","",IFERROR(VLOOKUP($D18,'Rules & Guardrails'!$A$9:$D$24,2,0),"Other")) -> Email | AS18: =IF($O18="","",$O18&"|"&$B18) -> 46353|AMER
A19: GL-005 | B19: Global | C19: All | D19: Email - Newsletter | E19: Customer | F19: Customer Newsletter | G19: Season's greetings & year in review | H19: Thank-you note + 2026 highlights. | I19: Year in review page | J19: Multi | K19: All Customers | L19: All Customers - Active | M19: Unsubscribed | N19: 21000 | O19: 46371 | P19: 10:00 | Q19: ET | R19: One-off | T19: =IF(OR($O19="",$D19=""),"",WORKDAY($O19,-IFERROR(VLOOKUP($D19,'Rules & Guardrails'!$A$9:$D$24,3,0),10))) -> 46357 | U19: Head of Marketing (Global) | V19: Digital | W19: Head of Marketing (Global) | X19: All regions | Y19: Not started | Z19: No | AA19: Yes | AB19: Yes | AE19: Planned | AF19: =IF($O19="","",IF(OR($AE19="Cancelled",$AE19="On hold",$AE19="Launched"),$AE19,IF(AND($Y19="Approved",OR($Z19="Yes",$Z19="N/A"),OR($AA19="Yes",$AA19="N/A"),OR($AB19="No",$AB19="N/A",AND($AB19="Yes",$AD19="Yes"))),"Ready",IF($O19<TODAY(),"Overdue",IF($O19-TODAY()<='Rules & Guardrails'!$C$5,"At Risk","In Progress"))))) -> In Progress | AG19: =IF($O19="","",IF(OR($AE19="Launched",$AE19="Cancelled"),"",MID(IF($Y19<>"Approved",", Content approval","")&IF(NOT(OR($Z19="Yes",$Z19="N/A")),", Assets","")&IF(NOT(OR($AA19="Yes",$AA19="N/A")),", List","")&IF($AB19="",", Ops decision",IF(AND($AB19="Yes",$AD19<>"Yes"),", Ops",""))&IF($U19="",", Owner","")&IF($K19="",", Segment",""),3,200))) -> Content approval, Assets, Ops | AH19: =IF($O19="","",$O19-TODAY()) -> 68 | AI19: =IF($O19="","",$O19-WEEKDAY($O19,3)) -> 46370 | AJ19: =IF($O19="","",DATE(YEAR($O19),MONTH($O19),1)) -> 46357 | AK19: =IF(OR($O19="",$K19=""),"",COUNTIFS('Comms Calendar'!$K$5:$K$504,$K19,'Comms Calendar'!$B$5:$B$504,$B19,'Comms Calendar'!$AI$5:$AI$504,$AI19,'Comms Calendar'!$AE$5:$AE$504,"<>Cancelled")) -> 1 | AL19: =IF($AK19="","",IF($AK19>'Rules & Guardrails'!$C$3,"Over cap","OK")) -> OK | AM19: =IF(OR($O19="",$K19=""),"",IF(COUNTIFS('Comms Calendar'!$K$5:$K$504,$K19,'Comms Calendar'!$B$5:$B$504,$B19,'Comms Calendar'!$O$5:$O$504,$O19,'Comms Calendar'!$AE$5:$AE$504,"<>Cancelled")>1,"Clash","")) | AN19: =IF($O19="","",IF(IF($B19="Global",COUNTIF('Rules & Guardrails'!$F$9:$F$60,$O19),COUNTIFS('Rules & Guardrails'!$F$9:$F$60,$O19,'Rules & Guardrails'!$G$9:$G$60,$B19)+COUNTIFS('Rules & Guardrails'!$F$9:$F$60,$O19,'Rules & Guardrails'!$G$9:$G$60,"Global"))>0,"Blackout","")) | AP19: 46303 | AQ19: Draft (example) | AR19: =IF($D19="","",IFERROR(VLOOKUP($D19,'Rules & Guardrails'!$A$9:$D$24,2,0),"Other")) -> Email | AS19: =IF($O19="","",$O19&"|"&$B19) -> 46371|Global
T20: =IF(OR($O20="",$D20=""),"",WORKDAY($O20,-IFERROR(VLOOKUP($D20,'Rules & Guardrails'!$A$9:$D$24,3,0),10))) | AF20: =IF($O20="","",IF(OR($AE20="Cancelled",$AE20="On hold",$AE20="Launched"),$AE20,IF(AND($Y20="Approved",OR($Z20="Yes",$Z20="N/A"),OR($AA20="Yes",$AA20="N/A"),OR($AB20="No",$AB20="N/A",AND($AB20="Yes",$AD20="Yes"))),"Ready",IF($O20<TODAY(),"Overdue",IF($O20-TODAY()<='Rules & Guardrails'!$C$5,"At Risk","In Progress"))))) | AG20: =IF($O20="","",IF(OR($AE20="Launched",$AE20="Cancelled"),"",MID(IF($Y20<>"Approved",", Content approval","")&IF(NOT(OR($Z20="Yes",$Z20="N/A")),", Assets","")&IF(NOT(OR($AA20="Yes",$AA20="N/A")),", List","")&IF($AB20="",", Ops decision",IF(AND($AB20="Yes",$AD20<>"Yes"),", Ops",""))&IF($U20="",", Owner","")&IF($K20="",", Segment",""),3,200))) | AH20: =IF($O20="","",$O20-TODAY()) | AI20: =IF($O20="","",$O20-WEEKDAY($O20,3)) | AJ20: =IF($O20="","",DATE(YEAR($O20),MONTH($O20),1)) | AK20: =IF(OR($O20="",$K20=""),"",COUNTIFS('Comms Calendar'!$K$5:$K$504,$K20,'Comms Calendar'!$B$5:$B$504,$B20,'Comms Calendar'!$AI$5:$AI$504,$AI20,'Comms Calendar'!$AE$5:$AE$504,"<>Cancelled")) | AL20: =IF($AK20="","",IF($AK20>'Rules & Guardrails'!$C$3,"Over cap","OK")) | AM20: =IF(OR($O20="",$K20=""),"",IF(COUNTIFS('Comms Calendar'!$K$5:$K$504,$K20,'Comms Calendar'!$B$5:$B$504,$B20,'Comms Calendar'!$O$5:$O$504,$O20,'Comms Calendar'!$AE$5:$AE$504,"<>Cancelled")>1,"Clash","")) | AN20: =IF($O20="","",IF(IF($B20="Global",COUNTIF('Rules & Guardrails'!$F$9:$F$60,$O20),COUNTIFS('Rules & Guardrails'!$F$9:$F$60,$O20,'Rules & Guardrails'!$G$9:$G$60,$B20)+COUNTIFS('Rules & Guardrails'!$F$9:$F$60,$O20,'Rules & Guardrails'!$G$9:$G$60,"Global"))>0,"Blackout","")) | AR20: =IF($D20="","",IFERROR(VLOOKUP($D20,'Rules & Guardrails'!$A$9:$D$24,2,0),"Other")) | AS20: =IF($O20="","",$O20&"|"&$B20)
T21: =IF(OR($O21="",$D21=""),"",WORKDAY($O21,-IFERROR(VLOOKUP($D21,'Rules & Guardrails'!$A$9:$D$24,3,0),10))) | AF21: =IF($O21="","",IF(OR($AE21="Cancelled",$AE21="On hold",$AE21="Launched"),$AE21,IF(AND($Y21="Approved",OR($Z21="Yes",$Z21="N/A"),OR($AA21="Yes",$AA21="N/A"),OR($AB21="No",$AB21="N/A",AND($AB21="Yes",$AD21="Yes"))),"Ready",IF($O21<TODAY(),"Overdue",IF($O21-TODAY()<='Rules & Guardrails'!$C$5,"At Risk","In Progress"))))) | AG21: =IF($O21="","",IF(OR($AE21="Launched",$AE21="Cancelled"),"",MID(IF($Y21<>"Approved",", Content approval","")&IF(NOT(OR($Z21="Yes",$Z21="N/A")),", Assets","")&IF(NOT(OR($AA21="Yes",$AA21="N/A")),", List","")&IF($AB21="",", Ops decision",IF(AND($AB21="Yes",$AD21<>"Yes"),", Ops",""))&IF($U21="",", Owner","")&IF($K21="",", Segment",""),3,200))) | AH21: =IF($O21="","",$O21-TODAY()) | AI21: =IF($O21="","",$O21-WEEKDAY($O21,3)) | AJ21: =IF($O21="","",DATE(YEAR($O21),MONTH($O21),1)) | AK21: =IF(OR($O21="",$K21=""),"",COUNTIFS('Comms Calendar'!$K$5:$K$504,$K21,'Comms Calendar'!$B$5:$B$504,$B21,'Comms Calendar'!$AI$5:$AI$504,$AI21,'Comms Calendar'!$AE$5:$AE$504,"<>Cancelled")) | AL21: =IF($AK21="","",IF($AK21>'Rules & Guardrails'!$C$3,"Over cap","OK")) | AM21: =IF(OR($O21="",$K21=""),"",IF(COUNTIFS('Comms Calendar'!$K$5:$K$504,$K21,'Comms Calendar'!$B$5:$B$504,$B21,'Comms Calendar'!$O$5:$O$504,$O21,'Comms Calendar'!$AE$5:$AE$504,"<>Cancelled")>1,"Clash","")) | AN21: =IF($O21="","",IF(IF($B21="Global",COUNTIF('Rules & Guardrails'!$F$9:$F$60,$O21),COUNTIFS('Rules & Guardrails'!$F$9:$F$60,$O21,'Rules & Guardrails'!$G$9:$G$60,$B21)+COUNTIFS('Rules & Guardrails'!$F$9:$F$60,$O21,'Rules & Guardrails'!$G$9:$G$60,"Global"))>0,"Blackout","")) | AR21: =IF($D21="","",IFERROR(VLOOKUP($D21,'Rules & Guardrails'!$A$9:$D$24,2,0),"Other")) | AS21: =IF($O21="","",$O21&"|"&$B21)
T22: =IF(OR($O22="",$D22=""),"",WORKDAY($O22,-IFERROR(VLOOKUP($D22,'Rules & Guardrails'!$A$9:$D$24,3,0),10))) | AF22: =IF($O22="","",IF(OR($AE22="Cancelled",$AE22="On hold",$AE22="Launched"),$AE22,IF(AND($Y22="Approved",OR($Z22="Yes",$Z22="N/A"),OR($AA22="Yes",$AA22="N/A"),OR($AB22="No",$AB22="N/A",AND($AB22="Yes",$AD22="Yes"))),"Ready",IF($O22<TODAY(),"Overdue",IF($O22-TODAY()<='Rules & Guardrails'!$C$5,"At Risk","In Progress"))))) | AG22: =IF($O22="","",IF(OR($AE22="Launched",$AE22="Cancelled"),"",MID(IF($Y22<>"Approved",", Content approval","")&IF(NOT(OR($Z22="Yes",$Z22="N/A")),", Assets","")&IF(NOT(OR($AA22="Yes",$AA22="N/A")),", List","")&IF($AB22="",", Ops decision",IF(AND($AB22="Yes",$AD22<>"Yes"),", Ops",""))&IF($U22="",", Owner","")&IF($K22="",", Segment",""),3,200))) | AH22: =IF($O22="","",$O22-TODAY()) | AI22: =IF($O22="","",$O22-WEEKDAY($O22,3)) | AJ22: =IF($O22="","",DATE(YEAR($O22),MONTH($O22),1)) | AK22: =IF(OR($O22="",$K22=""),"",COUNTIFS('Comms Calendar'!$K$5:$K$504,$K22,'Comms Calendar'!$B$5:$B$504,$B22,'Comms Calendar'!$AI$5:$AI$504,$AI22,'Comms Calendar'!$AE$5:$AE$504,"<>Cancelled")) | AL22: =IF($AK22="","",IF($AK22>'Rules & Guardrails'!$C$3,"Over cap","OK")) | AM22: =IF(OR($O22="",$K22=""),"",IF(COUNTIFS('Comms Calendar'!$K$5:$K$504,$K22,'Comms Calendar'!$B$5:$B$504,$B22,'Comms Calendar'!$O$5:$O$504,$O22,'Comms Calendar'!$AE$5:$AE$504,"<>Cancelled")>1,"Clash","")) | AN22: =IF($O22="","",IF(IF($B22="Global",COUNTIF('Rules & Guardrails'!$F$9:$F$60,$O22),COUNTIFS('Rules & Guardrails'!$F$9:$F$60,$O22,'Rules & Guardrails'!$G$9:$G$60,$B22)+COUNTIFS('Rules & Guardrails'!$F$9:$F$60,$O22,'Rules & Guardrails'!$G$9:$G$60,"Global"))>0,"Blackout","")) | AR22: =IF($D22="","",IFERROR(VLOOKUP($D22,'Rules & Guardrails'!$A$9:$D$24,2,0),"Other")) | AS22: =IF($O22="","",$O22&"|"&$B22)
T23: =IF(OR($O23="",$D23=""),"",WORKDAY($O23,-IFERROR(VLOOKUP($D23,'Rules & Guardrails'!$A$9:$D$24,3,0),10))) | AF23: =IF($O23="","",IF(OR($AE23="Cancelled",$AE23="On hold",$AE23="Launched"),$AE23,IF(AND($Y23="Approved",OR($Z23="Yes",$Z23="N/A"),OR($AA23="Yes",$AA23="N/A"),OR($AB23="No",$AB23="N/A",AND($AB23="Yes",$AD23="Yes"))),"Ready",IF($O23<TODAY(),"Overdue",IF($O23-TODAY()<='Rules & Guardrails'!$C$5,"At Risk","In Progress"))))) | AG23: =IF($O23="","",IF(OR($AE23="Launched",$AE23="Cancelled"),"",MID(IF($Y23<>"Approved",", Content approval","")&IF(NOT(OR($Z23="Yes",$Z23="N/A")),", Assets","")&IF(NOT(OR($AA23="Yes",$AA23="N/A")),", List","")&IF($AB23="",", Ops decision",IF(AND($AB23="Yes",$AD23<>"Yes"),", Ops",""))&IF($U23="",", Owner","")&IF($K23="",", Segment",""),3,200))) | AH23: =IF($O23="","",$O23-TODAY()) | AI23: =IF($O23="","",$O23-WEEKDAY($O23,3)) | AJ23: =IF($O23="","",DATE(YEAR($O23),MONTH($O23),1)) | AK23: =IF(OR($O23="",$K23=""),"",COUNTIFS('Comms Calendar'!$K$5:$K$504,$K23,'Comms Calendar'!$B$5:$B$504,$B23,'Comms Calendar'!$AI$5:$AI$504,$AI23,'Comms Calendar'!$AE$5:$AE$504,"<>Cancelled")) | AL23: =IF($AK23="","",IF($AK23>'Rules & Guardrails'!$C$3,"Over cap","OK")) | AM23: =IF(OR($O23="",$K23=""),"",IF(COUNTIFS('Comms Calendar'!$K$5:$K$504,$K23,'Comms Calendar'!$B$5:$B$504,$B23,'Comms Calendar'!$O$5:$O$504,$O23,'Comms Calendar'!$AE$5:$AE$504,"<>Cancelled")>1,"Clash","")) | AN23: =IF($O23="","",IF(IF($B23="Global",COUNTIF('Rules & Guardrails'!$F$9:$F$60,$O23),COUNTIFS('Rules & Guardrails'!$F$9:$F$60,$O23,'Rules & Guardrails'!$G$9:$G$60,$B23)+COUNTIFS('Rules & Guardrails'!$F$9:$F$60,$O23,'Rules & Guardrails'!$G$9:$G$60,"Global"))>0,"Blackout","")) | AR23: =IF($D23="","",IFERROR(VLOOKUP($D23,'Rules & Guardrails'!$A$9:$D$24,2,0),"Other")) | AS23: =IF($O23="","",$O23&"|"&$B23)
T24: =IF(OR($O24="",$D24=""),"",WORKDAY($O24,-IFERROR(VLOOKUP($D24,'Rules & Guardrails'!$A$9:$D$24,3,0),10))) | AF24: =IF($O24="","",IF(OR($AE24="Cancelled",$AE24="On hold",$AE24="Launched"),$AE24,IF(AND($Y24="Approved",OR($Z24="Yes",$Z24="N/A"),OR($AA24="Yes",$AA24="N/A"),OR($AB24="No",$AB24="N/A",AND($AB24="Yes",$AD24="Yes"))),"Ready",IF($O24<TODAY(),"Overdue",IF($O24-TODAY()<='Rules & Guardrails'!$C$5,"At Risk","In Progress"))))) | AG24: =IF($O24="","",IF(OR($AE24="Launched",$AE24="Cancelled"),"",MID(IF($Y24<>"Approved",", Content approval","")&IF(NOT(OR($Z24="Yes",$Z24="N/A")),", Assets","")&IF(NOT(OR($AA24="Yes",$AA24="N/A")),", List","")&IF($AB24="",", Ops decision",IF(AND($AB24="Yes",$AD24<>"Yes"),", Ops",""))&IF($U24="",", Owner","")&IF($K24="",", Segment",""),3,200))) | AH24: =IF($O24="","",$O24-TODAY()) | AI24: =IF($O24="","",$O24-WEEKDAY($O24,3)) | AJ24: =IF($O24="","",DATE(YEAR($O24),MONTH($O24),1)) | AK24: =IF(OR($O24="",$K24=""),"",COUNTIFS('Comms Calendar'!$K$5:$K$504,$K24,'Comms Calendar'!$B$5:$B$504,$B24,'Comms Calendar'!$AI$5:$AI$504,$AI24,'Comms Calendar'!$AE$5:$AE$504,"<>Cancelled")) | AL24: =IF($AK24="","",IF($AK24>'Rules & Guardrails'!$C$3,"Over cap","OK")) | AM24: =IF(OR($O24="",$K24=""),"",IF(COUNTIFS('Comms Calendar'!$K$5:$K$504,$K24,'Comms Calendar'!$B$5:$B$504,$B24,'Comms Calendar'!$O$5:$O$504,$O24,'Comms Calendar'!$AE$5:$AE$504,"<>Cancelled")>1,"Clash","")) | AN24: =IF($O24="","",IF(IF($B24="Global",COUNTIF('Rules & Guardrails'!$F$9:$F$60,$O24),COUNTIFS('Rules & Guardrails'!$F$9:$F$60,$O24,'Rules & Guardrails'!$G$9:$G$60,$B24)+COUNTIFS('Rules & Guardrails'!$F$9:$F$60,$O24,'Rules & Guardrails'!$G$9:$G$60,"Global"))>0,"Blackout","")) | AR24: =IF($D24="","",IFERROR(VLOOKUP($D24,'Rules & Guardrails'!$A$9:$D$24,2,0),"Other")) | AS24: =IF($O24="","",$O24&"|"&$B24)
T25: =IF(OR($O25="",$D25=""),"",WORKDAY($O25,-IFERROR(VLOOKUP($D25,'Rules & Guardrails'!$A$9:$D$24,3,0),10))) | AF25: =IF($O25="","",IF(OR($AE25="Cancelled",$AE25="On hold",$AE25="Launched"),$AE25,IF(AND($Y25="Approved",OR($Z25="Yes",$Z25="N/A"),OR($AA25="Yes",$AA25="N/A"),OR($AB25="No",$AB25="N/A",AND($AB25="Yes",$AD25="Yes"))),"Ready",IF($O25<TODAY(),"Overdue",IF($O25-TODAY()<='Rules & Guardrails'!$C$5,"At Risk","In Progress"))))) | AG25: =IF($O25="","",IF(OR($AE25="Launched",$AE25="Cancelled"),"",MID(IF($Y25<>"Approved",", Content approval","")&IF(NOT(OR($Z25="Yes",$Z25="N/A")),", Assets","")&IF(NOT(OR($AA25="Yes",$AA25="N/A")),", List","")&IF($AB25="",", Ops decision",IF(AND($AB25="Yes",$AD25<>"Yes"),", Ops",""))&IF($U25="",", Owner","")&IF($K25="",", Segment",""),3,200))) | AH25: =IF($O25="","",$O25-TODAY()) | AI25: =IF($O25="","",$O25-WEEKDAY($O25,3)) | AJ25: =IF($O25="","",DATE(YEAR($O25),MONTH($O25),1)) | AK25: =IF(OR($O25="",$K25=""),"",COUNTIFS('Comms Calendar'!$K$5:$K$504,$K25,'Comms Calendar'!$B$5:$B$504,$B25,'Comms Calendar'!$AI$5:$AI$504,$AI25,'Comms Calendar'!$AE$5:$AE$504,"<>Cancelled")) | AL25: =IF($AK25="","",IF($AK25>'Rules & Guardrails'!$C$3,"Over cap","OK")) | AM25: =IF(OR($O25="",$K25=""),"",IF(COUNTIFS('Comms Calendar'!$K$5:$K$504,$K25,'Comms Calendar'!$B$5:$B$504,$B25,'Comms Calendar'!$O$5:$O$504,$O25,'Comms Calendar'!$AE$5:$AE$504,"<>Cancelled")>1,"Clash","")) | AN25: =IF($O25="","",IF(IF($B25="Global",COUNTIF('Rules & Guardrails'!$F$9:$F$60,$O25),COUNTIFS('Rules & Guardrails'!$F$9:$F$60,$O25,'Rules & Guardrails'!$G$9:$G$60,$B25)+COUNTIFS('Rules & Guardrails'!$F$9:$F$60,$O25,'Rules & Guardrails'!$G$9:$G$60,"Global"))>0,"Blackout","")) | AR25: =IF($D25="","",IFERROR(VLOOKUP($D25,'Rules & Guardrails'!$A$9:$D$24,2,0),"Other")) | AS25: =IF($O25="","",$O25&"|"&$B25)
T26: =IF(OR($O26="",$D26=""),"",WORKDAY($O26,-IFERROR(VLOOKUP($D26,'Rules & Guardrails'!$A$9:$D$24,3,0),10))) | AF26: =IF($O26="","",IF(OR($AE26="Cancelled",$AE26="On hold",$AE26="Launched"),$AE26,IF(AND($Y26="Approved",OR($Z26="Yes",$Z26="N/A"),OR($AA26="Yes",$AA26="N/A"),OR($AB26="No",$AB26="N/A",AND($AB26="Yes",$AD26="Yes"))),"Ready",IF($O26<TODAY(),"Overdue",IF($O26-TODAY()<='Rules & Guardrails'!$C$5,"At Risk","In Progress"))))) | AG26: =IF($O26="","",IF(OR($AE26="Launched",$AE26="Cancelled"),"",MID(IF($Y26<>"Approved",", Content approval","")&IF(NOT(OR($Z26="Yes",$Z26="N/A")),", Assets","")&IF(NOT(OR($AA26="Yes",$AA26="N/A")),", List","")&IF($AB26="",", Ops decision",IF(AND($AB26="Yes",$AD26<>"Yes"),", Ops",""))&IF($U26="",", Owner","")&IF($K26="",", Segment",""),3,200))) | AH26: =IF($O26="","",$O26-TODAY()) | AI26: =IF($O26="","",$O26-WEEKDAY($O26,3)) | AJ26: =IF($O26="","",DATE(YEAR($O26),MONTH($O26),1)) | AK26: =IF(OR($O26="",$K26=""),"",COUNTIFS('Comms Calendar'!$K$5:$K$504,$K26,'Comms Calendar'!$B$5:$B$504,$B26,'Comms Calendar'!$AI$5:$AI$504,$AI26,'Comms Calendar'!$AE$5:$AE$504,"<>Cancelled")) | AL26: =IF($AK26="","",IF($AK26>'Rules & Guardrails'!$C$3,"Over cap","OK")) | AM26: =IF(OR($O26="",$K26=""),"",IF(COUNTIFS('Comms Calendar'!$K$5:$K$504,$K26,'Comms Calendar'!$B$5:$B$504,$B26,'Comms Calendar'!$O$5:$O$504,$O26,'Comms Calendar'!$AE$5:$AE$504,"<>Cancelled")>1,"Clash","")) | AN26: =IF($O26="","",IF(IF($B26="Global",COUNTIF('Rules & Guardrails'!$F$9:$F$60,$O26),COUNTIFS('Rules & Guardrails'!$F$9:$F$60,$O26,'Rules & Guardrails'!$G$9:$G$60,$B26)+COUNTIFS('Rules & Guardrails'!$F$9:$F$60,$O26,'Rules & Guardrails'!$G$9:$G$60,"Global"))>0,"Blackout","")) | AR26: =IF($D26="","",IFERROR(VLOOKUP($D26,'Rules & Guardrails'!$A$9:$D$24,2,0),"Other")) | AS26: =IF($O26="","",$O26&"|"&$B26)
T27: =IF(OR($O27="",$D27=""),"",WORKDAY($O27,-IFERROR(VLOOKUP($D27,'Rules & Guardrails'!$A$9:$D$24,3,0),10))) | AF27: =IF($O27="","",IF(OR($AE27="Cancelled",$AE27="On hold",$AE27="Launched"),$AE27,IF(AND($Y27="Approved",OR($Z27="Yes",$Z27="N/A"),OR($AA27="Yes",$AA27="N/A"),OR($AB27="No",$AB27="N/A",AND($AB27="Yes",$AD27="Yes"))),"Ready",IF($O27<TODAY(),"Overdue",IF($O27-TODAY()<='Rules & Guardrails'!$C$5,"At Risk","In Progress"))))) | AG27: =IF($O27="","",IF(OR($AE27="Launched",$AE27="Cancelled"),"",MID(IF($Y27<>"Approved",", Content approval","")&IF(NOT(OR($Z27="Yes",$Z27="N/A")),", Assets","")&IF(NOT(OR($AA27="Yes",$AA27="N/A")),", List","")&IF($AB27="",", Ops decision",IF(AND($AB27="Yes",$AD27<>"Yes"),", Ops",""))&IF($U27="",", Owner","")&IF($K27="",", Segment",""),3,200))) | AH27: =IF($O27="","",$O27-TODAY()) | AI27: =IF($O27="","",$O27-WEEKDAY($O27,3)) | AJ27: =IF($O27="","",DATE(YEAR($O27),MONTH($O27),1)) | AK27: =IF(OR($O27="",$K27=""),"",COUNTIFS('Comms Calendar'!$K$5:$K$504,$K27,'Comms Calendar'!$B$5:$B$504,$B27,'Comms Calendar'!$AI$5:$AI$504,$AI27,'Comms Calendar'!$AE$5:$AE$504,"<>Cancelled")) | AL27: =IF($AK27="","",IF($AK27>'Rules & Guardrails'!$C$3,"Over cap","OK")) | AM27: =IF(OR($O27="",$K27=""),"",IF(COUNTIFS('Comms Calendar'!$K$5:$K$504,$K27,'Comms Calendar'!$B$5:$B$504,$B27,'Comms Calendar'!$O$5:$O$504,$O27,'Comms Calendar'!$AE$5:$AE$504,"<>Cancelled")>1,"Clash","")) | AN27: =IF($O27="","",IF(IF($B27="Global",COUNTIF('Rules & Guardrails'!$F$9:$F$60,$O27),COUNTIFS('Rules & Guardrails'!$F$9:$F$60,$O27,'Rules & Guardrails'!$G$9:$G$60,$B27)+COUNTIFS('Rules & Guardrails'!$F$9:$F$60,$O27,'Rules & Guardrails'!$G$9:$G$60,"Global"))>0,"Blackout","")) | AR27: =IF($D27="","",IFERROR(VLOOKUP($D27,'Rules & Guardrails'!$A$9:$D$24,2,0),"Other")) | AS27: =IF($O27="","",$O27&"|"&$B27)
T28: =IF(OR($O28="",$D28=""),"",WORKDAY($O28,-IFERROR(VLOOKUP($D28,'Rules & Guardrails'!$A$9:$D$24,3,0),10))) | AF28: =IF($O28="","",IF(OR($AE28="Cancelled",$AE28="On hold",$AE28="Launched"),$AE28,IF(AND($Y28="Approved",OR($Z28="Yes",$Z28="N/A"),OR($AA28="Yes",$AA28="N/A"),OR($AB28="No",$AB28="N/A",AND($AB28="Yes",$AD28="Yes"))),"Ready",IF($O28<TODAY(),"Overdue",IF($O28-TODAY()<='Rules & Guardrails'!$C$5,"At Risk","In Progress"))))) | AG28: =IF($O28="","",IF(OR($AE28="Launched",$AE28="Cancelled"),"",MID(IF($Y28<>"Approved",", Content approval","")&IF(NOT(OR($Z28="Yes",$Z28="N/A")),", Assets","")&IF(NOT(OR($AA28="Yes",$AA28="N/A")),", List","")&IF($AB28="",", Ops decision",IF(AND($AB28="Yes",$AD28<>"Yes"),", Ops",""))&IF($U28="",", Owner","")&IF($K28="",", Segment",""),3,200))) | AH28: =IF($O28="","",$O28-TODAY()) | AI28: =IF($O28="","",$O28-WEEKDAY($O28,3)) | AJ28: =IF($O28="","",DATE(YEAR($O28),MONTH($O28),1)) | AK28: =IF(OR($O28="",$K28=""),"",COUNTIFS('Comms Calendar'!$K$5:$K$504,$K28,'Comms Calendar'!$B$5:$B$504,$B28,'Comms Calendar'!$AI$5:$AI$504,$AI28,'Comms Calendar'!$AE$5:$AE$504,"<>Cancelled")) | AL28: =IF($AK28="","",IF($AK28>'Rules & Guardrails'!$C$3,"Over cap","OK")) | AM28: =IF(OR($O28="",$K28=""),"",IF(COUNTIFS('Comms Calendar'!$K$5:$K$504,$K28,'Comms Calendar'!$B$5:$B$504,$B28,'Comms Calendar'!$O$5:$O$504,$O28,'Comms Calendar'!$AE$5:$AE$504,"<>Cancelled")>1,"Clash","")) | AN28: =IF($O28="","",IF(IF($B28="Global",COUNTIF('Rules & Guardrails'!$F$9:$F$60,$O28),COUNTIFS('Rules & Guardrails'!$F$9:$F$60,$O28,'Rules & Guardrails'!$G$9:$G$60,$B28)+COUNTIFS('Rules & Guardrails'!$F$9:$F$60,$O28,'Rules & Guardrails'!$G$9:$G$60,"Global"))>0,"Blackout","")) | AR28: =IF($D28="","",IFERROR(VLOOKUP($D28,'Rules & Guardrails'!$A$9:$D$24,2,0),"Other")) | AS28: =IF($O28="","",$O28&"|"&$B28)
T29: =IF(OR($O29="",$D29=""),"",WORKDAY($O29,-IFERROR(VLOOKUP($D29,'Rules & Guardrails'!$A$9:$D$24,3,0),10))) | AF29: =IF($O29="","",IF(OR($AE29="Cancelled",$AE29="On hold",$AE29="Launched"),$AE29,IF(AND($Y29="Approved",OR($Z29="Yes",$Z29="N/A"),OR($AA29="Yes",$AA29="N/A"),OR($AB29="No",$AB29="N/A",AND($AB29="Yes",$AD29="Yes"))),"Ready",IF($O29<TODAY(),"Overdue",IF($O29-TODAY()<='Rules & Guardrails'!$C$5,"At Risk","In Progress"))))) | AG29: =IF($O29="","",IF(OR($AE29="Launched",$AE29="Cancelled"),"",MID(IF($Y29<>"Approved",", Content approval","")&IF(NOT(OR($Z29="Yes",$Z29="N/A")),", Assets","")&IF(NOT(OR($AA29="Yes",$AA29="N/A")),", List","")&IF($AB29="",", Ops decision",IF(AND($AB29="Yes",$AD29<>"Yes"),", Ops",""))&IF($U29="",", Owner","")&IF($K29="",", Segment",""),3,200))) | AH29: =IF($O29="","",$O29-TODAY()) | AI29: =IF($O29="","",$O29-WEEKDAY($O29,3)) | AJ29: =IF($O29="","",DATE(YEAR($O29),MONTH($O29),1)) | AK29: =IF(OR($O29="",$K29=""),"",COUNTIFS('Comms Calendar'!$K$5:$K$504,$K29,'Comms Calendar'!$B$5:$B$504,$B29,'Comms Calendar'!$AI$5:$AI$504,$AI29,'Comms Calendar'!$AE$5:$AE$504,"<>Cancelled")) | AL29: =IF($AK29="","",IF($AK29>'Rules & Guardrails'!$C$3,"Over cap","OK")) | AM29: =IF(OR($O29="",$K29=""),"",IF(COUNTIFS('Comms Calendar'!$K$5:$K$504,$K29,'Comms Calendar'!$B$5:$B$504,$B29,'Comms Calendar'!$O$5:$O$504,$O29,'Comms Calendar'!$AE$5:$AE$504,"<>Cancelled")>1,"Clash","")) | AN29: =IF($O29="","",IF(IF($B29="Global",COUNTIF('Rules & Guardrails'!$F$9:$F$60,$O29),COUNTIFS('Rules & Guardrails'!$F$9:$F$60,$O29,'Rules & Guardrails'!$G$9:$G$60,$B29)+COUNTIFS('Rules & Guardrails'!$F$9:$F$60,$O29,'Rules & Guardrails'!$G$9:$G$60,"Global"))>0,"Blackout","")) | AR29: =IF($D29="","",IFERROR(VLOOKUP($D29,'Rules & Guardrails'!$A$9:$D$24,2,0),"Other")) | AS29: =IF($O29="","",$O29&"|"&$B29)
T30: =IF(OR($O30="",$D30=""),"",WORKDAY($O30,-IFERROR(VLOOKUP($D30,'Rules & Guardrails'!$A$9:$D$24,3,0),10))) | AF30: =IF($O30="","",IF(OR($AE30="Cancelled",$AE30="On hold",$AE30="Launched"),$AE30,IF(AND($Y30="Approved",OR($Z30="Yes",$Z30="N/A"),OR($AA30="Yes",$AA30="N/A"),OR($AB30="No",$AB30="N/A",AND($AB30="Yes",$AD30="Yes"))),"Ready",IF($O30<TODAY(),"Overdue",IF($O30-TODAY()<='Rules & Guardrails'!$C$5,"At Risk","In Progress"))))) | AG30: =IF($O30="","",IF(OR($AE30="Launched",$AE30="Cancelled"),"",MID(IF($Y30<>"Approved",", Content approval","")&IF(NOT(OR($Z30="Yes",$Z30="N/A")),", Assets","")&IF(NOT(OR($AA30="Yes",$AA30="N/A")),", List","")&IF($AB30="",", Ops decision",IF(AND($AB30="Yes",$AD30<>"Yes"),", Ops",""))&IF($U30="",", Owner","")&IF($K30="",", Segment",""),3,200))) | AH30: =IF($O30="","",$O30-TODAY()) | AI30: =IF($O30="","",$O30-WEEKDAY($O30,3)) | AJ30: =IF($O30="","",DATE(YEAR($O30),MONTH($O30),1)) | AK30: =IF(OR($O30="",$K30=""),"",COUNTIFS('Comms Calendar'!$K$5:$K$504,$K30,'Comms Calendar'!$B$5:$B$504,$B30,'Comms Calendar'!$AI$5:$AI$504,$AI30,'Comms Calendar'!$AE$5:$AE$504,"<>Cancelled")) | AL30: =IF($AK30="","",IF($AK30>'Rules & Guardrails'!$C$3,"Over cap","OK")) | AM30: =IF(OR($O30="",$K30=""),"",IF(COUNTIFS('Comms Calendar'!$K$5:$K$504,$K30,'Comms Calendar'!$B$5:$B$504,$B30,'Comms Calendar'!$O$5:$O$504,$O30,'Comms Calendar'!$AE$5:$AE$504,"<>Cancelled")>1,"Clash","")) | AN30: =IF($O30="","",IF(IF($B30="Global",COUNTIF('Rules & Guardrails'!$F$9:$F$60,$O30),COUNTIFS('Rules & Guardrails'!$F$9:$F$60,$O30,'Rules & Guardrails'!$G$9:$G$60,$B30)+COUNTIFS('Rules & Guardrails'!$F$9:$F$60,$O30,'Rules & Guardrails'!$G$9:$G$60,"Global"))>0,"Blackout","")) | AR30: =IF($D30="","",IFERROR(VLOOKUP($D30,'Rules & Guardrails'!$A$9:$D$24,2,0),"Other")) | AS30: =IF($O30="","",$O30&"|"&$B30)
T31: =IF(OR($O31="",$D31=""),"",WORKDAY($O31,-IFERROR(VLOOKUP($D31,'Rules & Guardrails'!$A$9:$D$24,3,0),10))) | AF31: =IF($O31="","",IF(OR($AE31="Cancelled",$AE31="On hold",$AE31="Launched"),$AE31,IF(AND($Y31="Approved",OR($Z31="Yes",$Z31="N/A"),OR($AA31="Yes",$AA31="N/A"),OR($AB31="No",$AB31="N/A",AND($AB31="Yes",$AD31="Yes"))),"Ready",IF($O31<TODAY(),"Overdue",IF($O31-TODAY()<='Rules & Guardrails'!$C$5,"At Risk","In Progress"))))) | AG31: =IF($O31="","",IF(OR($AE31="Launched",$AE31="Cancelled"),"",MID(IF($Y31<>"Approved",", Content approval","")&IF(NOT(OR($Z31="Yes",$Z31="N/A")),", Assets","")&IF(NOT(OR($AA31="Yes",$AA31="N/A")),", List","")&IF($AB31="",", Ops decision",IF(AND($AB31="Yes",$AD31<>"Yes"),", Ops",""))&IF($U31="",", Owner","")&IF($K31="",", Segment",""),3,200))) | AH31: =IF($O31="","",$O31-TODAY()) | AI31: =IF($O31="","",$O31-WEEKDAY($O31,3)) | AJ31: =IF($O31="","",DATE(YEAR($O31),MONTH($O31),1)) | AK31: =IF(OR($O31="",$K31=""),"",COUNTIFS('Comms Calendar'!$K$5:$K$504,$K31,'Comms Calendar'!$B$5:$B$504,$B31,'Comms Calendar'!$AI$5:$AI$504,$AI31,'Comms Calendar'!$AE$5:$AE$504,"<>Cancelled")) | AL31: =IF($AK31="","",IF($AK31>'Rules & Guardrails'!$C$3,"Over cap","OK")) | AM31: =IF(OR($O31="",$K31=""),"",IF(COUNTIFS('Comms Calendar'!$K$5:$K$504,$K31,'Comms Calendar'!$B$5:$B$504,$B31,'Comms Calendar'!$O$5:$O$504,$O31,'Comms Calendar'!$AE$5:$AE$504,"<>Cancelled")>1,"Clash","")) | AN31: =IF($O31="","",IF(IF($B31="Global",COUNTIF('Rules & Guardrails'!$F$9:$F$60,$O31),COUNTIFS('Rules & Guardrails'!$F$9:$F$60,$O31,'Rules & Guardrails'!$G$9:$G$60,$B31)+COUNTIFS('Rules & Guardrails'!$F$9:$F$60,$O31,'Rules & Guardrails'!$G$9:$G$60,"Global"))>0,"Blackout","")) | AR31: =IF($D31="","",IFERROR(VLOOKUP($D31,'Rules & Guardrails'!$A$9:$D$24,2,0),"Other")) | AS31: =IF($O31="","",$O31&"|"&$B31)
... T504: =IF(OR($O504="",$D504=""),"",WORKDAY($O504,-IFERROR(VLOOKUP($D504,'Rules & Guardrails'!$A$9:$D$24,3,0),10))) | AF504: =IF($O504="","",IF(OR($AE504="Cancelled",$AE504="On hold",$AE504="Launched"),$AE504,IF(AND($Y504="Approved",OR($Z504="Yes",$Z504="N/A"),OR($AA504="Yes",$AA504="N/A"),OR($AB504="No",$AB504="N/A",AND($AB504="Yes",$AD504="Yes"))),"Ready",IF($O504<TODAY(),"Overdue",IF($O504-TODAY()<='Rules & Guardrails'!$C$5,"At Risk","In Progress"))))) | AG504: =IF($O504="","",IF(OR($AE504="Launched",$AE504="Cancelled"),"",MID(IF($Y504<>"Approved",", Content approval","")&IF(NOT(OR($Z504="Yes",$Z504="N/A")),", Assets","")&IF(NOT(OR($AA504="Yes",$AA504="N/A")),", List","")&IF($AB504="",", Ops decision",IF(AND($AB504="Yes",$AD504<>"Yes"),", Ops",""))&IF($U504="",", Owner","")&IF($K504="",", Segment",""),3,200))) | AH504: =IF($O504="","",$O504-TODAY()) | AI504: =IF($O504="","",$O504-WEEKDAY($O504,3)) | AJ504: =IF($O504="","",DATE(YEAR($O504),MONTH($O504),1)) | AK504: =IF(OR($O504="",$K504=""),"",COUNTIFS('Comms Calendar'!$K$5:$K$504,$K504,'Comms Calendar'!$B$5:$B$504,$B504,'Comms Calendar'!$AI$5:$AI$504,$AI504,'Comms Calendar'!$AE$5:$AE$504,"<>Cancelled")) | AL504: =IF($AK504="","",IF($AK504>'Rules & Guardrails'!$C$3,"Over cap","OK")) | AM504: =IF(OR($O504="",$K504=""),"",IF(COUNTIFS('Comms Calendar'!$K$5:$K$504,$K504,'Comms Calendar'!$B$5:$B$504,$B504,'Comms Calendar'!$O$5:$O$504,$O504,'Comms Calendar'!$AE$5:$AE$504,"<>Cancelled")>1,"Clash","")) | AN504: =IF($O504="","",IF(IF($B504="Global",COUNTIF('Rules & Guardrails'!$F$9:$F$60,$O504),COUNTIFS('Rules & Guardrails'!$F$9:$F$60,$O504,'Rules & Guardrails'!$G$9:$G$60,$B504)+COUNTIFS('Rules & Guardrails'!$F$9:$F$60,$O504,'Rules & Guardrails'!$G$9:$G$60,"Global"))>0,"Blackout","")) | AR504: =IF($D504="","",IFERROR(VLOOKUP($D504,'Rules & Guardrails'!$A$9:$D$24,2,0),"Other")) | AS504: =IF($O504="","",$O504&"|"&$B504)

Sheet Month View
B1: Month View
B3: Month (any date in it): | C3: 46296 | E3: Region: | F3: All | H3: ="Total this month: "&SUMPRODUCT(('Comms Calendar'!$O$5:$O$504>=DATE(YEAR($C$3),MONTH($C$3),1))*('Comms Calendar'!$O$5:$O$504<DATE(YEAR($C$3),MONTH($C$3)+1,1))*('Comms Calendar'!$AE$5:$AE$504<>"Cancelled")*(($F$3="All")+('Comms Calendar'!$B$5:$B$504=$F$3)>0)) -> Total this month: 9
B4: Change the yellow cells. Each day shows how many comms launch, the AM/EM/AP/GL split, and the first title. Cancelled items are excluded. Full detail lives on the Comms Calendar tab.
B6: Monday | C6: Tuesday | D6: Wednesday | E6: Thursday | F6: Friday | G6: Saturday | H6: Sunday
B7: =DATE(YEAR($C$3),MONTH($C$3),1)-WEEKDAY(DATE(YEAR($C$3),MONTH($C$3),1),3) -> 46293 | C7: =B7+1 -> 46294 | D7: =C7+1 -> 46295 | E7: =D7+1 -> 46296 | F7: =E7+1 -> 46297 | G7: =F7+1 -> 46298 | H7: =G7+1 -> 46299
B8: =IF($F$3="All",COUNTIFS('Comms Calendar'!$O$5:$O$504,B7,'Comms Calendar'!$AE$5:$AE$504,"<>Cancelled"),COUNTIFS('Comms Calendar'!$O$5:$O$504,B7,'Comms Calendar'!$B$5:$B$504,$F$3,'Comms Calendar'!$AE$5:$AE$504,"<>Cancelled")) -> 0 | C8: =IF($F$3="All",COUNTIFS('Comms Calendar'!$O$5:$O$504,C7,'Comms Calendar'!$AE$5:$AE$504,"<>Cancelled"),COUNTIFS('Comms Calendar'!$O$5:$O$504,C7,'Comms Calendar'!$B$5:$B$504,$F$3,'Comms Calendar'!$AE$5:$AE$504,"<>Cancelled")) -> 0 | D8: =IF($F$3="All",COUNTIFS('Comms Calendar'!$O$5:$O$504,D7,'Comms Calendar'!$AE$5:$AE$504,"<>Cancelled"),COUNTIFS('Comms Calendar'!$O$5:$O$504,D7,'Comms Calendar'!$B$5:$B$504,$F$3,'Comms Calendar'!$AE$5:$AE$504,"<>Cancelled")) -> 0 | E8: =IF($F$3="All",COUNTIFS('Comms Calendar'!$O$5:$O$504,E7,'Comms Calendar'!$AE$5:$AE$504,"<>Cancelled"),COUNTIFS('Comms Calendar'!$O$5:$O$504,E7,'Comms Calendar'!$B$5:$B$504,$F$3,'Comms Calendar'!$AE$5:$AE$504,"<>Cancelled")) -> 0 | F8: =IF($F$3="All",COUNTIFS('Comms Calendar'!$O$5:$O$504,F7,'Comms Calendar'!$AE$5:$AE$504,"<>Cancelled"),COUNTIFS('Comms Calendar'!$O$5:$O$504,F7,'Comms Calendar'!$B$5:$B$504,$F$3,'Comms Calendar'!$AE$5:$AE$504,"<>Cancelled")) -> 0 | G8: =IF($F$3="All",COUNTIFS('Comms Calendar'!$O$5:$O$504,G7,'Comms Calendar'!$AE$5:$AE$504,"<>Cancelled"),COUNTIFS('Comms Calendar'!$O$5:$O$504,G7,'Comms Calendar'!$B$5:$B$504,$F$3,'Comms Calendar'!$AE$5:$AE$504,"<>Cancelled")) -> 0 | H8: =IF($F$3="All",COUNTIFS('Comms Calendar'!$O$5:$O$504,H7,'Comms Calendar'!$AE$5:$AE$504,"<>Cancelled"),COUNTIFS('Comms Calendar'!$O$5:$O$504,H7,'Comms Calendar'!$B$5:$B$504,$F$3,'Comms Calendar'!$AE$5:$AE$504,"<>Cancelled")) -> 0
B9: =IF(B8=0,"","AM "&COUNTIFS('Comms Calendar'!$O$5:$O$504,B7,'Comms Calendar'!$B$5:$B$504,"AMER",'Comms Calendar'!$AE$5:$AE$504,"<>Cancelled")&" · "&"EM "&COUNTIFS('Comms Calendar'!$O$5:$O$504,B7,'Comms Calendar'!$B$5:$B$504,"EMEA",'Comms Calendar'!$AE$5:$AE$504,"<>Cancelled")&" · "&"AP "&COUNTIFS('Comms Calendar'!$O$5:$O$504,B7,'Comms Calendar'!$B$5:$B$504,"APAC",'Comms Calendar'!$AE$5:$AE$504,"<>Cancelled")&" · "&"GL "&COUNTIFS('Comms Calendar'!$O$5:$O$504,B7,'Comms Calendar'!$B$5:$B$504,"Global",'Comms Calendar'!$AE$5:$AE$504,"<>Cancelled")) | C9: =IF(C8=0,"","AM "&COUNTIFS('Comms Calendar'!$O$5:$O$504,C7,'Comms Calendar'!$B$5:$B$504,"AMER",'Comms Calendar'!$AE$5:$AE$504,"<>Cancelled")&" · "&"EM "&COUNTIFS('Comms Calendar'!$O$5:$O$504,C7,'Comms Calendar'!$B$5:$B$504,"EMEA",'Comms Calendar'!$AE$5:$AE$504,"<>Cancelled")&" · "&"AP "&COUNTIFS('Comms Calendar'!$O$5:$O$504,C7,'Comms Calendar'!$B$5:$B$504,"APAC",'Comms Calendar'!$AE$5:$AE$504,"<>Cancelled")&" · "&"GL "&COUNTIFS('Comms Calendar'!$O$5:$O$504,C7,'Comms Calendar'!$B$5:$B$504,"Global",'Comms Calendar'!$AE$5:$AE$504,"<>Cancelled")) | D9: =IF(D8=0,"","AM "&COUNTIFS('Comms Calendar'!$O$5:$O$504,D7,'Comms Calendar'!$B$5:$B$504,"AMER",'Comms Calendar'!$AE$5:$AE$504,"<>Cancelled")&" · "&"EM "&COUNTIFS('Comms Calendar'!$O$5:$O$504,D7,'Comms Calendar'!$B$5:$B$504,"EMEA",'Comms Calendar'!$AE$5:$AE$504,"<>Cancelled")&" · "&"AP "&COUNTIFS('Comms Calendar'!$O$5:$O$504,D7,'Comms Calendar'!$B$5:$B$504,"APAC",'Comms Calendar'!$AE$5:$AE$504,"<>Cancelled")&" · "&"GL "&COUNTIFS('Comms Calendar'!$O$5:$O$504,D7,'Comms Calendar'!$B$5:$B$504,"Global",'Comms Calendar'!$AE$5:$AE$504,"<>Cancelled")) | E9: =IF(E8=0,"","AM "&COUNTIFS('Comms Calendar'!$O$5:$O$504,E7,'Comms Calendar'!$B$5:$B$504,"AMER",'Comms Calendar'!$AE$5:$AE$504,"<>Cancelled")&" · "&"EM "&COUNTIFS('Comms Calendar'!$O$5:$O$504,E7,'Comms Calendar'!$B$5:$B$504,"EMEA",'Comms Calendar'!$AE$5:$AE$504,"<>Cancelled")&" · "&"AP "&COUNTIFS('Comms Calendar'!$O$5:$O$504,E7,'Comms Calendar'!$B$5:$B$504,"APAC",'Comms Calendar'!$AE$5:$AE$504,"<>Cancelled")&" · "&"GL "&COUNTIFS('Comms Calendar'!$O$5:$O$504,E7,'Comms Calendar'!$B$5:$B$504,"Global",'Comms Calendar'!$AE$5:$AE$504,"<>Cancelled")) | F9: =IF(F8=0,"","AM "&COUNTIFS('Comms Calendar'!$O$5:$O$504,F7,'Comms Calendar'!$B$5:$B$504,"AMER",'Comms Calendar'!$AE$5:$AE$504,"<>Cancelled")&" · "&"EM "&COUNTIFS('Comms Calendar'!$O$5:$O$504,F7,'Comms Calendar'!$B$5:$B$504,"EMEA",'Comms Calendar'!$AE$5:$AE$504,"<>Cancelled")&" · "&"AP "&COUNTIFS('Comms Calendar'!$O$5:$O$504,F7,'Comms Calendar'!$B$5:$B$504,"APAC",'Comms Calendar'!$AE$5:$AE$504,"<>Cancelled")&" · "&"GL "&COUNTIFS('Comms Calendar'!$O$5:$O$504,F7,'Comms Calendar'!$B$5:$B$504,"Global",'Comms Calendar'!$AE$5:$AE$504,"<>Cancelled")) | G9: =IF(G8=0,"","AM "&COUNTIFS('Comms Calendar'!$O$5:$O$504,G7,'Comms Calendar'!$B$5:$B$504,"AMER",'Comms Calendar'!$AE$5:$AE$504,"<>Cancelled")&" · "&"EM "&COUNTIFS('Comms Calendar'!$O$5:$O$504,G7,'Comms Calendar'!$B$5:$B$504,"EMEA",'Comms Calendar'!$AE$5:$AE$504,"<>Cancelled")&" · "&"AP "&COUNTIFS('Comms Calendar'!$O$5:$O$504,G7,'Comms Calendar'!$B$5:$B$504,"APAC",'Comms Calendar'!$AE$5:$AE$504,"<>Cancelled")&" · "&"GL "&COUNTIFS('Comms Calendar'!$O$5:$O$504,G7,'Comms Calendar'!$B$5:$B$504,"Global",'Comms Calendar'!$AE$5:$AE$504,"<>Cancelled")) | H9: =IF(H8=0,"","AM "&COUNTIFS('Comms Calendar'!$O$5:$O$504,H7,'Comms Calendar'!$B$5:$B$504,"AMER",'Comms Calendar'!$AE$5:$AE$504,"<>Cancelled")&" · "&"EM "&COUNTIFS('Comms Calendar'!$O$5:$O$504,H7,'Comms Calendar'!$B$5:$B$504,"EMEA",'Comms Calendar'!$AE$5:$AE$504,"<>Cancelled")&" · "&"AP "&COUNTIFS('Comms Calendar'!$O$5:$O$504,H7,'Comms Calendar'!$B$5:$B$504,"APAC",'Comms Calendar'!$AE$5:$AE$504,"<>Cancelled")&" · "&"GL "&COUNTIFS('Comms Calendar'!$O$5:$O$504,H7,'Comms Calendar'!$B$5:$B$504,"Global",'Comms Calendar'!$AE$5:$AE$504,"<>Cancelled"))
B10: =IF(B8=0,"",IFERROR(INDEX('Comms Calendar'!$G$5:$G$504,IF($F$3="All",MATCH(B7,'Comms Calendar'!$O$5:$O$504,0),MATCH(B7&"|"&$F$3,'Comms Calendar'!$AS$5:$AS$504,0))),"")&IF(B8>1," (+"&(B8-1)&" more)","")) | C10: =IF(C8=0,"",IFERROR(INDEX('Comms Calendar'!$G$5:$G$504,IF($F$3="All",MATCH(C7,'Comms Calendar'!$O$5:$O$504,0),MATCH(C7&"|"&$F$3,'Comms Calendar'!$AS$5:$AS$504,0))),"")&IF(C8>1," (+"&(C8-1)&" more)","")) | D10: =IF(D8=0,"",IFERROR(INDEX('Comms Calendar'!$G$5:$G$504,IF($F$3="All",MATCH(D7,'Comms Calendar'!$O$5:$O$504,0),MATCH(D7&"|"&$F$3,'Comms Calendar'!$AS$5:$AS$504,0))),"")&IF(D8>1," (+"&(D8-1)&" more)","")) | E10: =IF(E8=0,"",IFERROR(INDEX('Comms Calendar'!$G$5:$G$504,IF($F$3="All",MATCH(E7,'Comms Calendar'!$O$5:$O$504,0),MATCH(E7&"|"&$F$3,'Comms Calendar'!$AS$5:$AS$504,0))),"")&IF(E8>1," (+"&(E8-1)&" more)","")) | F10: =IF(F8=0,"",IFERROR(INDEX('Comms Calendar'!$G$5:$G$504,IF($F$3="All",MATCH(F7,'Comms Calendar'!$O$5:$O$504,0),MATCH(F7&"|"&$F$3,'Comms Calendar'!$AS$5:$AS$504,0))),"")&IF(F8>1," (+"&(F8-1)&" more)","")) | G10: =IF(G8=0,"",IFERROR(INDEX('Comms Calendar'!$G$5:$G$504,IF($F$3="All",MATCH(G7,'Comms Calendar'!$O$5:$O$504,0),MATCH(G7&"|"&$F$3,'Comms Calendar'!$AS$5:$AS$504,0))),"")&IF(G8>1," (+"&(G8-1)&" more)","")) | H10: =IF(H8=0,"",IFERROR(INDEX('Comms Calendar'!$G$5:$G$504,IF($F$3="All",MATCH(H7,'Comms Calendar'!$O$5:$O$504,0),MATCH(H7&"|"&$F$3,'Comms Calendar'!$AS$5:$AS$504,0))),"")&IF(H8>1," (+"&(H8-1)&" more)",""))
B11: =H7+1 -> 46300 | C11: =B11+1 -> 46301 | D11: =C11+1 -> 46302 | E11: =D11+1 -> 46303 | F11: =E11+1 -> 46304 | G11: =F11+1 -> 46305 | H11: =G11+1 -> 46306
B12: =IF($F$3="All",COUNTIFS('Comms Calendar'!$O$5:$O$504,B11,'Comms Calendar'!$AE$5:$AE$504,"<>Cancelled"),COUNTIFS('Comms Calendar'!$O$5:$O$504,B11,'Comms Calendar'!$B$5:$B$504,$F$3,'Comms Calendar'!$AE$5:$AE$504,"<>Cancelled")) -> 0 | C12: =IF($F$3="All",COUNTIFS('Comms Calendar'!$O$5:$O$504,C11,'Comms Calendar'!$AE$5:$AE$504,"<>Cancelled"),COUNTIFS('Comms Calendar'!$O$5:$O$504,C11,'Comms Calendar'!$B$5:$B$504,$F$3,'Comms Calendar'!$AE$5:$AE$504,"<>Cancelled")) -> 0 | D12: =IF($F$3="All",COUNTIFS('Comms Calendar'!$O$5:$O$504,D11,'Comms Calendar'!$AE$5:$AE$504,"<>Cancelled"),COUNTIFS('Comms Calendar'!$O$5:$O$504,D11,'Comms Calendar'!$B$5:$B$504,$F$3,'Comms Calendar'!$AE$5:$AE$504,"<>Cancelled")) -> 0 | E12: =IF($F$3="All",COUNTIFS('Comms Calendar'!$O$5:$O$504,E11,'Comms Calendar'!$AE$5:$AE$504,"<>Cancelled"),COUNTIFS('Comms Calendar'!$O$5:$O$504,E11,'Comms Calendar'!$B$5:$B$504,$F$3,'Comms Calendar'!$AE$5:$AE$504,"<>Cancelled")) -> 0 | F12: =IF($F$3="All",COUNTIFS('Comms Calendar'!$O$5:$O$504,F11,'Comms Calendar'!$AE$5:$AE$504,"<>Cancelled"),COUNTIFS('Comms Calendar'!$O$5:$O$504,F11,'Comms Calendar'!$B$5:$B$504,$F$3,'Comms Calendar'!$AE$5:$AE$504,"<>Cancelled")) -> 0 | G12: =IF($F$3="All",COUNTIFS('Comms Calendar'!$O$5:$O$504,G11,'Comms Calendar'!$AE$5:$AE$504,"<>Cancelled"),COUNTIFS('Comms Calendar'!$O$5:$O$504,G11,'Comms Calendar'!$B$5:$B$504,$F$3,'Comms Calendar'!$AE$5:$AE$504,"<>Cancelled")) -> 0 | H12: =IF($F$3="All",COUNTIFS('Comms Calendar'!$O$5:$O$504,H11,'Comms Calendar'!$AE$5:$AE$504,"<>Cancelled"),COUNTIFS('Comms Calendar'!$O$5:$O$504,H11,'Comms Calendar'!$B$5:$B$504,$F$3,'Comms Calendar'!$AE$5:$AE$504,"<>Cancelled")) -> 0
B13: =IF(B12=0,"","AM "&COUNTIFS('Comms Calendar'!$O$5:$O$504,B11,'Comms Calendar'!$B$5:$B$504,"AMER",'Comms Calendar'!$AE$5:$AE$504,"<>Cancelled")&" · "&"EM "&COUNTIFS('Comms Calendar'!$O$5:$O$504,B11,'Comms Calendar'!$B$5:$B$504,"EMEA",'Comms Calendar'!$AE$5:$AE$504,"<>Cancelled")&" · "&"AP "&COUNTIFS('Comms Calendar'!$O$5:$O$504,B11,'Comms Calendar'!$B$5:$B$504,"APAC",'Comms Calendar'!$AE$5:$AE$504,"<>Cancelled")&" · "&"GL "&COUNTIFS('Comms Calendar'!$O$5:$O$504,B11,'Comms Calendar'!$B$5:$B$504,"Global",'Comms Calendar'!$AE$5:$AE$504,"<>Cancelled")) | C13: =IF(C12=0,"","AM "&COUNTIFS('Comms Calendar'!$O$5:$O$504,C11,'Comms Calendar'!$B$5:$B$504,"AMER",'Comms Calendar'!$AE$5:$AE$504,"<>Cancelled")&" · "&"EM "&COUNTIFS('Comms Calendar'!$O$5:$O$504,C11,'Comms Calendar'!$B$5:$B$504,"EMEA",'Comms Calendar'!$AE$5:$AE$504,"<>Cancelled")&" · "&"AP "&COUNTIFS('Comms Calendar'!$O$5:$O$504,C11,'Comms Calendar'!$B$5:$B$504,"APAC",'Comms Calendar'!$AE$5:$AE$504,"<>Cancelled")&" · "&"GL "&COUNTIFS('Comms Calendar'!$O$5:$O$504,C11,'Comms Calendar'!$B$5:$B$504,"Global",'Comms Calendar'!$AE$5:$AE$504,"<>Cancelled")) | D13: =IF(D12=0,"","AM "&COUNTIFS('Comms Calendar'!$O$5:$O$504,D11,'Comms Calendar'!$B$5:$B$504,"AMER",'Comms Calendar'!$AE$5:$AE$504,"<>Cancelled")&" · "&"EM "&COUNTIFS('Comms Calendar'!$O$5:$O$504,D11,'Comms Calendar'!$B$5:$B$504,"EMEA",'Comms Calendar'!$AE$5:$AE$504,"<>Cancelled")&" · "&"AP "&COUNTIFS('Comms Calendar'!$O$5:$O$504,D11,'Comms Calendar'!$B$5:$B$504,"APAC",'Comms Calendar'!$AE$5:$AE$504,"<>Cancelled")&" · "&"GL "&COUNTIFS('Comms Calendar'!$O$5:$O$504,D11,'Comms Calendar'!$B$5:$B$504,"Global",'Comms Calendar'!$AE$5:$AE$504,"<>Cancelled")) | E13: =IF(E12=0,"","AM "&COUNTIFS('Comms Calendar'!$O$5:$O$504,E11,'Comms Calendar'!$B$5:$B$504,"AMER",'Comms Calendar'!$AE$5:$AE$504,"<>Cancelled")&" · "&"EM "&COUNTIFS('Comms Calendar'!$O$5:$O$504,E11,'Comms Calendar'!$B$5:$B$504,"EMEA",'Comms Calendar'!$AE$5:$AE$504,"<>Cancelled")&" · "&"AP "&COUNTIFS('Comms Calendar'!$O$5:$O$504,E11,'Comms Calendar'!$B$5:$B$504,"APAC",'Comms Calendar'!$AE$5:$AE$504,"<>Cancelled")&" · "&"GL "&COUNTIFS('Comms Calendar'!$O$5:$O$504,E11,'Comms Calendar'!$B$5:$B$504,"Global",'Comms Calendar'!$AE$5:$AE$504,"<>Cancelled")) | F13: =IF(F12=0,"","AM "&COUNTIFS('Comms Calendar'!$O$5:$O$504,F11,'Comms Calendar'!$B$5:$B$504,"AMER",'Comms Calendar'!$AE$5:$AE$504,"<>Cancelled")&" · "&"EM "&COUNTIFS('Comms Calendar'!$O$5:$O$504,F11,'Comms Calendar'!$B$5:$B$504,"EMEA",'Comms Calendar'!$AE$5:$AE$504,"<>Cancelled")&" · "&"AP "&COUNTIFS('Comms Calendar'!$O$5:$O$504,F11,'Comms Calendar'!$B$5:$B$504,"APAC",'Comms Calendar'!$AE$5:$AE$504,"<>Cancelled")&" · "&"GL "&COUNTIFS('Comms Calendar'!$O$5:$O$504,F11,'Comms Calendar'!$B$5:$B$504,"Global",'Comms Calendar'!$AE$5:$AE$504,"<>Cancelled")) | G13: =IF(G12=0,"","AM "&COUNTIFS('Comms Calendar'!$O$5:$O$504,G11,'Comms Calendar'!$B$5:$B$504,"AMER",'Comms Calendar'!$AE$5:$AE$504,"<>Cancelled")&" · "&"EM "&COUNTIFS('Comms Calendar'!$O$5:$O$504,G11,'Comms Calendar'!$B$5:$B$504,"EMEA",'Comms Calendar'!$AE$5:$AE$504,"<>Cancelled")&" · "&"AP "&COUNTIFS('Comms Calendar'!$O$5:$O$504,G11,'Comms Calendar'!$B$5:$B$504,"APAC",'Comms Calendar'!$AE$5:$AE$504,"<>Cancelled")&" · "&"GL "&COUNTIFS('Comms Calendar'!$O$5:$O$504,G11,'Comms Calendar'!$B$5:$B$504,"Global",'Comms Calendar'!$AE$5:$AE$504,"<>Cancelled")) | H13: =IF(H12=0,"","AM "&COUNTIFS('Comms Calendar'!$O$5:$O$504,H11,'Comms Calendar'!$B$5:$B$504,"AMER",'Comms Calendar'!$AE$5:$AE$504,"<>Cancelled")&" · "&"EM "&COUNTIFS('Comms Calendar'!$O$5:$O$504,H11,'Comms Calendar'!$B$5:$B$504,"EMEA",'Comms Calendar'!$AE$5:$AE$504,"<>Cancelled")&" · "&"AP "&COUNTIFS('Comms Calendar'!$O$5:$O$504,H11,'Comms Calendar'!$B$5:$B$504,"APAC",'Comms Calendar'!$AE$5:$AE$504,"<>Cancelled")&" · "&"GL "&COUNTIFS('Comms Calendar'!$O$5:$O$504,H11,'Comms Calendar'!$B$5:$B$504,"Global",'Comms Calendar'!$AE$5:$AE$504,"<>Cancelled"))
B14: =IF(B12=0,"",IFERROR(INDEX('Comms Calendar'!$G$5:$G$504,IF($F$3="All",MATCH(B11,'Comms Calendar'!$O$5:$O$504,0),MATCH(B11&"|"&$F$3,'Comms Calendar'!$AS$5:$AS$504,0))),"")&IF(B12>1," (+"&(B12-1)&" more)","")) | C14: =IF(C12=0,"",IFERROR(INDEX('Comms Calendar'!$G$5:$G$504,IF($F$3="All",MATCH(C11,'Comms Calendar'!$O$5:$O$504,0),MATCH(C11&"|"&$F$3,'Comms Calendar'!$AS$5:$AS$504,0))),"")&IF(C12>1," (+"&(C12-1)&" more)","")) | D14: =IF(D12=0,"",IFERROR(INDEX('Comms Calendar'!$G$5:$G$504,IF($F$3="All",MATCH(D11,'Comms Calendar'!$O$5:$O$504,0),MATCH(D11&"|"&$F$3,'Comms Calendar'!$AS$5:$AS$504,0))),"")&IF(D12>1," (+"&(D12-1)&" more)","")) | E14: =IF(E12=0,"",IFERROR(INDEX('Comms Calendar'!$G$5:$G$504,IF($F$3="All",MATCH(E11,'Comms Calendar'!$O$5:$O$504,0),MATCH(E11&"|"&$F$3,'Comms Calendar'!$AS$5:$AS$504,0))),"")&IF(E12>1," (+"&(E12-1)&" more)","")) | F14: =IF(F12=0,"",IFERROR(INDEX('Comms Calendar'!$G$5:$G$504,IF($F$3="All",MATCH(F11,'Comms Calendar'!$O$5:$O$504,0),MATCH(F11&"|"&$F$3,'Comms Calendar'!$AS$5:$AS$504,0))),"")&IF(F12>1," (+"&(F12-1)&" more)","")) | G14: =IF(G12=0,"",IFERROR(INDEX('Comms Calendar'!$G$5:$G$504,IF($F$3="All",MATCH(G11,'Comms Calendar'!$O$5:$O$504,0),MATCH(G11&"|"&$F$3,'Comms Calendar'!$AS$5:$AS$504,0))),"")&IF(G12>1," (+"&(G12-1)&" more)","")) | H14: =IF(H12=0,"",IFERROR(INDEX('Comms Calendar'!$G$5:$G$504,IF($F$3="All",MATCH(H11,'Comms Calendar'!$O$5:$O$504,0),MATCH(H11&"|"&$F$3,'Comms Calendar'!$AS$5:$AS$504,0))),"")&IF(H12>1," (+"&(H12-1)&" more)",""))
B15: =H11+1 -> 46307 | C15: =B15+1 -> 46308 | D15: =C15+1 -> 46309 | E15: =D15+1 -> 46310 | F15: =E15+1 -> 46311 | G15: =F15+1 -> 46312 | H15: =G15+1 -> 46313
B16: =IF($F$3="All",COUNTIFS('Comms Calendar'!$O$5:$O$504,B15,'Comms Calendar'!$AE$5:$AE$504,"<>Cancelled"),COUNTIFS('Comms Calendar'!$O$5:$O$504,B15,'Comms Calendar'!$B$5:$B$504,$F$3,'Comms Calendar'!$AE$5:$AE$504,"<>Cancelled")) -> 0 | C16: =IF($F$3="All",COUNTIFS('Comms Calendar'!$O$5:$O$504,C15,'Comms Calendar'!$AE$5:$AE$504,"<>Cancelled"),COUNTIFS('Comms Calendar'!$O$5:$O$504,C15,'Comms Calendar'!$B$5:$B$504,$F$3,'Comms Calendar'!$AE$5:$AE$504,"<>Cancelled")) -> 2 | D16: =IF($F$3="All",COUNTIFS('Comms Calendar'!$O$5:$O$504,D15,'Comms Calendar'!$AE$5:$AE$504,"<>Cancelled"),COUNTIFS('Comms Calendar'!$O$5:$O$504,D15,'Comms Calendar'!$B$5:$B$504,$F$3,'Comms Calendar'!$AE$5:$AE$504,"<>Cancelled")) -> 1 | E16: =IF($F$3="All",COUNTIFS('Comms Calendar'!$O$5:$O$504,E15,'Comms Calendar'!$AE$5:$AE$504,"<>Cancelled"),COUNTIFS('Comms Calendar'!$O$5:$O$504,E15,'Comms Calendar'!$B$5:$B$504,$F$3,'Comms Calendar'!$AE$5:$AE$504,"<>Cancelled")) -> 2 | F16: =IF($F$3="All",COUNTIFS('Comms Calendar'!$O$5:$O$504,F15,'Comms Calendar'!$AE$5:$AE$504,"<>Cancelled"),COUNTIFS('Comms Calendar'!$O$5:$O$504,F15,'Comms Calendar'!$B$5:$B$504,$F$3,'Comms Calendar'!$AE$5:$AE$504,"<>Cancelled")) -> 0 | G16: =IF($F$3="All",COUNTIFS('Comms Calendar'!$O$5:$O$504,G15,'Comms Calendar'!$AE$5:$AE$504,"<>Cancelled"),COUNTIFS('Comms Calendar'!$O$5:$O$504,G15,'Comms Calendar'!$B$5:$B$504,$F$3,'Comms Calendar'!$AE$5:$AE$504,"<>Cancelled")) -> 0 | H16: =IF($F$3="All",COUNTIFS('Comms Calendar'!$O$5:$O$504,H15,'Comms Calendar'!$AE$5:$AE$504,"<>Cancelled"),COUNTIFS('Comms Calendar'!$O$5:$O$504,H15,'Comms Calendar'!$B$5:$B$504,$F$3,'Comms Calendar'!$AE$5:$AE$504,"<>Cancelled")) -> 0
B17: =IF(B16=0,"","AM "&COUNTIFS('Comms Calendar'!$O$5:$O$504,B15,'Comms Calendar'!$B$5:$B$504,"AMER",'Comms Calendar'!$AE$5:$AE$504,"<>Cancelled")&" · "&"EM "&COUNTIFS('Comms Calendar'!$O$5:$O$504,B15,'Comms Calendar'!$B$5:$B$504,"EMEA",'Comms Calendar'!$AE$5:$AE$504,"<>Cancelled")&" · "&"AP "&COUNTIFS('Comms Calendar'!$O$5:$O$504,B15,'Comms Calendar'!$B$5:$B$504,"APAC",'Comms Calendar'!$AE$5:$AE$504,"<>Cancelled")&" · "&"GL "&COUNTIFS('Comms Calendar'!$O$5:$O$504,B15,'Comms Calendar'!$B$5:$B$504,"Global",'Comms Calendar'!$AE$5:$AE$504,"<>Cancelled")) | C17: =IF(C16=0,"","AM "&COUNTIFS('Comms Calendar'!$O$5:$O$504,C15,'Comms Calendar'!$B$5:$B$504,"AMER",'Comms Calendar'!$AE$5:$AE$504,"<>Cancelled")&" · "&"EM "&COUNTIFS('Comms Calendar'!$O$5:$O$504,C15,'Comms Calendar'!$B$5:$B$504,"EMEA",'Comms Calendar'!$AE$5:$AE$504,"<>Cancelled")&" · "&"AP "&COUNTIFS('Comms Calendar'!$O$5:$O$504,C15,'Comms Calendar'!$B$5:$B$504,"APAC",'Comms Calendar'!$AE$5:$AE$504,"<>Cancelled")&" · "&"GL "&COUNTIFS('Comms Calendar'!$O$5:$O$504,C15,'Comms Calendar'!$B$5:$B$504,"Global",'Comms Calendar'!$AE$5:$AE$504,"<>Cancelled")) -> AM 2 · EM 0 · AP 0 · GL 0 | D17: =IF(D16=0,"","AM "&COUNTIFS('Comms Calendar'!$O$5:$O$504,D15,'Comms Calendar'!$B$5:$B$504,"AMER",'Comms Calendar'!$AE$5:$AE$504,"<>Cancelled")&" · "&"EM "&COUNTIFS('Comms Calendar'!$O$5:$O$504,D15,'Comms Calendar'!$B$5:$B$504,"EMEA",'Comms Calendar'!$AE$5:$AE$504,"<>Cancelled")&" · "&"AP "&COUNTIFS('Comms Calendar'!$O$5:$O$504,D15,'Comms Calendar'!$B$5:$B$504,"APAC",'Comms Calendar'!$AE$5:$AE$504,"<>Cancelled")&" · "&"GL "&COUNTIFS('Comms Calendar'!$O$5:$O$504,D15,'Comms Calendar'!$B$5:$B$504,"Global",'Comms Calendar'!$AE$5:$AE$504,"<>Cancelled")) -> AM 0 · EM 1 · AP 0 · GL 0 | E17: =IF(E16=0,"","AM "&COUNTIFS('Comms Calendar'!$O$5:$O$504,E15,'Comms Calendar'!$B$5:$B$504,"AMER",'Comms Calendar'!$AE$5:$AE$504,"<>Cancelled")&" · "&"EM "&COUNTIFS('Comms Calendar'!$O$5:$O$504,E15,'Comms Calendar'!$B$5:$B$504,"EMEA",'Comms Calendar'!$AE$5:$AE$504,"<>Cancelled")&" · "&"AP "&COUNTIFS('Comms Calendar'!$O$5:$O$504,E15,'Comms Calendar'!$B$5:$B$504,"APAC",'Comms Calendar'!$AE$5:$AE$504,"<>Cancelled")&" · "&"GL "&COUNTIFS('Comms Calendar'!$O$5:$O$504,E15,'Comms Calendar'!$B$5:$B$504,"Global",'Comms Calendar'!$AE$5:$AE$504,"<>Cancelled")) -> AM 1 · EM 0 · AP 0 · GL 1 | F17: =IF(F16=0,"","AM "&COUNTIFS('Comms Calendar'!$O$5:$O$504,F15,'Comms Calendar'!$B$5:$B$504,"AMER",'Comms Calendar'!$AE$5:$AE$504,"<>Cancelled")&" · "&"EM "&COUNTIFS('Comms Calendar'!$O$5:$O$504,F15,'Comms Calendar'!$B$5:$B$504,"EMEA",'Comms Calendar'!$AE$5:$AE$504,"<>Cancelled")&" · "&"AP "&COUNTIFS('Comms Calendar'!$O$5:$O$504,F15,'Comms Calendar'!$B$5:$B$504,"APAC",'Comms Calendar'!$AE$5:$AE$504,"<>Cancelled")&" · "&"GL "&COUNTIFS('Comms Calendar'!$O$5:$O$504,F15,'Comms Calendar'!$B$5:$B$504,"Global",'Comms Calendar'!$AE$5:$AE$504,"<>Cancelled")) | G17: =IF(G16=0,"","AM "&COUNTIFS('Comms Calendar'!$O$5:$O$504,G15,'Comms Calendar'!$B$5:$B$504,"AMER",'Comms Calendar'!$AE$5:$AE$504,"<>Cancelled")&" · "&"EM "&COUNTIFS('Comms Calendar'!$O$5:$O$504,G15,'Comms Calendar'!$B$5:$B$504,"EMEA",'Comms Calendar'!$AE$5:$AE$504,"<>Cancelled")&" · "&"AP "&COUNTIFS('Comms Calendar'!$O$5:$O$504,G15,'Comms Calendar'!$B$5:$B$504,"APAC",'Comms Calendar'!$AE$5:$AE$504,"<>Cancelled")&" · "&"GL "&COUNTIFS('Comms Calendar'!$O$5:$O$504,G15,'Comms Calendar'!$B$5:$B$504,"Global",'Comms Calendar'!$AE$5:$AE$504,"<>Cancelled")) | H17: =IF(H16=0,"","AM "&COUNTIFS('Comms Calendar'!$O$5:$O$504,H15,'Comms Calendar'!$B$5:$B$504,"AMER",'Comms Calendar'!$AE$5:$AE$504,"<>Cancelled")&" · "&"EM "&COUNTIFS('Comms Calendar'!$O$5:$O$504,H15,'Comms Calendar'!$B$5:$B$504,"EMEA",'Comms Calendar'!$AE$5:$AE$504,"<>Cancelled")&" · "&"AP "&COUNTIFS('Comms Calendar'!$O$5:$O$504,H15,'Comms Calendar'!$B$5:$B$504,"APAC",'Comms Calendar'!$AE$5:$AE$504,"<>Cancelled")&" · "&"GL "&COUNTIFS('Comms Calendar'!$O$5:$O$504,H15,'Comms Calendar'!$B$5:$B$504,"Global",'Comms Calendar'!$AE$5:$AE$504,"<>Cancelled"))
B18: =IF(B16=0,"",IFERROR(INDEX('Comms Calendar'!$G$5:$G$504,IF($F$3="All",MATCH(B15,'Comms Calendar'!$O$5:$O$504,0),MATCH(B15&"|"&$F$3,'Comms Calendar'!$AS$5:$AS$504,0))),"")&IF(B16>1," (+"&(B16-1)&" more)","")) | C18: =IF(C16=0,"",IFERROR(INDEX('Comms Calendar'!$G$5:$G$504,IF($F$3="All",MATCH(C15,'Comms Calendar'!$O$5:$O$504,0),MATCH(C15&"|"&$F$3,'Comms Calendar'!$AS$5:$AS$504,0))),"")&IF(C16>1," (+"&(C16-1)&" more)","")) -> You're invited: What's next on our Q4 roadmap (+1 more) | D18: =IF(D16=0,"",IFERROR(INDEX('Comms Calendar'!$G$5:$G$504,IF($F$3="All",MATCH(D15,'Comms Calendar'!$O$5:$O$504,0),MATCH(D15&"|"&$F$3,'Comms Calendar'!$AS$5:$AS$504,0))),"")&IF(D16>1," (+"&(D16-1)&" more)","")) -> Join us: Q4 roadmap live (EN/DE/FR) | E18: =IF(E16=0,"",IFERROR(INDEX('Comms Calendar'!$G$5:$G$504,IF($F$3="All",MATCH(E15,'Comms Calendar'!$O$5:$O$504,0),MATCH(E15&"|"&$F$3,'Comms Calendar'!$AS$5:$AS$504,0))),"")&IF(E16>1," (+"&(E16-1)&" more)","")) -> Reminder: Q4 roadmap webinar is next week (+1 more) | F18: =IF(F16=0,"",IFERROR(INDEX('Comms Calendar'!$G$5:$G$504,IF($F$3="All",MATCH(F15,'Comms Calendar'!$O$5:$O$504,0),MATCH(F15&"|"&$F$3,'Comms Calendar'!$AS$5:$AS$504,0))),"")&IF(F16>1," (+"&(F16-1)&" more)","")) | G18: =IF(G16=0,"",IFERROR(INDEX('Comms Calendar'!$G$5:$G$504,IF($F$3="All",MATCH(G15,'Comms Calendar'!$O$5:$O$504,0),MATCH(G15&"|"&$F$3,'Comms Calendar'!$AS$5:$AS$504,0))),"")&IF(G16>1," (+"&(G16-1)&" more)","")) | H18: =IF(H16=0,"",IFERROR(INDEX('Comms Calendar'!$G$5:$G$504,IF($F$3="All",MATCH(H15,'Comms Calendar'!$O$5:$O$504,0),MATCH(H15&"|"&$F$3,'Comms Calendar'!$AS$5:$AS$504,0))),"")&IF(H16>1," (+"&(H16-1)&" more)",""))
B19: =H15+1 -> 46314 | C19: =B19+1 -> 46315 | D19: =C19+1 -> 46316 | E19: =D19+1 -> 46317 | F19: =E19+1 -> 46318 | G19: =F19+1 -> 46319 | H19: =G19+1 -> 46320
B20: =IF($F$3="All",COUNTIFS('Comms Calendar'!$O$5:$O$504,B19,'Comms Calendar'!$AE$5:$AE$504,"<>Cancelled"),COUNTIFS('Comms Calendar'!$O$5:$O$504,B19,'Comms Calendar'!$B$5:$B$504,$F$3,'Comms Calendar'!$AE$5:$AE$504,"<>Cancelled")) -> 0 | C20: =IF($F$3="All",COUNTIFS('Comms Calendar'!$O$5:$O$504,C19,'Comms Calendar'!$AE$5:$AE$504,"<>Cancelled"),COUNTIFS('Comms Calendar'!$O$5:$O$504,C19,'Comms Calendar'!$B$5:$B$504,$F$3,'Comms Calendar'!$AE$5:$AE$504,"<>Cancelled")) -> 0 | D20: =IF($F$3="All",COUNTIFS('Comms Calendar'!$O$5:$O$504,D19,'Comms Calendar'!$AE$5:$AE$504,"<>Cancelled"),COUNTIFS('Comms Calendar'!$O$5:$O$504,D19,'Comms Calendar'!$B$5:$B$504,$F$3,'Comms Calendar'!$AE$5:$AE$504,"<>Cancelled")) -> 0 | E20: =IF($F$3="All",COUNTIFS('Comms Calendar'!$O$5:$O$504,E19,'Comms Calendar'!$AE$5:$AE$504,"<>Cancelled"),COUNTIFS('Comms Calendar'!$O$5:$O$504,E19,'Comms Calendar'!$B$5:$B$504,$F$3,'Comms Calendar'!$AE$5:$AE$504,"<>Cancelled")) -> 1 | F20: =IF($F$3="All",COUNTIFS('Comms Calendar'!$O$5:$O$504,F19,'Comms Calendar'!$AE$5:$AE$504,"<>Cancelled"),COUNTIFS('Comms Calendar'!$O$5:$O$504,F19,'Comms Calendar'!$B$5:$B$504,$F$3,'Comms Calendar'!$AE$5:$AE$504,"<>Cancelled")) -> 1 | G20: =IF($F$3="All",COUNTIFS('Comms Calendar'!$O$5:$O$504,G19,'Comms Calendar'!$AE$5:$AE$504,"<>Cancelled"),COUNTIFS('Comms Calendar'!$O$5:$O$504,G19,'Comms Calendar'!$B$5:$B$504,$F$3,'Comms Calendar'!$AE$5:$AE$504,"<>Cancelled")) -> 0 | H20: =IF($F$3="All",COUNTIFS('Comms Calendar'!$O$5:$O$504,H19,'Comms Calendar'!$AE$5:$AE$504,"<>Cancelled"),COUNTIFS('Comms Calendar'!$O$5:$O$504,H19,'Comms Calendar'!$B$5:$B$504,$F$3,'Comms Calendar'!$AE$5:$AE$504,"<>Cancelled")) -> 0
B21: =IF(B20=0,"","AM "&COUNTIFS('Comms Calendar'!$O$5:$O$504,B19,'Comms Calendar'!$B$5:$B$504,"AMER",'Comms Calendar'!$AE$5:$AE$504,"<>Cancelled")&" · "&"EM "&COUNTIFS('Comms Calendar'!$O$5:$O$504,B19,'Comms Calendar'!$B$5:$B$504,"EMEA",'Comms Calendar'!$AE$5:$AE$504,"<>Cancelled")&" · "&"AP "&COUNTIFS('Comms Calendar'!$O$5:$O$504,B19,'Comms Calendar'!$B$5:$B$504,"APAC",'Comms Calendar'!$AE$5:$AE$504,"<>Cancelled")&" · "&"GL "&COUNTIFS('Comms Calendar'!$O$5:$O$504,B19,'Comms Calendar'!$B$5:$B$504,"Global",'Comms Calendar'!$AE$5:$AE$504,"<>Cancelled")) | C21: =IF(C20=0,"","AM "&COUNTIFS('Comms Calendar'!$O$5:$O$504,C19,'Comms Calendar'!$B$5:$B$504,"AMER",'Comms Calendar'!$AE$5:$AE$504,"<>Cancelled")&" · "&"EM "&COUNTIFS('Comms Calendar'!$O$5:$O$504,C19,'Comms Calendar'!$B$5:$B$504,"EMEA",'Comms Calendar'!$AE$5:$AE$504,"<>Cancelled")&" · "&"AP "&COUNTIFS('Comms Calendar'!$O$5:$O$504,C19,'Comms Calendar'!$B$5:$B$504,"APAC",'Comms Calendar'!$AE$5:$AE$504,"<>Cancelled")&" · "&"GL "&COUNTIFS('Comms Calendar'!$O$5:$O$504,C19,'Comms Calendar'!$B$5:$B$504,"Global",'Comms Calendar'!$AE$5:$AE$504,"<>Cancelled")) | D21: =IF(D20=0,"","AM "&COUNTIFS('Comms Calendar'!$O$5:$O$504,D19,'Comms Calendar'!$B$5:$B$504,"AMER",'Comms Calendar'!$AE$5:$AE$504,"<>Cancelled")&" · "&"EM "&COUNTIFS('Comms Calendar'!$O$5:$O$504,D19,'Comms Calendar'!$B$5:$B$504,"EMEA",'Comms Calendar'!$AE$5:$AE$504,"<>Cancelled")&" · "&"AP "&COUNTIFS('Comms Calendar'!$O$5:$O$504,D19,'Comms Calendar'!$B$5:$B$504,"APAC",'Comms Calendar'!$AE$5:$AE$504,"<>Cancelled")&" · "&"GL "&COUNTIFS('Comms Calendar'!$O$5:$O$504,D19,'Comms Calendar'!$B$5:$B$504,"Global",'Comms Calendar'!$AE$5:$AE$504,"<>Cancelled")) | E21: =IF(E20=0,"","AM "&COUNTIFS('Comms Calendar'!$O$5:$O$504,E19,'Comms Calendar'!$B$5:$B$504,"AMER",'Comms Calendar'!$AE$5:$AE$504,"<>Cancelled")&" · "&"EM "&COUNTIFS('Comms Calendar'!$O$5:$O$504,E19,'Comms Calendar'!$B$5:$B$504,"EMEA",'Comms Calendar'!$AE$5:$AE$504,"<>Cancelled")&" · "&"AP "&COUNTIFS('Comms Calendar'!$O$5:$O$504,E19,'Comms Calendar'!$B$5:$B$504,"APAC",'Comms Calendar'!$AE$5:$AE$504,"<>Cancelled")&" · "&"GL "&COUNTIFS('Comms Calendar'!$O$5:$O$504,E19,'Comms Calendar'!$B$5:$B$504,"Global",'Comms Calendar'!$AE$5:$AE$504,"<>Cancelled")) -> AM 1 · EM 0 · AP 0 · GL 0 | F21: =IF(F20=0,"","AM "&COUNTIFS('Comms Calendar'!$O$5:$O$504,F19,'Comms Calendar'!$B$5:$B$504,"AMER",'Comms Calendar'!$AE$5:$AE$504,"<>Cancelled")&" · "&"EM "&COUNTIFS('Comms Calendar'!$O$5:$O$504,F19,'Comms Calendar'!$B$5:$B$504,"EMEA",'Comms Calendar'!$AE$5:$AE$504,"<>Cancelled")&" · "&"AP "&COUNTIFS('Comms Calendar'!$O$5:$O$504,F19,'Comms Calendar'!$B$5:$B$504,"APAC",'Comms Calendar'!$AE$5:$AE$504,"<>Cancelled")&" · "&"GL "&COUNTIFS('Comms Calendar'!$O$5:$O$504,F19,'Comms Calendar'!$B$5:$B$504,"Global",'Comms Calendar'!$AE$5:$AE$504,"<>Cancelled")) -> AM 0 · EM 1 · AP 0 · GL 0 | G21: =IF(G20=0,"","AM "&COUNTIFS('Comms Calendar'!$O$5:$O$504,G19,'Comms Calendar'!$B$5:$B$504,"AMER",'Comms Calendar'!$AE$5:$AE$504,"<>Cancelled")&" · "&"EM "&COUNTIFS('Comms Calendar'!$O$5:$O$504,G19,'Comms Calendar'!$B$5:$B$504,"EMEA",'Comms Calendar'!$AE$5:$AE$504,"<>Cancelled")&" · "&"AP "&COUNTIFS('Comms Calendar'!$O$5:$O$504,G19,'Comms Calendar'!$B$5:$B$504,"APAC",'Comms Calendar'!$AE$5:$AE$504,"<>Cancelled")&" · "&"GL "&COUNTIFS('Comms Calendar'!$O$5:$O$504,G19,'Comms Calendar'!$B$5:$B$504,"Global",'Comms Calendar'!$AE$5:$AE$504,"<>Cancelled")) | H21: =IF(H20=0,"","AM "&COUNTIFS('Comms Calendar'!$O$5:$O$504,H19,'Comms Calendar'!$B$5:$B$504,"AMER",'Comms Calendar'!$AE$5:$AE$504,"<>Cancelled")&" · "&"EM "&COUNTIFS('Comms Calendar'!$O$5:$O$504,H19,'Comms Calendar'!$B$5:$B$504,"EMEA",'Comms Calendar'!$AE$5:$AE$504,"<>Cancelled")&" · "&"AP "&COUNTIFS('Comms Calendar'!$O$5:$O$504,H19,'Comms Calendar'!$B$5:$B$504,"APAC",'Comms Calendar'!$AE$5:$AE$504,"<>Cancelled")&" · "&"GL "&COUNTIFS('Comms Calendar'!$O$5:$O$504,H19,'Comms Calendar'!$B$5:$B$504,"Global",'Comms Calendar'!$AE$5:$AE$504,"<>Cancelled"))
B22: =IF(B20=0,"",IFERROR(INDEX('Comms Calendar'!$G$5:$G$504,IF($F$3="All",MATCH(B19,'Comms Calendar'!$O$5:$O$504,0),MATCH(B19&"|"&$F$3,'Comms Calendar'!$AS$5:$AS$504,0))),"")&IF(B20>1," (+"&(B20-1)&" more)","")) | C22: =IF(C20=0,"",IFERROR(INDEX('Comms Calendar'!$G$5:$G$504,IF($F$3="All",MATCH(C19,'Comms Calendar'!$O$5:$O$504,0),MATCH(C19&"|"&$F$3,'Comms Calendar'!$AS$5:$AS$504,0))),"")&IF(C20>1," (+"&(C20-1)&" more)","")) | D22: =IF(D20=0,"",IFERROR(INDEX('Comms Calendar'!$G$5:$G$504,IF($F$3="All",MATCH(D19,'Comms Calendar'!$O$5:$O$504,0),MATCH(D19&"|"&$F$3,'Comms Calendar'!$AS$5:$AS$504,0))),"")&IF(D20>1," (+"&(D20-1)&" more)","")) | E22: =IF(E20=0,"",IFERROR(INDEX('Comms Calendar'!$G$5:$G$504,IF($F$3="All",MATCH(E19,'Comms Calendar'!$O$5:$O$504,0),MATCH(E19&"|"&$F$3,'Comms Calendar'!$AS$5:$AS$504,0))),"")&IF(E20>1," (+"&(E20-1)&" more)","")) -> Q4 Product Roadmap - Live Webinar | F22: =IF(F20=0,"",IFERROR(INDEX('Comms Calendar'!$G$5:$G$504,IF($F$3="All",MATCH(F19,'Comms Calendar'!$O$5:$O$504,0),MATCH(F19&"|"&$F$3,'Comms Calendar'!$AS$5:$AS$504,0))),"")&IF(F20>1," (+"&(F20-1)&" more)","")) -> Q4 Product Roadmap - EMEA session | G22: =IF(G20=0,"",IFERROR(INDEX('Comms Calendar'!$G$5:$G$504,IF($F$3="All",MATCH(G19,'Comms Calendar'!$O$5:$O$504,0),MATCH(G19&"|"&$F$3,'Comms Calendar'!$AS$5:$AS$504,0))),"")&IF(G20>1," (+"&(G20-1)&" more)","")) | H22: =IF(H20=0,"",IFERROR(INDEX('Comms Calendar'!$G$5:$G$504,IF($F$3="All",MATCH(H19,'Comms Calendar'!$O$5:$O$504,0),MATCH(H19&"|"&$F$3,'Comms Calendar'!$AS$5:$AS$504,0))),"")&IF(H20>1," (+"&(H20-1)&" more)",""))
B23: =H19+1 -> 46321 | C23: =B23+1 -> 46322 | D23: =C23+1 -> 46323 | E23: =D23+1 -> 46324 | F23: =E23+1 -> 46325 | G23: =F23+1 -> 46326 | H23: =G23+1 -> 46327
B24: =IF($F$3="All",COUNTIFS('Comms Calendar'!$O$5:$O$504,B23,'Comms Calendar'!$AE$5:$AE$504,"<>Cancelled"),COUNTIFS('Comms Calendar'!$O$5:$O$504,B23,'Comms Calendar'!$B$5:$B$504,$F$3,'Comms Calendar'!$AE$5:$AE$504,"<>Cancelled")) -> 0 | C24: =IF($F$3="All",COUNTIFS('Comms Calendar'!$O$5:$O$504,C23,'Comms Calendar'!$AE$5:$AE$504,"<>Cancelled"),COUNTIFS('Comms Calendar'!$O$5:$O$504,C23,'Comms Calendar'!$B$5:$B$504,$F$3,'Comms Calendar'!$AE$5:$AE$504,"<>Cancelled")) -> 0 | D24: =IF($F$3="All",COUNTIFS('Comms Calendar'!$O$5:$O$504,D23,'Comms Calendar'!$AE$5:$AE$504,"<>Cancelled"),COUNTIFS('Comms Calendar'!$O$5:$O$504,D23,'Comms Calendar'!$B$5:$B$504,$F$3,'Comms Calendar'!$AE$5:$AE$504,"<>Cancelled")) -> 1 | E24: =IF($F$3="All",COUNTIFS('Comms Calendar'!$O$5:$O$504,E23,'Comms Calendar'!$AE$5:$AE$504,"<>Cancelled"),COUNTIFS('Comms Calendar'!$O$5:$O$504,E23,'Comms Calendar'!$B$5:$B$504,$F$3,'Comms Calendar'!$AE$5:$AE$504,"<>Cancelled")) -> 1 | F24: =IF($F$3="All",COUNTIFS('Comms Calendar'!$O$5:$O$504,F23,'Comms Calendar'!$AE$5:$AE$504,"<>Cancelled"),COUNTIFS('Comms Calendar'!$O$5:$O$504,F23,'Comms Calendar'!$B$5:$B$504,$F$3,'Comms Calendar'!$AE$5:$AE$504,"<>Cancelled")) -> 0 | G24: =IF($F$3="All",COUNTIFS('Comms Calendar'!$O$5:$O$504,G23,'Comms Calendar'!$AE$5:$AE$504,"<>Cancelled"),COUNTIFS('Comms Calendar'!$O$5:$O$504,G23,'Comms Calendar'!$B$5:$B$504,$F$3,'Comms Calendar'!$AE$5:$AE$504,"<>Cancelled")) -> 0 | H24: =IF($F$3="All",COUNTIFS('Comms Calendar'!$O$5:$O$504,H23,'Comms Calendar'!$AE$5:$AE$504,"<>Cancelled"),COUNTIFS('Comms Calendar'!$O$5:$O$504,H23,'Comms Calendar'!$B$5:$B$504,$F$3,'Comms Calendar'!$AE$5:$AE$504,"<>Cancelled")) -> 0
B25: =IF(B24=0,"","AM "&COUNTIFS('Comms Calendar'!$O$5:$O$504,B23,'Comms Calendar'!$B$5:$B$504,"AMER",'Comms Calendar'!$AE$5:$AE$504,"<>Cancelled")&" · "&"EM "&COUNTIFS('Comms Calendar'!$O$5:$O$504,B23,'Comms Calendar'!$B$5:$B$504,"EMEA",'Comms Calendar'!$AE$5:$AE$504,"<>Cancelled")&" · "&"AP "&COUNTIFS('Comms Calendar'!$O$5:$O$504,B23,'Comms Calendar'!$B$5:$B$504,"APAC",'Comms Calendar'!$AE$5:$AE$504,"<>Cancelled")&" · "&"GL "&COUNTIFS('Comms Calendar'!$O$5:$O$504,B23,'Comms Calendar'!$B$5:$B$504,"Global",'Comms Calendar'!$AE$5:$AE$504,"<>Cancelled")) | C25: =IF(C24=0,"","AM "&COUNTIFS('Comms Calendar'!$O$5:$O$504,C23,'Comms Calendar'!$B$5:$B$504,"AMER",'Comms Calendar'!$AE$5:$AE$504,"<>Cancelled")&" · "&"EM "&COUNTIFS('Comms Calendar'!$O$5:$O$504,C23,'Comms Calendar'!$B$5:$B$504,"EMEA",'Comms Calendar'!$AE$5:$AE$504,"<>Cancelled")&" · "&"AP "&COUNTIFS('Comms Calendar'!$O$5:$O$504,C23,'Comms Calendar'!$B$5:$B$504,"APAC",'Comms Calendar'!$AE$5:$AE$504,"<>Cancelled")&" · "&"GL "&COUNTIFS('Comms Calendar'!$O$5:$O$504,C23,'Comms Calendar'!$B$5:$B$504,"Global",'Comms Calendar'!$AE$5:$AE$504,"<>Cancelled")) | D25: =IF(D24=0,"","AM "&COUNTIFS('Comms Calendar'!$O$5:$O$504,D23,'Comms Calendar'!$B$5:$B$504,"AMER",'Comms Calendar'!$AE$5:$AE$504,"<>Cancelled")&" · "&"EM "&COUNTIFS('Comms Calendar'!$O$5:$O$504,D23,'Comms Calendar'!$B$5:$B$504,"EMEA",'Comms Calendar'!$AE$5:$AE$504,"<>Cancelled")&" · "&"AP "&COUNTIFS('Comms Calendar'!$O$5:$O$504,D23,'Comms Calendar'!$B$5:$B$504,"APAC",'Comms Calendar'!$AE$5:$AE$504,"<>Cancelled")&" · "&"GL "&COUNTIFS('Comms Calendar'!$O$5:$O$504,D23,'Comms Calendar'!$B$5:$B$504,"Global",'Comms Calendar'!$AE$5:$AE$504,"<>Cancelled")) -> AM 0 · EM 0 · AP 1 · GL 0 | E25: =IF(E24=0,"","AM "&COUNTIFS('Comms Calendar'!$O$5:$O$504,E23,'Comms Calendar'!$B$5:$B$504,"AMER",'Comms Calendar'!$AE$5:$AE$504,"<>Cancelled")&" · "&"EM "&COUNTIFS('Comms Calendar'!$O$5:$O$504,E23,'Comms Calendar'!$B$5:$B$504,"EMEA",'Comms Calendar'!$AE$5:$AE$504,"<>Cancelled")&" · "&"AP "&COUNTIFS('Comms Calendar'!$O$5:$O$504,E23,'Comms Calendar'!$B$5:$B$504,"APAC",'Comms Calendar'!$AE$5:$AE$504,"<>Cancelled")&" · "&"GL "&COUNTIFS('Comms Calendar'!$O$5:$O$504,E23,'Comms Calendar'!$B$5:$B$504,"Global",'Comms Calendar'!$AE$5:$AE$504,"<>Cancelled")) -> AM 0 · EM 0 · AP 0 · GL 1 | F25: =IF(F24=0,"","AM "&COUNTIFS('Comms Calendar'!$O$5:$O$504,F23,'Comms Calendar'!$B$5:$B$504,"AMER",'Comms Calendar'!$AE$5:$AE$504,"<>Cancelled")&" · "&"EM "&COUNTIFS('Comms Calendar'!$O$5:$O$504,F23,'Comms Calendar'!$B$5:$B$504,"EMEA",'Comms Calendar'!$AE$5:$AE$504,"<>Cancelled")&" · "&"AP "&COUNTIFS('Comms Calendar'!$O$5:$O$504,F23,'Comms Calendar'!$B$5:$B$504,"APAC",'Comms Calendar'!$AE$5:$AE$504,"<>Cancelled")&" · "&"GL "&COUNTIFS('Comms Calendar'!$O$5:$O$504,F23,'Comms Calendar'!$B$5:$B$504,"Global",'Comms Calendar'!$AE$5:$AE$504,"<>Cancelled")) | G25: =IF(G24=0,"","AM "&COUNTIFS('Comms Calendar'!$O$5:$O$504,G23,'Comms Calendar'!$B$5:$B$504,"AMER",'Comms Calendar'!$AE$5:$AE$504,"<>Cancelled")&" · "&"EM "&COUNTIFS('Comms Calendar'!$O$5:$O$504,G23,'Comms Calendar'!$B$5:$B$504,"EMEA",'Comms Calendar'!$AE$5:$AE$504,"<>Cancelled")&" · "&"AP "&COUNTIFS('Comms Calendar'!$O$5:$O$504,G23,'Comms Calendar'!$B$5:$B$504,"APAC",'Comms Calendar'!$AE$5:$AE$504,"<>Cancelled")&" · "&"GL "&COUNTIFS('Comms Calendar'!$O$5:$O$504,G23,'Comms Calendar'!$B$5:$B$504,"Global",'Comms Calendar'!$AE$5:$AE$504,"<>Cancelled")) | H25: =IF(H24=0,"","AM "&COUNTIFS('Comms Calendar'!$O$5:$O$504,H23,'Comms Calendar'!$B$5:$B$504,"AMER",'Comms Calendar'!$AE$5:$AE$504,"<>Cancelled")&" · "&"EM "&COUNTIFS('Comms Calendar'!$O$5:$O$504,H23,'Comms Calendar'!$B$5:$B$504,"EMEA",'Comms Calendar'!$AE$5:$AE$504,"<>Cancelled")&" · "&"AP "&COUNTIFS('Comms Calendar'!$O$5:$O$504,H23,'Comms Calendar'!$B$5:$B$504,"APAC",'Comms Calendar'!$AE$5:$AE$504,"<>Cancelled")&" · "&"GL "&COUNTIFS('Comms Calendar'!$O$5:$O$504,H23,'Comms Calendar'!$B$5:$B$504,"Global",'Comms Calendar'!$AE$5:$AE$504,"<>Cancelled"))
B26: =IF(B24=0,"",IFERROR(INDEX('Comms Calendar'!$G$5:$G$504,IF($F$3="All",MATCH(B23,'Comms Calendar'!$O$5:$O$504,0),MATCH(B23&"|"&$F$3,'Comms Calendar'!$AS$5:$AS$504,0))),"")&IF(B24>1," (+"&(B24-1)&" more)","")) | C26: =IF(C24=0,"",IFERROR(INDEX('Comms Calendar'!$G$5:$G$504,IF($F$3="All",MATCH(C23,'Comms Calendar'!$O$5:$O$504,0),MATCH(C23&"|"&$F$3,'Comms Calendar'!$AS$5:$AS$504,0))),"")&IF(C24>1," (+"&(C24-1)&" more)","")) | D26: =IF(D24=0,"",IFERROR(INDEX('Comms Calendar'!$G$5:$G$504,IF($F$3="All",MATCH(D23,'Comms Calendar'!$O$5:$O$504,0),MATCH(D23&"|"&$F$3,'Comms Calendar'!$AS$5:$AS$504,0))),"")&IF(D24>1," (+"&(D24-1)&" more)","")) -> Q4 Product Roadmap - APAC session | E26: =IF(E24=0,"",IFERROR(INDEX('Comms Calendar'!$G$5:$G$504,IF($F$3="All",MATCH(E23,'Comms Calendar'!$O$5:$O$504,0),MATCH(E23&"|"&$F$3,'Comms Calendar'!$AS$5:$AS$504,0))),"")&IF(E24>1," (+"&(E24-1)&" more)","")) -> October customer newsletter | F26: =IF(F24=0,"",IFERROR(INDEX('Comms Calendar'!$G$5:$G$504,IF($F$3="All",MATCH(F23,'Comms Calendar'!$O$5:$O$504,0),MATCH(F23&"|"&$F$3,'Comms Calendar'!$AS$5:$AS$504,0))),"")&IF(F24>1," (+"&(F24-1)&" more)","")) | G26: =IF(G24=0,"",IFERROR(INDEX('Comms Calendar'!$G$5:$G$504,IF($F$3="All",MATCH(G23,'Comms Calendar'!$O$5:$O$504,0),MATCH(G23&"|"&$F$3,'Comms Calendar'!$AS$5:$AS$504,0))),"")&IF(G24>1," (+"&(G24-1)&" more)","")) | H26: =IF(H24=0,"",IFERROR(INDEX('Comms Calendar'!$G$5:$G$504,IF($F$3="All",MATCH(H23,'Comms Calendar'!$O$5:$O$504,0),MATCH(H23&"|"&$F$3,'Comms Calendar'!$AS$5:$AS$504,0))),"")&IF(H24>1," (+"&(H24-1)&" more)",""))
B27: =H23+1 -> 46328 | C27: =B27+1 -> 46329 | D27: =C27+1 -> 46330 | E27: =D27+1 -> 46331 | F27: =E27+1 -> 46332 | G27: =F27+1 -> 46333 | H27: =G27+1 -> 46334
B28: =IF($F$3="All",COUNTIFS('Comms Calendar'!$O$5:$O$504,B27,'Comms Calendar'!$AE$5:$AE$504,"<>Cancelled"),COUNTIFS('Comms Calendar'!$O$5:$O$504,B27,'Comms Calendar'!$B$5:$B$504,$F$3,'Comms Calendar'!$AE$5:$AE$504,"<>Cancelled")) -> 0 | C28: =IF($F$3="All",COUNTIFS('Comms Calendar'!$O$5:$O$504,C27,'Comms Calendar'!$AE$5:$AE$504,"<>Cancelled"),COUNTIFS('Comms Calendar'!$O$5:$O$504,C27,'Comms Calendar'!$B$5:$B$504,$F$3,'Comms Calendar'!$AE$5:$AE$504,"<>Cancelled")) -> 0 | D28: =IF($F$3="All",COUNTIFS('Comms Calendar'!$O$5:$O$504,D27,'Comms Calendar'!$AE$5:$AE$504,"<>Cancelled"),COUNTIFS('Comms Calendar'!$O$5:$O$504,D27,'Comms Calendar'!$B$5:$B$504,$F$3,'Comms Calendar'!$AE$5:$AE$504,"<>Cancelled")) -> 0 | E28: =IF($F$3="All",COUNTIFS('Comms Calendar'!$O$5:$O$504,E27,'Comms Calendar'!$AE$5:$AE$504,"<>Cancelled"),COUNTIFS('Comms Calendar'!$O$5:$O$504,E27,'Comms Calendar'!$B$5:$B$504,$F$3,'Comms Calendar'!$AE$5:$AE$504,"<>Cancelled")) -> 1 | F28: =IF($F$3="All",COUNTIFS('Comms Calendar'!$O$5:$O$504,F27,'Comms Calendar'!$AE$5:$AE$504,"<>Cancelled"),COUNTIFS('Comms Calendar'!$O$5:$O$504,F27,'Comms Calendar'!$B$5:$B$504,$F$3,'Comms Calendar'!$AE$5:$AE$504,"<>Cancelled")) -> 0 | G28: =IF($F$3="All",COUNTIFS('Comms Calendar'!$O$5:$O$504,G27,'Comms Calendar'!$AE$5:$AE$504,"<>Cancelled"),COUNTIFS('Comms Calendar'!$O$5:$O$504,G27,'Comms Calendar'!$B$5:$B$504,$F$3,'Comms Calendar'!$AE$5:$AE$504,"<>Cancelled")) -> 0 | H28: =IF($F$3="All",COUNTIFS('Comms Calendar'!$O$5:$O$504,H27,'Comms Calendar'!$AE$5:$AE$504,"<>Cancelled"),COUNTIFS('Comms Calendar'!$O$5:$O$504,H27,'Comms Calendar'!$B$5:$B$504,$F$3,'Comms Calendar'!$AE$5:$AE$504,"<>Cancelled")) -> 0
B29: =IF(B28=0,"","AM "&COUNTIFS('Comms Calendar'!$O$5:$O$504,B27,'Comms Calendar'!$B$5:$B$504,"AMER",'Comms Calendar'!$AE$5:$AE$504,"<>Cancelled")&" · "&"EM "&COUNTIFS('Comms Calendar'!$O$5:$O$504,B27,'Comms Calendar'!$B$5:$B$504,"EMEA",'Comms Calendar'!$AE$5:$AE$504,"<>Cancelled")&" · "&"AP "&COUNTIFS('Comms Calendar'!$O$5:$O$504,B27,'Comms Calendar'!$B$5:$B$504,"APAC",'Comms Calendar'!$AE$5:$AE$504,"<>Cancelled")&" · "&"GL "&COUNTIFS('Comms Calendar'!$O$5:$O$504,B27,'Comms Calendar'!$B$5:$B$504,"Global",'Comms Calendar'!$AE$5:$AE$504,"<>Cancelled")) | C29: =IF(C28=0,"","AM "&COUNTIFS('Comms Calendar'!$O$5:$O$504,C27,'Comms Calendar'!$B$5:$B$504,"AMER",'Comms Calendar'!$AE$5:$AE$504,"<>Cancelled")&" · "&"EM "&COUNTIFS('Comms Calendar'!$O$5:$O$504,C27,'Comms Calendar'!$B$5:$B$504,"EMEA",'Comms Calendar'!$AE$5:$AE$504,"<>Cancelled")&" · "&"AP "&COUNTIFS('Comms Calendar'!$O$5:$O$504,C27,'Comms Calendar'!$B$5:$B$504,"APAC",'Comms Calendar'!$AE$5:$AE$504,"<>Cancelled")&" · "&"GL "&COUNTIFS('Comms Calendar'!$O$5:$O$504,C27,'Comms Calendar'!$B$5:$B$504,"Global",'Comms Calendar'!$AE$5:$AE$504,"<>Cancelled")) | D29: =IF(D28=0,"","AM "&COUNTIFS('Comms Calendar'!$O$5:$O$504,D27,'Comms Calendar'!$B$5:$B$504,"AMER",'Comms Calendar'!$AE$5:$AE$504,"<>Cancelled")&" · "&"EM "&COUNTIFS('Comms Calendar'!$O$5:$O$504,D27,'Comms Calendar'!$B$5:$B$504,"EMEA",'Comms Calendar'!$AE$5:$AE$504,"<>Cancelled")&" · "&"AP "&COUNTIFS('Comms Calendar'!$O$5:$O$504,D27,'Comms Calendar'!$B$5:$B$504,"APAC",'Comms Calendar'!$AE$5:$AE$504,"<>Cancelled")&" · "&"GL "&COUNTIFS('Comms Calendar'!$O$5:$O$504,D27,'Comms Calendar'!$B$5:$B$504,"Global",'Comms Calendar'!$AE$5:$AE$504,"<>Cancelled")) | E29: =IF(E28=0,"","AM "&COUNTIFS('Comms Calendar'!$O$5:$O$504,E27,'Comms Calendar'!$B$5:$B$504,"AMER",'Comms Calendar'!$AE$5:$AE$504,"<>Cancelled")&" · "&"EM "&COUNTIFS('Comms Calendar'!$O$5:$O$504,E27,'Comms Calendar'!$B$5:$B$504,"EMEA",'Comms Calendar'!$AE$5:$AE$504,"<>Cancelled")&" · "&"AP "&COUNTIFS('Comms Calendar'!$O$5:$O$504,E27,'Comms Calendar'!$B$5:$B$504,"APAC",'Comms Calendar'!$AE$5:$AE$504,"<>Cancelled")&" · "&"GL "&COUNTIFS('Comms Calendar'!$O$5:$O$504,E27,'Comms Calendar'!$B$5:$B$504,"Global",'Comms Calendar'!$AE$5:$AE$504,"<>Cancelled")) -> AM 0 · EM 0 · AP 1 · GL 0 | F29: =IF(F28=0,"","AM "&COUNTIFS('Comms Calendar'!$O$5:$O$504,F27,'Comms Calendar'!$B$5:$B$504,"AMER",'Comms Calendar'!$AE$5:$AE$504,"<>Cancelled")&" · "&"EM "&COUNTIFS('Comms Calendar'!$O$5:$O$504,F27,'Comms Calendar'!$B$5:$B$504,"EMEA",'Comms Calendar'!$AE$5:$AE$504,"<>Cancelled")&" · "&"AP "&COUNTIFS('Comms Calendar'!$O$5:$O$504,F27,'Comms Calendar'!$B$5:$B$504,"APAC",'Comms Calendar'!$AE$5:$AE$504,"<>Cancelled")&" · "&"GL "&COUNTIFS('Comms Calendar'!$O$5:$O$504,F27,'Comms Calendar'!$B$5:$B$504,"Global",'Comms Calendar'!$AE$5:$AE$504,"<>Cancelled")) | G29: =IF(G28=0,"","AM "&COUNTIFS('Comms Calendar'!$O$5:$O$504,G27,'Comms Calendar'!$B$5:$B$504,"AMER",'Comms Calendar'!$AE$5:$AE$504,"<>Cancelled")&" · "&"EM "&COUNTIFS('Comms Calendar'!$O$5:$O$504,G27,'Comms Calendar'!$B$5:$B$504,"EMEA",'Comms Calendar'!$AE$5:$AE$504,"<>Cancelled")&" · "&"AP "&COUNTIFS('Comms Calendar'!$O$5:$O$504,G27,'Comms Calendar'!$B$5:$B$504,"APAC",'Comms Calendar'!$AE$5:$AE$504,"<>Cancelled")&" · "&"GL "&COUNTIFS('Comms Calendar'!$O$5:$O$504,G27,'Comms Calendar'!$B$5:$B$504,"Global",'Comms Calendar'!$AE$5:$AE$504,"<>Cancelled")) | H29: =IF(H28=0,"","AM "&COUNTIFS('Comms Calendar'!$O$5:$O$504,H27,'Comms Calendar'!$B$5:$B$504,"AMER",'Comms Calendar'!$AE$5:$AE$504,"<>Cancelled")&" · "&"EM "&COUNTIFS('Comms Calendar'!$O$5:$O$504,H27,'Comms Calendar'!$B$5:$B$504,"EMEA",'Comms Calendar'!$AE$5:$AE$504,"<>Cancelled")&" · "&"AP "&COUNTIFS('Comms Calendar'!$O$5:$O$504,H27,'Comms Calendar'!$B$5:$B$504,"APAC",'Comms Calendar'!$AE$5:$AE$504,"<>Cancelled")&" · "&"GL "&COUNTIFS('Comms Calendar'!$O$5:$O$504,H27,'Comms Calendar'!$B$5:$B$504,"Global",'Comms Calendar'!$AE$5:$AE$504,"<>Cancelled"))
B30: =IF(B28=0,"",IFERROR(INDEX('Comms Calendar'!$G$5:$G$504,IF($F$3="All",MATCH(B27,'Comms Calendar'!$O$5:$O$504,0),MATCH(B27&"|"&$F$3,'Comms Calendar'!$AS$5:$AS$504,0))),"")&IF(B28>1," (+"&(B28-1)&" more)","")) | C30: =IF(C28=0,"",IFERROR(INDEX('Comms Calendar'!$G$5:$G$504,IF($F$3="All",MATCH(C27,'Comms Calendar'!$O$5:$O$504,0),MATCH(C27&"|"&$F$3,'Comms Calendar'!$AS$5:$AS$504,0))),"")&IF(C28>1," (+"&(C28-1)&" more)","")) | D30: =IF(D28=0,"",IFERROR(INDEX('Comms Calendar'!$G$5:$G$504,IF($F$3="All",MATCH(D27,'Comms Calendar'!$O$5:$O$504,0),MATCH(D27&"|"&$F$3,'Comms Calendar'!$AS$5:$AS$504,0))),"")&IF(D28>1," (+"&(D28-1)&" more)","")) | E30: =IF(E28=0,"",IFERROR(INDEX('Comms Calendar'!$G$5:$G$504,IF($F$3="All",MATCH(E27,'Comms Calendar'!$O$5:$O$504,0),MATCH(E27&"|"&$F$3,'Comms Calendar'!$AS$5:$AS$504,0))),"")&IF(E28>1," (+"&(E28-1)&" more)","")) -> 3 ways teams in ANZ cut reporting time | F30: =IF(F28=0,"",IFERROR(INDEX('Comms Calendar'!$G$5:$G$504,IF($F$3="All",MATCH(F27,'Comms Calendar'!$O$5:$O$504,0),MATCH(F27&"|"&$F$3,'Comms Calendar'!$AS$5:$AS$504,0))),"")&IF(F28>1," (+"&(F28-1)&" more)","")) | G30: =IF(G28=0,"",IFERROR(INDEX('Comms Calendar'!$G$5:$G$504,IF($F$3="All",MATCH(G27,'Comms Calendar'!$O$5:$O$504,0),MATCH(G27&"|"&$F$3,'Comms Calendar'!$AS$5:$AS$504,0))),"")&IF(G28>1," (+"&(G28-1)&" more)","")) | H30: =IF(H28=0,"",IFERROR(INDEX('Comms Calendar'!$G$5:$G$504,IF($F$3="All",MATCH(H27,'Comms Calendar'!$O$5:$O$504,0),MATCH(H27&"|"&$F$3,'Comms Calendar'!$AS$5:$AS$504,0))),"")&IF(H28>1," (+"&(H28-1)&" more)",""))
B32: Legend: blue tint = 1-2 comms · orange tint = 3+ comms (check for overload) · yellow = today · grey = outside the month

Sheet Week View
B1: Week View — rolling 26 weeks
B3: First week (Monday): | D3: =TODAY()-WEEKDAY(TODAY(),3) -> 46300 | E3: Defaults to the current week — overwrite with any date to look elsewhere.
B5: Week Commencing | C5: AMER | D5: EMEA | E5: APAC | F5: Global | G5: Total | H5: Webinars | I5: Emails | J5: Social | K5: Events | L5: Customer-facing | M5: Not Ready | N5: Ops Involved | O5: Over Cap | P5: Clashes | Q5: Blackout
B6: =$D$3 -> 46300 | C6: =COUNTIFS('Comms Calendar'!$AI$5:$AI$504,$B6,'Comms Calendar'!$B$5:$B$504,"AMER",'Comms Calendar'!$AE$5:$AE$504,"<>Cancelled") -> 0 | D6: =COUNTIFS('Comms Calendar'!$AI$5:$AI$504,$B6,'Comms Calendar'!$B$5:$B$504,"EMEA",'Comms Calendar'!$AE$5:$AE$504,"<>Cancelled") -> 0 | E6: =COUNTIFS('Comms Calendar'!$AI$5:$AI$504,$B6,'Comms Calendar'!$B$5:$B$504,"APAC",'Comms Calendar'!$AE$5:$AE$504,"<>Cancelled") -> 0 | F6: =COUNTIFS('Comms Calendar'!$AI$5:$AI$504,$B6,'Comms Calendar'!$B$5:$B$504,"Global",'Comms Calendar'!$AE$5:$AE$504,"<>Cancelled") -> 0 | G6: =SUM(C6:F6) -> 0 | H6: =COUNTIFS('Comms Calendar'!$AI$5:$AI$504,$B6,'Comms Calendar'!$AR$5:$AR$504,"Webinar",'Comms Calendar'!$AE$5:$AE$504,"<>Cancelled") -> 0 | I6: =COUNTIFS('Comms Calendar'!$AI$5:$AI$504,$B6,'Comms Calendar'!$AR$5:$AR$504,"Email",'Comms Calendar'!$AE$5:$AE$504,"<>Cancelled") -> 0 | J6: =COUNTIFS('Comms Calendar'!$AI$5:$AI$504,$B6,'Comms Calendar'!$AR$5:$AR$504,"Social",'Comms Calendar'!$AE$5:$AE$504,"<>Cancelled") -> 0 | K6: =COUNTIFS('Comms Calendar'!$AI$5:$AI$504,$B6,'Comms Calendar'!$AR$5:$AR$504,"Event",'Comms Calendar'!$AE$5:$AE$504,"<>Cancelled") -> 0 | L6: =COUNTIFS('Comms Calendar'!$AI$5:$AI$504,$B6,'Comms Calendar'!$E$5:$E$504,"Customer",'Comms Calendar'!$AE$5:$AE$504,"<>Cancelled")+COUNTIFS('Comms Calendar'!$AI$5:$AI$504,$B6,'Comms Calendar'!$E$5:$E$504,"Customer + Prospect",'Comms Calendar'!$AE$5:$AE$504,"<>Cancelled") -> 0 | M6: =COUNTIFS('Comms Calendar'!$AI$5:$AI$504,$B6,'Comms Calendar'!$AF$5:$AF$504,"In Progress")+COUNTIFS('Comms Calendar'!$AI$5:$AI$504,$B6,'Comms Calendar'!$AF$5:$AF$504,"At Risk")+COUNTIFS('Comms Calendar'!$AI$5:$AI$504,$B6,'Comms Calendar'!$AF$5:$AF$504,"Overdue") -> 0 | N6: =COUNTIFS('Comms Calendar'!$AI$5:$AI$504,$B6,'Comms Calendar'!$AB$5:$AB$504,"Yes",'Comms Calendar'!$AE$5:$AE$504,"<>Cancelled") -> 0 | O6: =COUNTIFS('Comms Calendar'!$AI$5:$AI$504,$B6,'Comms Calendar'!$AL$5:$AL$504,"Over cap",'Comms Calendar'!$AE$5:$AE$504,"<>Cancelled") -> 0 | P6: =COUNTIFS('Comms Calendar'!$AI$5:$AI$504,$B6,'Comms Calendar'!$AM$5:$AM$504,"Clash",'Comms Calendar'!$AE$5:$AE$504,"<>Cancelled") -> 0 | Q6: =COUNTIFS('Comms Calendar'!$AI$5:$AI$504,$B6,'Comms Calendar'!$AN$5:$AN$504,"Blackout",'Comms Calendar'!$AE$5:$AE$504,"<>Cancelled") -> 0
B7: =B6+7 -> 46307 | C7: =COUNTIFS('Comms Calendar'!$AI$5:$AI$504,$B7,'Comms Calendar'!$B$5:$B$504,"AMER",'Comms Calendar'!$AE$5:$AE$504,"<>Cancelled") -> 3 | D7: =COUNTIFS('Comms Calendar'!$AI$5:$AI$504,$B7,'Comms Calendar'!$B$5:$B$504,"EMEA",'Comms Calendar'!$AE$5:$AE$504,"<>Cancelled") -> 1 | E7: =COUNTIFS('Comms Calendar'!$AI$5:$AI$504,$B7,'Comms Calendar'!$B$5:$B$504,"APAC",'Comms Calendar'!$AE$5:$AE$504,"<>Cancelled") -> 0 | F7: =COUNTIFS('Comms Calendar'!$AI$5:$AI$504,$B7,'Comms Calendar'!$B$5:$B$504,"Global",'Comms Calendar'!$AE$5:$AE$504,"<>Cancelled") -> 1 | G7: =SUM(C7:F7) -> 5 | H7: =COUNTIFS('Comms Calendar'!$AI$5:$AI$504,$B7,'Comms Calendar'!$AR$5:$AR$504,"Webinar",'Comms Calendar'!$AE$5:$AE$504,"<>Cancelled") -> 0 | I7: =COUNTIFS('Comms Calendar'!$AI$5:$AI$504,$B7,'Comms Calendar'!$AR$5:$AR$504,"Email",'Comms Calendar'!$AE$5:$AE$504,"<>Cancelled") -> 4 | J7: =COUNTIFS('Comms Calendar'!$AI$5:$AI$504,$B7,'Comms Calendar'!$AR$5:$AR$504,"Social",'Comms Calendar'!$AE$5:$AE$504,"<>Cancelled") -> 1 | K7: =COUNTIFS('Comms Calendar'!$AI$5:$AI$504,$B7,'Comms Calendar'!$AR$5:$AR$504,"Event",'Comms Calendar'!$AE$5:$AE$504,"<>Cancelled") -> 0 | L7: =COUNTIFS('Comms Calendar'!$AI$5:$AI$504,$B7,'Comms Calendar'!$E$5:$E$504,"Customer",'Comms Calendar'!$AE$5:$AE$504,"<>Cancelled")+COUNTIFS('Comms Calendar'!$AI$5:$AI$504,$B7,'Comms Calendar'!$E$5:$E$504,"Customer + Prospect",'Comms Calendar'!$AE$5:$AE$504,"<>Cancelled") -> 5 | M7: =COUNTIFS('Comms Calendar'!$AI$5:$AI$504,$B7,'Comms Calendar'!$AF$5:$AF$504,"In Progress")+COUNTIFS('Comms Calendar'!$AI$5:$AI$504,$B7,'Comms Calendar'!$AF$5:$AF$504,"At Risk")+COUNTIFS('Comms Calendar'!$AI$5:$AI$504,$B7,'Comms Calendar'!$AF$5:$AF$504,"Overdue") -> 2 | N7: =COUNTIFS('Comms Calendar'!$AI$5:$AI$504,$B7,'Comms Calendar'!$AB$5:$AB$504,"Yes",'Comms Calendar'!$AE$5:$AE$504,"<>Cancelled") -> 4 | O7: =COUNTIFS('Comms Calendar'!$AI$5:$AI$504,$B7,'Comms Calendar'!$AL$5:$AL$504,"Over cap",'Comms Calendar'!$AE$5:$AE$504,"<>Cancelled") -> 3 | P7: =COUNTIFS('Comms Calendar'!$AI$5:$AI$504,$B7,'Comms Calendar'!$AM$5:$AM$504,"Clash",'Comms Calendar'!$AE$5:$AE$504,"<>Cancelled") -> 2 | Q7: =COUNTIFS('Comms Calendar'!$AI$5:$AI$504,$B7,'Comms Calendar'!$AN$5:$AN$504,"Blackout",'Comms Calendar'!$AE$5:$AE$504,"<>Cancelled") -> 0
B8: =B7+7 -> 46314 | C8: =COUNTIFS('Comms Calendar'!$AI$5:$AI$504,$B8,'Comms Calendar'!$B$5:$B$504,"AMER",'Comms Calendar'!$AE$5:$AE$504,"<>Cancelled") -> 1 | D8: =COUNTIFS('Comms Calendar'!$AI$5:$AI$504,$B8,'Comms Calendar'!$B$5:$B$504,"EMEA",'Comms Calendar'!$AE$5:$AE$504,"<>Cancelled") -> 1 | E8: =COUNTIFS('Comms Calendar'!$AI$5:$AI$504,$B8,'Comms Calendar'!$B$5:$B$504,"APAC",'Comms Calendar'!$AE$5:$AE$504,"<>Cancelled") -> 0 | F8: =COUNTIFS('Comms Calendar'!$AI$5:$AI$504,$B8,'Comms Calendar'!$B$5:$B$504,"Global",'Comms Calendar'!$AE$5:$AE$504,"<>Cancelled") -> 0 | G8: =SUM(C8:F8) -> 2 | H8: =COUNTIFS('Comms Calendar'!$AI$5:$AI$504,$B8,'Comms Calendar'!$AR$5:$AR$504,"Webinar",'Comms Calendar'!$AE$5:$AE$504,"<>Cancelled") -> 2 | I8: =COUNTIFS('Comms Calendar'!$AI$5:$AI$504,$B8,'Comms Calendar'!$AR$5:$AR$504,"Email",'Comms Calendar'!$AE$5:$AE$504,"<>Cancelled") -> 0 | J8: =COUNTIFS('Comms Calendar'!$AI$5:$AI$504,$B8,'Comms Calendar'!$AR$5:$AR$504,"Social",'Comms Calendar'!$AE$5:$AE$504,"<>Cancelled") -> 0 | K8: =COUNTIFS('Comms Calendar'!$AI$5:$AI$504,$B8,'Comms Calendar'!$AR$5:$AR$504,"Event",'Comms Calendar'!$AE$5:$AE$504,"<>Cancelled") -> 0 | L8: =COUNTIFS('Comms Calendar'!$AI$5:$AI$504,$B8,'Comms Calendar'!$E$5:$E$504,"Customer",'Comms Calendar'!$AE$5:$AE$504,"<>Cancelled")+COUNTIFS('Comms Calendar'!$AI$5:$AI$504,$B8,'Comms Calendar'!$E$5:$E$504,"Customer + Prospect",'Comms Calendar'!$AE$5:$AE$504,"<>Cancelled") -> 2 | M8: =COUNTIFS('Comms Calendar'!$AI$5:$AI$504,$B8,'Comms Calendar'!$AF$5:$AF$504,"In Progress")+COUNTIFS('Comms Calendar'!$AI$5:$AI$504,$B8,'Comms Calendar'!$AF$5:$AF$504,"At Risk")+COUNTIFS('Comms Calendar'!$AI$5:$AI$504,$B8,'Comms Calendar'!$AF$5:$AF$504,"Overdue") -> 1 | N8: =COUNTIFS('Comms Calendar'!$AI$5:$AI$504,$B8,'Comms Calendar'!$AB$5:$AB$504,"Yes",'Comms Calendar'!$AE$5:$AE$504,"<>Cancelled") -> 2 | O8: =COUNTIFS('Comms Calendar'!$AI$5:$AI$504,$B8,'Comms Calendar'!$AL$5:$AL$504,"Over cap",'Comms Calendar'!$AE$5:$AE$504,"<>Cancelled") -> 0 | P8: =COUNTIFS('Comms Calendar'!$AI$5:$AI$504,$B8,'Comms Calendar'!$AM$5:$AM$504,"Clash",'Comms Calendar'!$AE$5:$AE$504,"<>Cancelled") -> 0 | Q8: =COUNTIFS('Comms Calendar'!$AI$5:$AI$504,$B8,'Comms Calendar'!$AN$5:$AN$504,"Blackout",'Comms Calendar'!$AE$5:$AE$504,"<>Cancelled") -> 0
B9: =B8+7 -> 46321 | C9: =COUNTIFS('Comms Calendar'!$AI$5:$AI$504,$B9,'Comms Calendar'!$B$5:$B$504,"AMER",'Comms Calendar'!$AE$5:$AE$504,"<>Cancelled") -> 0 | D9: =COUNTIFS('Comms Calendar'!$AI$5:$AI$504,$B9,'Comms Calendar'!$B$5:$B$504,"EMEA",'Comms Calendar'!$AE$5:$AE$504,"<>Cancelled") -> 0 | E9: =COUNTIFS('Comms Calendar'!$AI$5:$AI$504,$B9,'Comms Calendar'!$B$5:$B$504,"APAC",'Comms Calendar'!$AE$5:$AE$504,"<>Cancelled") -> 1 | F9: =COUNTIFS('Comms Calendar'!$AI$5:$AI$504,$B9,'Comms Calendar'!$B$5:$B$504,"Global",'Comms Calendar'!$AE$5:$AE$504,"<>Cancelled") -> 1 | G9: =SUM(C9:F9) -> 2 | H9: =COUNTIFS('Comms Calendar'!$AI$5:$AI$504,$B9,'Comms Calendar'!$AR$5:$AR$504,"Webinar",'Comms Calendar'!$AE$5:$AE$504,"<>Cancelled") -> 1 | I9: =COUNTIFS('Comms Calendar'!$AI$5:$AI$504,$B9,'Comms Calendar'!$AR$5:$AR$504,"Email",'Comms Calendar'!$AE$5:$AE$504,"<>Cancelled") -> 1 | J9: =COUNTIFS('Comms Calendar'!$AI$5:$AI$504,$B9,'Comms Calendar'!$AR$5:$AR$504,"Social",'Comms Calendar'!$AE$5:$AE$504,"<>Cancelled") -> 0 | K9: =COUNTIFS('Comms Calendar'!$AI$5:$AI$504,$B9,'Comms Calendar'!$AR$5:$AR$504,"Event",'Comms Calendar'!$AE$5:$AE$504,"<>Cancelled") -> 0 | L9: =COUNTIFS('Comms Calendar'!$AI$5:$AI$504,$B9,'Comms Calendar'!$E$5:$E$504,"Customer",'Comms Calendar'!$AE$5:$AE$504,"<>Cancelled")+COUNTIFS('Comms Calendar'!$AI$5:$AI$504,$B9,'Comms Calendar'!$E$5:$E$504,"Customer + Prospect",'Comms Calendar'!$AE$5:$AE$504,"<>Cancelled") -> 2 | M9: =COUNTIFS('Comms Calendar'!$AI$5:$AI$504,$B9,'Comms Calendar'!$AF$5:$AF$504,"In Progress")+COUNTIFS('Comms Calendar'!$AI$5:$AI$504,$B9,'Comms Calendar'!$AF$5:$AF$504,"At Risk")+COUNTIFS('Comms Calendar'!$AI$5:$AI$504,$B9,'Comms Calendar'!$AF$5:$AF$504,"Overdue") -> 2 | N9: =COUNTIFS('Comms Calendar'!$AI$5:$AI$504,$B9,'Comms Calendar'!$AB$5:$AB$504,"Yes",'Comms Calendar'!$AE$5:$AE$504,"<>Cancelled") -> 2 | O9: =COUNTIFS('Comms Calendar'!$AI$5:$AI$504,$B9,'Comms Calendar'!$AL$5:$AL$504,"Over cap",'Comms Calendar'!$AE$5:$AE$504,"<>Cancelled") -> 0 | P9: =COUNTIFS('Comms Calendar'!$AI$5:$AI$504,$B9,'Comms Calendar'!$AM$5:$AM$504,"Clash",'Comms Calendar'!$AE$5:$AE$504,"<>Cancelled") -> 0 | Q9: =COUNTIFS('Comms Calendar'!$AI$5:$AI$504,$B9,'Comms Calendar'!$AN$5:$AN$504,"Blackout",'Comms Calendar'!$AE$5:$AE$504,"<>Cancelled") -> 0
B10: =B9+7 -> 46328 | C10: =COUNTIFS('Comms Calendar'!$AI$5:$AI$504,$B10,'Comms Calendar'!$B$5:$B$504,"AMER",'Comms Calendar'!$AE$5:$AE$504,"<>Cancelled") -> 0 | D10: =COUNTIFS('Comms Calendar'!$AI$5:$AI$504,$B10,'Comms Calendar'!$B$5:$B$504,"EMEA",'Comms Calendar'!$AE$5:$AE$504,"<>Cancelled") -> 0 | E10: =COUNTIFS('Comms Calendar'!$AI$5:$AI$504,$B10,'Comms Calendar'!$B$5:$B$504,"APAC",'Comms Calendar'!$AE$5:$AE$504,"<>Cancelled") -> 1 | F10: =COUNTIFS('Comms Calendar'!$AI$5:$AI$504,$B10,'Comms Calendar'!$B$5:$B$504,"Global",'Comms Calendar'!$AE$5:$AE$504,"<>Cancelled") -> 0 | G10: =SUM(C10:F10) -> 1 | H10: =COUNTIFS('Comms Calendar'!$AI$5:$AI$504,$B10,'Comms Calendar'!$AR$5:$AR$504,"Webinar",'Comms Calendar'!$AE$5:$AE$504,"<>Cancelled") -> 0 | I10: =COUNTIFS('Comms Calendar'!$AI$5:$AI$504,$B10,'Comms Calendar'!$AR$5:$AR$504,"Email",'Comms Calendar'!$AE$5:$AE$504,"<>Cancelled") -> 1 | J10: =COUNTIFS('Comms Calendar'!$AI$5:$AI$504,$B10,'Comms Calendar'!$AR$5:$AR$504,"Social",'Comms Calendar'!$AE$5:$AE$504,"<>Cancelled") -> 0 | K10: =COUNTIFS('Comms Calendar'!$AI$5:$AI$504,$B10,'Comms Calendar'!$AR$5:$AR$504,"Event",'Comms Calendar'!$AE$5:$AE$504,"<>Cancelled") -> 0 | L10: =COUNTIFS('Comms Calendar'!$AI$5:$AI$504,$B10,'Comms Calendar'!$E$5:$E$504,"Customer",'Comms Calendar'!$AE$5:$AE$504,"<>Cancelled")+COUNTIFS('Comms Calendar'!$AI$5:$AI$504,$B10,'Comms Calendar'!$E$5:$E$504,"Customer + Prospect",'Comms Calendar'!$AE$5:$AE$504,"<>Cancelled") -> 0 | M10: =COUNTIFS('Comms Calendar'!$AI$5:$AI$504,$B10,'Comms Calendar'!$AF$5:$AF$504,"In Progress")+COUNTIFS('Comms Calendar'!$AI$5:$AI$504,$B10,'Comms Calendar'!$AF$5:$AF$504,"At Risk")+COUNTIFS('Comms Calendar'!$AI$5:$AI$504,$B10,'Comms Calendar'!$AF$5:$AF$504,"Overdue") -> 1 | N10: =COUNTIFS('Comms Calendar'!$AI$5:$AI$504,$B10,'Comms Calendar'!$AB$5:$AB$504,"Yes",'Comms Calendar'!$AE$5:$AE$504,"<>Cancelled") -> 1 | O10: =COUNTIFS('Comms Calendar'!$AI$5:$AI$504,$B10,'Comms Calendar'!$AL$5:$AL$504,"Over cap",'Comms Calendar'!$AE$5:$AE$504,"<>Cancelled") -> 0 | P10: =COUNTIFS('Comms Calendar'!$AI$5:$AI$504,$B10,'Comms Calendar'!$AM$5:$AM$504,"Clash",'Comms Calendar'!$AE$5:$AE$504,"<>Cancelled") -> 0 | Q10: =COUNTIFS('Comms Calendar'!$AI$5:$AI$504,$B10,'Comms Calendar'!$AN$5:$AN$504,"Blackout",'Comms Calendar'!$AE$5:$AE$504,"<>Cancelled") -> 0
B11: =B10+7 -> 46335 | C11: =COUNTIFS('Comms Calendar'!$AI$5:$AI$504,$B11,'Comms Calendar'!$B$5:$B$504,"AMER",'Comms Calendar'!$AE$5:$AE$504,"<>Cancelled") -> 0 | D11: =COUNTIFS('Comms Calendar'!$AI$5:$AI$504,$B11,'Comms Calendar'!$B$5:$B$504,"EMEA",'Comms Calendar'!$AE$5:$AE$504,"<>Cancelled") -> 1 | E11: =COUNTIFS('Comms Calendar'!$AI$5:$AI$504,$B11,'Comms Calendar'!$B$5:$B$504,"APAC",'Comms Calendar'!$AE$5:$AE$504,"<>Cancelled") -> 0 | F11: =COUNTIFS('Comms Calendar'!$AI$5:$AI$504,$B11,'Comms Calendar'!$B$5:$B$504,"Global",'Comms Calendar'!$AE$5:$AE$504,"<>Cancelled") -> 0 | G11: =SUM(C11:F11) -> 1 | H11: =COUNTIFS('Comms Calendar'!$AI$5:$AI$504,$B11,'Comms Calendar'!$AR$5:$AR$504,"Webinar",'Comms Calendar'!$AE$5:$AE$504,"<>Cancelled") -> 0 | I11: =COUNTIFS('Comms Calendar'!$AI$5:$AI$504,$B11,'Comms Calendar'!$AR$5:$AR$504,"Email",'Comms Calendar'!$AE$5:$AE$504,"<>Cancelled") -> 0 | J11: =COUNTIFS('Comms Calendar'!$AI$5:$AI$504,$B11,'Comms Calendar'!$AR$5:$AR$504,"Social",'Comms Calendar'!$AE$5:$AE$504,"<>Cancelled") -> 0 | K11: =COUNTIFS('Comms Calendar'!$AI$5:$AI$504,$B11,'Comms Calendar'!$AR$5:$AR$504,"Event",'Comms Calendar'!$AE$5:$AE$504,"<>Cancelled") -> 1 | L11: =COUNTIFS('Comms Calendar'!$AI$5:$AI$504,$B11,'Comms Calendar'!$E$5:$E$504,"Customer",'Comms Calendar'!$AE$5:$AE$504,"<>Cancelled")+COUNTIFS('Comms Calendar'!$AI$5:$AI$504,$B11,'Comms Calendar'!$E$5:$E$504,"Customer + Prospect",'Comms Calendar'!$AE$5:$AE$504,"<>Cancelled") -> 1 | M11: =COUNTIFS('Comms Calendar'!$AI$5:$AI$504,$B11,'Comms Calendar'!$AF$5:$AF$504,"In Progress")+COUNTIFS('Comms Calendar'!$AI$5:$AI$504,$B11,'Comms Calendar'!$AF$5:$AF$504,"At Risk")+COUNTIFS('Comms Calendar'!$AI$5:$AI$504,$B11,'Comms Calendar'!$AF$5:$AF$504,"Overdue") -> 0 | N11: =COUNTIFS('Comms Calendar'!$AI$5:$AI$504,$B11,'Comms Calendar'!$AB$5:$AB$504,"Yes",'Comms Calendar'!$AE$5:$AE$504,"<>Cancelled") -> 0 | O11: =COUNTIFS('Comms Calendar'!$AI$5:$AI$504,$B11,'Comms Calendar'!$AL$5:$AL$504,"Over cap",'Comms Calendar'!$AE$5:$AE$504,"<>Cancelled") -> 0 | P11: =COUNTIFS('Comms Calendar'!$AI$5:$AI$504,$B11,'Comms Calendar'!$AM$5:$AM$504,"Clash",'Comms Calendar'!$AE$5:$AE$504,"<>Cancelled") -> 0 | Q11: =COUNTIFS('Comms Calendar'!$AI$5:$AI$504,$B11,'Comms Calendar'!$AN$5:$AN$504,"Blackout",'Comms Calendar'!$AE$5:$AE$504,"<>Cancelled") -> 0
B12: =B11+7 -> 46342 | C12: =COUNTIFS('Comms Calendar'!$AI$5:$AI$504,$B12,'Comms Calendar'!$B$5:$B$504,"AMER",'Comms Calendar'!$AE$5:$AE$504,"<>Cancelled") -> 0 | D12: =COUNTIFS('Comms Calendar'!$AI$5:$AI$504,$B12,'Comms Calendar'!$B$5:$B$504,"EMEA",'Comms Calendar'!$AE$5:$AE$504,"<>Cancelled") -> 0 | E12: =COUNTIFS('Comms Calendar'!$AI$5:$AI$504,$B12,'Comms Calendar'!$B$5:$B$504,"APAC",'Comms Calendar'!$AE$5:$AE$504,"<>Cancelled") -> 0 | F12: =COUNTIFS('Comms Calendar'!$AI$5:$AI$504,$B12,'Comms Calendar'!$B$5:$B$504,"Global",'Comms Calendar'!$AE$5:$AE$504,"<>Cancelled") -> 2 | G12: =SUM(C12:F12) -> 2 | H12: =COUNTIFS('Comms Calendar'!$AI$5:$AI$504,$B12,'Comms Calendar'!$AR$5:$AR$504,"Webinar",'Comms Calendar'!$AE$5:$AE$504,"<>Cancelled") -> 0 | I12: =COUNTIFS('Comms Calendar'!$AI$5:$AI$504,$B12,'Comms Calendar'!$AR$5:$AR$504,"Email",'Comms Calendar'!$AE$5:$AE$504,"<>Cancelled") -> 0 | J12: =COUNTIFS('Comms Calendar'!$AI$5:$AI$504,$B12,'Comms Calendar'!$AR$5:$AR$504,"Social",'Comms Calendar'!$AE$5:$AE$504,"<>Cancelled") -> 0 | K12: =COUNTIFS('Comms Calendar'!$AI$5:$AI$504,$B12,'Comms Calendar'!$AR$5:$AR$504,"Event",'Comms Calendar'!$AE$5:$AE$504,"<>Cancelled") -> 0 | L12: =COUNTIFS('Comms Calendar'!$AI$5:$AI$504,$B12,'Comms Calendar'!$E$5:$E$504,"Customer",'Comms Calendar'!$AE$5:$AE$504,"<>Cancelled")+COUNTIFS('Comms Calendar'!$AI$5:$AI$504,$B12,'Comms Calendar'!$E$5:$E$504,"Customer + Prospect",'Comms Calendar'!$AE$5:$AE$504,"<>Cancelled") -> 2 | M12: =COUNTIFS('Comms Calendar'!$AI$5:$AI$504,$B12,'Comms Calendar'!$AF$5:$AF$504,"In Progress")+COUNTIFS('Comms Calendar'!$AI$5:$AI$504,$B12,'Comms Calendar'!$AF$5:$AF$504,"At Risk")+COUNTIFS('Comms Calendar'!$AI$5:$AI$504,$B12,'Comms Calendar'!$AF$5:$AF$504,"Overdue") -> 2 | N12: =COUNTIFS('Comms Calendar'!$AI$5:$AI$504,$B12,'Comms Calendar'!$AB$5:$AB$504,"Yes",'Comms Calendar'!$AE$5:$AE$504,"<>Cancelled") -> 0 | O12: =COUNTIFS('Comms Calendar'!$AI$5:$AI$504,$B12,'Comms Calendar'!$AL$5:$AL$504,"Over cap",'Comms Calendar'!$AE$5:$AE$504,"<>Cancelled") -> 0 | P12: =COUNTIFS('Comms Calendar'!$AI$5:$AI$504,$B12,'Comms Calendar'!$AM$5:$AM$504,"Clash",'Comms Calendar'!$AE$5:$AE$504,"<>Cancelled") -> 0 | Q12: =COUNTIFS('Comms Calendar'!$AI$5:$AI$504,$B12,'Comms Calendar'!$AN$5:$AN$504,"Blackout",'Comms Calendar'!$AE$5:$AE$504,"<>Cancelled") -> 0
B13: =B12+7 -> 46349 | C13: =COUNTIFS('Comms Calendar'!$AI$5:$AI$504,$B13,'Comms Calendar'!$B$5:$B$504,"AMER",'Comms Calendar'!$AE$5:$AE$504,"<>Cancelled") -> 1 | D13: =COUNTIFS('Comms Calendar'!$AI$5:$AI$504,$B13,'Comms Calendar'!$B$5:$B$504,"EMEA",'Comms Calendar'!$AE$5:$AE$504,"<>Cancelled") -> 0 | E13: =COUNTIFS('Comms Calendar'!$AI$5:$AI$504,$B13,'Comms Calendar'!$B$5:$B$504,"APAC",'Comms Calendar'!$AE$5:$AE$504,"<>Cancelled") -> 0 | F13: =COUNTIFS('Comms Calendar'!$AI$5:$AI$504,$B13,'Comms Calendar'!$B$5:$B$504,"Global",'Comms Calendar'!$AE$5:$AE$504,"<>Cancelled") -> 0 | G13: =SUM(C13:F13) -> 1 | H13: =COUNTIFS('Comms Calendar'!$AI$5:$AI$504,$B13,'Comms Calendar'!$AR$5:$AR$504,"Webinar",'Comms Calendar'!$AE$5:$AE$504,"<>Cancelled") -> 0 | I13: =COUNTIFS('Comms Calendar'!$AI$5:$AI$504,$B13,'Comms Calendar'!$AR$5:$AR$504,"Email",'Comms Calendar'!$AE$5:$AE$504,"<>Cancelled") -> 1 | J13: =COUNTIFS('Comms Calendar'!$AI$5:$AI$504,$B13,'Comms Calendar'!$AR$5:$AR$504,"Social",'Comms Calendar'!$AE$5:$AE$504,"<>Cancelled") -> 0 | K13: =COUNTIFS('Comms Calendar'!$AI$5:$AI$504,$B13,'Comms Calendar'!$AR$5:$AR$504,"Event",'Comms Calendar'!$AE$5:$AE$504,"<>Cancelled") -> 0 | L13: =COUNTIFS('Comms Calendar'!$AI$5:$AI$504,$B13,'Comms Calendar'!$E$5:$E$504,"Customer",'Comms Calendar'!$AE$5:$AE$504,"<>Cancelled")+COUNTIFS('Comms Calendar'!$AI$5:$AI$504,$B13,'Comms Calendar'!$E$5:$E$504,"Customer + Prospect",'Comms Calendar'!$AE$5:$AE$504,"<>Cancelled") -> 0 | M13: =COUNTIFS('Comms Calendar'!$AI$5:$AI$504,$B13,'Comms Calendar'!$AF$5:$AF$504,"In Progress")+COUNTIFS('Comms Calendar'!$AI$5:$AI$504,$B13,'Comms Calendar'!$AF$5:$AF$504,"At Risk")+COUNTIFS('Comms Calendar'!$AI$5:$AI$504,$B13,'Comms Calendar'!$AF$5:$AF$504,"Overdue") -> 1 | N13: =COUNTIFS('Comms Calendar'!$AI$5:$AI$504,$B13,'Comms Calendar'!$AB$5:$AB$504,"Yes",'Comms Calendar'!$AE$5:$AE$504,"<>Cancelled") -> 1 | O13: =COUNTIFS('Comms Calendar'!$AI$5:$AI$504,$B13,'Comms Calendar'!$AL$5:$AL$504,"Over cap",'Comms Calendar'!$AE$5:$AE$504,"<>Cancelled") -> 0 | P13: =COUNTIFS('Comms Calendar'!$AI$5:$AI$504,$B13,'Comms Calendar'!$AM$5:$AM$504,"Clash",'Comms Calendar'!$AE$5:$AE$504,"<>Cancelled") -> 0 | Q13: =COUNTIFS('Comms Calendar'!$AI$5:$AI$504,$B13,'Comms Calendar'!$AN$5:$AN$504,"Blackout",'Comms Calendar'!$AE$5:$AE$504,"<>Cancelled") -> 1
B14: =B13+7 -> 46356 | C14: =COUNTIFS('Comms Calendar'!$AI$5:$AI$504,$B14,'Comms Calendar'!$B$5:$B$504,"AMER",'Comms Calendar'!$AE$5:$AE$504,"<>Cancelled") -> 0 | D14: =COUNTIFS('Comms Calendar'!$AI$5:$AI$504,$B14,'Comms Calendar'!$B$5:$B$504,"EMEA",'Comms Calendar'!$AE$5:$AE$504,"<>Cancelled") -> 0 | E14: =COUNTIFS('Comms Calendar'!$AI$5:$AI$504,$B14,'Comms Calendar'!$B$5:$B$504,"APAC",'Comms Calendar'!$AE$5:$AE$504,"<>Cancelled") -> 0 | F14: =COUNTIFS('Comms Calendar'!$AI$5:$AI$504,$B14,'Comms Calendar'!$B$5:$B$504,"Global",'Comms Calendar'!$AE$5:$AE$504,"<>Cancelled") -> 0 | G14: =SUM(C14:F14) -> 0 | H14: =COUNTIFS('Comms Calendar'!$AI$5:$AI$504,$B14,'Comms Calendar'!$AR$5:$AR$504,"Webinar",'Comms Calendar'!$AE$5:$AE$504,"<>Cancelled") -> 0 | I14: =COUNTIFS('Comms Calendar'!$AI$5:$AI$504,$B14,'Comms Calendar'!$AR$5:$AR$504,"Email",'Comms Calendar'!$AE$5:$AE$504,"<>Cancelled") -> 0 | J14: =COUNTIFS('Comms Calendar'!$AI$5:$AI$504,$B14,'Comms Calendar'!$AR$5:$AR$504,"Social",'Comms Calendar'!$AE$5:$AE$504,"<>Cancelled") -> 0 | K14: =COUNTIFS('Comms Calendar'!$AI$5:$AI$504,$B14,'Comms Calendar'!$AR$5:$AR$504,"Event",'Comms Calendar'!$AE$5:$AE$504,"<>Cancelled") -> 0 | L14: =COUNTIFS('Comms Calendar'!$AI$5:$AI$504,$B14,'Comms Calendar'!$E$5:$E$504,"Customer",'Comms Calendar'!$AE$5:$AE$504,"<>Cancelled")+COUNTIFS('Comms Calendar'!$AI$5:$AI$504,$B14,'Comms Calendar'!$E$5:$E$504,"Customer + Prospect",'Comms Calendar'!$AE$5:$AE$504,"<>Cancelled") -> 0 | M14: =COUNTIFS('Comms Calendar'!$AI$5:$AI$504,$B14,'Comms Calendar'!$AF$5:$AF$504,"In Progress")+COUNTIFS('Comms Calendar'!$AI$5:$AI$504,$B14,'Comms Calendar'!$AF$5:$AF$504,"At Risk")+COUNTIFS('Comms Calendar'!$AI$5:$AI$504,$B14,'Comms Calendar'!$AF$5:$AF$504,"Overdue") -> 0 | N14: =COUNTIFS('Comms Calendar'!$AI$5:$AI$504,$B14,'Comms Calendar'!$AB$5:$AB$504,"Yes",'Comms Calendar'!$AE$5:$AE$504,"<>Cancelled") -> 0 | O14: =COUNTIFS('Comms Calendar'!$AI$5:$AI$504,$B14,'Comms Calendar'!$AL$5:$AL$504,"Over cap",'Comms Calendar'!$AE$5:$AE$504,"<>Cancelled") -> 0 | P14: =COUNTIFS('Comms Calendar'!$AI$5:$AI$504,$B14,'Comms Calendar'!$AM$5:$AM$504,"Clash",'Comms Calendar'!$AE$5:$AE$504,"<>Cancelled") -> 0 | Q14: =COUNTIFS('Comms Calendar'!$AI$5:$AI$504,$B14,'Comms Calendar'!$AN$5:$AN$504,"Blackout",'Comms Calendar'!$AE$5:$AE$504,"<>Cancelled") -> 0
B15: =B14+7 -> 46363 | C15: =COUNTIFS('Comms Calendar'!$AI$5:$AI$504,$B15,'Comms Calendar'!$B$5:$B$504,"AMER",'Comms Calendar'!$AE$5:$AE$504,"<>Cancelled") -> 0 | D15: =COUNTIFS('Comms Calendar'!$AI$5:$AI$504,$B15,'Comms Calendar'!$B$5:$B$504,"EMEA",'Comms Calendar'!$AE$5:$AE$504,"<>Cancelled") -> 0 | E15: =COUNTIFS('Comms Calendar'!$AI$5:$AI$504,$B15,'Comms Calendar'!$B$5:$B$504,"APAC",'Comms Calendar'!$AE$5:$AE$504,"<>Cancelled") -> 0 | F15: =COUNTIFS('Comms Calendar'!$AI$5:$AI$504,$B15,'Comms Calendar'!$B$5:$B$504,"Global",'Comms Calendar'!$AE$5:$AE$504,"<>Cancelled") -> 0 | G15: =SUM(C15:F15) -> 0 | H15: =COUNTIFS('Comms Calendar'!$AI$5:$AI$504,$B15,'Comms Calendar'!$AR$5:$AR$504,"Webinar",'Comms Calendar'!$AE$5:$AE$504,"<>Cancelled") -> 0 | I15: =COUNTIFS('Comms Calendar'!$AI$5:$AI$504,$B15,'Comms Calendar'!$AR$5:$AR$504,"Email",'Comms Calendar'!$AE$5:$AE$504,"<>Cancelled") -> 0 | J15: =COUNTIFS('Comms Calendar'!$AI$5:$AI$504,$B15,'Comms Calendar'!$AR$5:$AR$504,"Social",'Comms Calendar'!$AE$5:$AE$504,"<>Cancelled") -> 0 | K15: =COUNTIFS('Comms Calendar'!$AI$5:$AI$504,$B15,'Comms Calendar'!$AR$5:$AR$504,"Event",'Comms Calendar'!$AE$5:$AE$504,"<>Cancelled") -> 0 | L15: =COUNTIFS('Comms Calendar'!$AI$5:$AI$504,$B15,'Comms Calendar'!$E$5:$E$504,"Customer",'Comms Calendar'!$AE$5:$AE$504,"<>Cancelled")+COUNTIFS('Comms Calendar'!$AI$5:$AI$504,$B15,'Comms Calendar'!$E$5:$E$504,"Customer + Prospect",'Comms Calendar'!$AE$5:$AE$504,"<>Cancelled") -> 0 | M15: =COUNTIFS('Comms Calendar'!$AI$5:$AI$504,$B15,'Comms Calendar'!$AF$5:$AF$504,"In Progress")+COUNTIFS('Comms Calendar'!$AI$5:$AI$504,$B15,'Comms Calendar'!$AF$5:$AF$504,"At Risk")+COUNTIFS('Comms Calendar'!$AI$5:$AI$504,$B15,'Comms Calendar'!$AF$5:$AF$504,"Overdue") -> 0 | N15: =COUNTIFS('Comms Calendar'!$AI$5:$AI$504,$B15,'Comms Calendar'!$AB$5:$AB$504,"Yes",'Comms Calendar'!$AE$5:$AE$504,"<>Cancelled") -> 0 | O15: =COUNTIFS('Comms Calendar'!$AI$5:$AI$504,$B15,'Comms Calendar'!$AL$5:$AL$504,"Over cap",'Comms Calendar'!$AE$5:$AE$504,"<>Cancelled") -> 0 | P15: =COUNTIFS('Comms Calendar'!$AI$5:$AI$504,$B15,'Comms Calendar'!$AM$5:$AM$504,"Clash",'Comms Calendar'!$AE$5:$AE$504,"<>Cancelled") -> 0 | Q15: =COUNTIFS('Comms Calendar'!$AI$5:$AI$504,$B15,'Comms Calendar'!$AN$5:$AN$504,"Blackout",'Comms Calendar'!$AE$5:$AE$504,"<>Cancelled") -> 0
B16: =B15+7 -> 46370 | C16: =COUNTIFS('Comms Calendar'!$AI$5:$AI$504,$B16,'Comms Calendar'!$B$5:$B$504,"AMER",'Comms Calendar'!$AE$5:$AE$504,"<>Cancelled") -> 0 | D16: =COUNTIFS('Comms Calendar'!$AI$5:$AI$504,$B16,'Comms Calendar'!$B$5:$B$504,"EMEA",'Comms Calendar'!$AE$5:$AE$504,"<>Cancelled") -> 0 | E16: =COUNTIFS('Comms Calendar'!$AI$5:$AI$504,$B16,'Comms Calendar'!$B$5:$B$504,"APAC",'Comms Calendar'!$AE$5:$AE$504,"<>Cancelled") -> 0 | F16: =COUNTIFS('Comms Calendar'!$AI$5:$AI$504,$B16,'Comms Calendar'!$B$5:$B$504,"Global",'Comms Calendar'!$AE$5:$AE$504,"<>Cancelled") -> 1 | G16: =SUM(C16:F16) -> 1 | H16: =COUNTIFS('Comms Calendar'!$AI$5:$AI$504,$B16,'Comms Calendar'!$AR$5:$AR$504,"Webinar",'Comms Calendar'!$AE$5:$AE$504,"<>Cancelled") -> 0 | I16: =COUNTIFS('Comms Calendar'!$AI$5:$AI$504,$B16,'Comms Calendar'!$AR$5:$AR$504,"Email",'Comms Calendar'!$AE$5:$AE$504,"<>Cancelled") -> 1 | J16: =COUNTIFS('Comms Calendar'!$AI$5:$AI$504,$B16,'Comms Calendar'!$AR$5:$AR$504,"Social",'Comms Calendar'!$AE$5:$AE$504,"<>Cancelled") -> 0 | K16: =COUNTIFS('Comms Calendar'!$AI$5:$AI$504,$B16,'Comms Calendar'!$AR$5:$AR$504,"Event",'Comms Calendar'!$AE$5:$AE$504,"<>Cancelled") -> 0 | L16: =COUNTIFS('Comms Calendar'!$AI$5:$AI$504,$B16,'Comms Calendar'!$E$5:$E$504,"Customer",'Comms Calendar'!$AE$5:$AE$504,"<>Cancelled")+COUNTIFS('Comms Calendar'!$AI$5:$AI$504,$B16,'Comms Calendar'!$E$5:$E$504,"Customer + Prospect",'Comms Calendar'!$AE$5:$AE$504,"<>Cancelled") -> 1 | M16: =COUNTIFS('Comms Calendar'!$AI$5:$AI$504,$B16,'Comms Calendar'!$AF$5:$AF$504,"In Progress")+COUNTIFS('Comms Calendar'!$AI$5:$AI$504,$B16,'Comms Calendar'!$AF$5:$AF$504,"At Risk")+COUNTIFS('Comms Calendar'!$AI$5:$AI$504,$B16,'Comms Calendar'!$AF$5:$AF$504,"Overdue") -> 1 | N16: =COUNTIFS('Comms Calendar'!$AI$5:$AI$504,$B16,'Comms Calendar'!$AB$5:$AB$504,"Yes",'Comms Calendar'!$AE$5:$AE$504,"<>Cancelled") -> 1 | O16: =COUNTIFS('Comms Calendar'!$AI$5:$AI$504,$B16,'Comms Calendar'!$AL$5:$AL$504,"Over cap",'Comms Calendar'!$AE$5:$AE$504,"<>Cancelled") -> 0 | P16: =COUNTIFS('Comms Calendar'!$AI$5:$AI$504,$B16,'Comms Calendar'!$AM$5:$AM$504,"Clash",'Comms Calendar'!$AE$5:$AE$504,"<>Cancelled") -> 0 | Q16: =COUNTIFS('Comms Calendar'!$AI$5:$AI$504,$B16,'Comms Calendar'!$AN$5:$AN$504,"Blackout",'Comms Calendar'!$AE$5:$AE$504,"<>Cancelled") -> 0
B17: =B16+7 -> 46377 | C17: =COUNTIFS('Comms Calendar'!$AI$5:$AI$504,$B17,'Comms Calendar'!$B$5:$B$504,"AMER",'Comms Calendar'!$AE$5:$AE$504,"<>Cancelled") -> 0 | D17: =COUNTIFS('Comms Calendar'!$AI$5:$AI$504,$B17,'Comms Calendar'!$B$5:$B$504,"EMEA",'Comms Calendar'!$AE$5:$AE$504,"<>Cancelled") -> 0 | E17: =COUNTIFS('Comms Calendar'!$AI$5:$AI$504,$B17,'Comms Calendar'!$B$5:$B$504,"APAC",'Comms Calendar'!$AE$5:$AE$504,"<>Cancelled") -> 0 | F17: =COUNTIFS('Comms Calendar'!$AI$5:$AI$504,$B17,'Comms Calendar'!$B$5:$B$504,"Global",'Comms Calendar'!$AE$5:$AE$504,"<>Cancelled") -> 0 | G17: =SUM(C17:F17) -> 0 | H17: =COUNTIFS('Comms Calendar'!$AI$5:$AI$504,$B17,'Comms Calendar'!$AR$5:$AR$504,"Webinar",'Comms Calendar'!$AE$5:$AE$504,"<>Cancelled") -> 0 | I17: =COUNTIFS('Comms Calendar'!$AI$5:$AI$504,$B17,'Comms Calendar'!$AR$5:$AR$504,"Email",'Comms Calendar'!$AE$5:$AE$504,"<>Cancelled") -> 0 | J17: =COUNTIFS('Comms Calendar'!$AI$5:$AI$504,$B17,'Comms Calendar'!$AR$5:$AR$504,"Social",'Comms Calendar'!$AE$5:$AE$504,"<>Cancelled") -> 0 | K17: =COUNTIFS('Comms Calendar'!$AI$5:$AI$504,$B17,'Comms Calendar'!$AR$5:$AR$504,"Event",'Comms Calendar'!$AE$5:$AE$504,"<>Cancelled") -> 0 | L17: =COUNTIFS('Comms Calendar'!$AI$5:$AI$504,$B17,'Comms Calendar'!$E$5:$E$504,"Customer",'Comms Calendar'!$AE$5:$AE$504,"<>Cancelled")+COUNTIFS('Comms Calendar'!$AI$5:$AI$504,$B17,'Comms Calendar'!$E$5:$E$504,"Customer + Prospect",'Comms Calendar'!$AE$5:$AE$504,"<>Cancelled") -> 0 | M17: =COUNTIFS('Comms Calendar'!$AI$5:$AI$504,$B17,'Comms Calendar'!$AF$5:$AF$504,"In Progress")+COUNTIFS('Comms Calendar'!$AI$5:$AI$504,$B17,'Comms Calendar'!$AF$5:$AF$504,"At Risk")+COUNTIFS('Comms Calendar'!$AI$5:$AI$504,$B17,'Comms Calendar'!$AF$5:$AF$504,"Overdue") -> 0 | N17: =COUNTIFS('Comms Calendar'!$AI$5:$AI$504,$B17,'Comms Calendar'!$AB$5:$AB$504,"Yes",'Comms Calendar'!$AE$5:$AE$504,"<>Cancelled") -> 0 | O17: =COUNTIFS('Comms Calendar'!$AI$5:$AI$504,$B17,'Comms Calendar'!$AL$5:$AL$504,"Over cap",'Comms Calendar'!$AE$5:$AE$504,"<>Cancelled") -> 0 | P17: =COUNTIFS('Comms Calendar'!$AI$5:$AI$504,$B17,'Comms Calendar'!$AM$5:$AM$504,"Clash",'Comms Calendar'!$AE$5:$AE$504,"<>Cancelled") -> 0 | Q17: =COUNTIFS('Comms Calendar'!$AI$5:$AI$504,$B17,'Comms Calendar'!$AN$5:$AN$504,"Blackout",'Comms Calendar'!$AE$5:$AE$504,"<>Cancelled") -> 0
B18: =B17+7 -> 46384 | C18: =COUNTIFS('Comms Calendar'!$AI$5:$AI$504,$B18,'Comms Calendar'!$B$5:$B$504,"AMER",'Comms Calendar'!$AE$5:$AE$504,"<>Cancelled") -> 0 | D18: =COUNTIFS('Comms Calendar'!$AI$5:$AI$504,$B18,'Comms Calendar'!$B$5:$B$504,"EMEA",'Comms Calendar'!$AE$5:$AE$504,"<>Cancelled") -> 0 | E18: =COUNTIFS('Comms Calendar'!$AI$5:$AI$504,$B18,'Comms Calendar'!$B$5:$B$504,"APAC",'Comms Calendar'!$AE$5:$AE$504,"<>Cancelled") -> 0 | F18: =COUNTIFS('Comms Calendar'!$AI$5:$AI$504,$B18,'Comms Calendar'!$B$5:$B$504,"Global",'Comms Calendar'!$AE$5:$AE$504,"<>Cancelled") -> 0 | G18: =SUM(C18:F18) -> 0 | H18: =COUNTIFS('Comms Calendar'!$AI$5:$AI$504,$B18,'Comms Calendar'!$AR$5:$AR$504,"Webinar",'Comms Calendar'!$AE$5:$AE$504,"<>Cancelled") -> 0 | I18: =COUNTIFS('Comms Calendar'!$AI$5:$AI$504,$B18,'Comms Calendar'!$AR$5:$AR$504,"Email",'Comms Calendar'!$AE$5:$AE$504,"<>Cancelled") -> 0 | J18: =COUNTIFS('Comms Calendar'!$AI$5:$AI$504,$B18,'Comms Calendar'!$AR$5:$AR$504,"Social",'Comms Calendar'!$AE$5:$AE$504,"<>Cancelled") -> 0 | K18: =COUNTIFS('Comms Calendar'!$AI$5:$AI$504,$B18,'Comms Calendar'!$AR$5:$AR$504,"Event",'Comms Calendar'!$AE$5:$AE$504,"<>Cancelled") -> 0 | L18: =COUNTIFS('Comms Calendar'!$AI$5:$AI$504,$B18,'Comms Calendar'!$E$5:$E$504,"Customer",'Comms Calendar'!$AE$5:$AE$504,"<>Cancelled")+COUNTIFS('Comms Calendar'!$AI$5:$AI$504,$B18,'Comms Calendar'!$E$5:$E$504,"Customer + Prospect",'Comms Calendar'!$AE$5:$AE$504,"<>Cancelled") -> 0 | M18: =COUNTIFS('Comms Calendar'!$AI$5:$AI$504,$B18,'Comms Calendar'!$AF$5:$AF$504,"In Progress")+COUNTIFS('Comms Calendar'!$AI$5:$AI$504,$B18,'Comms Calendar'!$AF$5:$AF$504,"At Risk")+COUNTIFS('Comms Calendar'!$AI$5:$AI$504,$B18,'Comms Calendar'!$AF$5:$AF$504,"Overdue") -> 0 | N18: =COUNTIFS('Comms Calendar'!$AI$5:$AI$504,$B18,'Comms Calendar'!$AB$5:$AB$504,"Yes",'Comms Calendar'!$AE$5:$AE$504,"<>Cancelled") -> 0 | O18: =COUNTIFS('Comms Calendar'!$AI$5:$AI$504,$B18,'Comms Calendar'!$AL$5:$AL$504,"Over cap",'Comms Calendar'!$AE$5:$AE$504,"<>Cancelled") -> 0 | P18: =COUNTIFS('Comms Calendar'!$AI$5:$AI$504,$B18,'Comms Calendar'!$AM$5:$AM$504,"Clash",'Comms Calendar'!$AE$5:$AE$504,"<>Cancelled") -> 0 | Q18: =COUNTIFS('Comms Calendar'!$AI$5:$AI$504,$B18,'Comms Calendar'!$AN$5:$AN$504,"Blackout",'Comms Calendar'!$AE$5:$AE$504,"<>Cancelled") -> 0
... B31: =B30+7 -> 46475 | C31: =COUNTIFS('Comms Calendar'!$AI$5:$AI$504,$B31,'Comms Calendar'!$B$5:$B$504,"AMER",'Comms Calendar'!$AE$5:$AE$504,"<>Cancelled") -> 0 | D31: =COUNTIFS('Comms Calendar'!$AI$5:$AI$504,$B31,'Comms Calendar'!$B$5:$B$504,"EMEA",'Comms Calendar'!$AE$5:$AE$504,"<>Cancelled") -> 0 | E31: =COUNTIFS('Comms Calendar'!$AI$5:$AI$504,$B31,'Comms Calendar'!$B$5:$B$504,"APAC",'Comms Calendar'!$AE$5:$AE$504,"<>Cancelled") -> 0 | F31: =COUNTIFS('Comms Calendar'!$AI$5:$AI$504,$B31,'Comms Calendar'!$B$5:$B$504,"Global",'Comms Calendar'!$AE$5:$AE$504,"<>Cancelled") -> 0 | G31: =SUM(C31:F31) -> 0 | H31: =COUNTIFS('Comms Calendar'!$AI$5:$AI$504,$B31,'Comms Calendar'!$AR$5:$AR$504,"Webinar",'Comms Calendar'!$AE$5:$AE$504,"<>Cancelled") -> 0 | I31: =COUNTIFS('Comms Calendar'!$AI$5:$AI$504,$B31,'Comms Calendar'!$AR$5:$AR$504,"Email",'Comms Calendar'!$AE$5:$AE$504,"<>Cancelled") -> 0 | J31: =COUNTIFS('Comms Calendar'!$AI$5:$AI$504,$B31,'Comms Calendar'!$AR$5:$AR$504,"Social",'Comms Calendar'!$AE$5:$AE$504,"<>Cancelled") -> 0 | K31: =COUNTIFS('Comms Calendar'!$AI$5:$AI$504,$B31,'Comms Calendar'!$AR$5:$AR$504,"Event",'Comms Calendar'!$AE$5:$AE$504,"<>Cancelled") -> 0 | L31: =COUNTIFS('Comms Calendar'!$AI$5:$AI$504,$B31,'Comms Calendar'!$E$5:$E$504,"Customer",'Comms Calendar'!$AE$5:$AE$504,"<>Cancelled")+COUNTIFS('Comms Calendar'!$AI$5:$AI$504,$B31,'Comms Calendar'!$E$5:$E$504,"Customer + Prospect",'Comms Calendar'!$AE$5:$AE$504,"<>Cancelled") -> 0 | M31: =COUNTIFS('Comms Calendar'!$AI$5:$AI$504,$B31,'Comms Calendar'!$AF$5:$AF$504,"In Progress")+COUNTIFS('Comms Calendar'!$AI$5:$AI$504,$B31,'Comms Calendar'!$AF$5:$AF$504,"At Risk")+COUNTIFS('Comms Calendar'!$AI$5:$AI$504,$B31,'Comms Calendar'!$AF$5:$AF$504,"Overdue") -> 0 | N31: =COUNTIFS('Comms Calendar'!$AI$5:$AI$504,$B31,'Comms Calendar'!$AB$5:$AB$504,"Yes",'Comms Calendar'!$AE$5:$AE$504,"<>Cancelled") -> 0 | O31: =COUNTIFS('Comms Calendar'!$AI$5:$AI$504,$B31,'Comms Calendar'!$AL$5:$AL$504,"Over cap",'Comms Calendar'!$AE$5:$AE$504,"<>Cancelled") -> 0 | P31: =COUNTIFS('Comms Calendar'!$AI$5:$AI$504,$B31,'Comms Calendar'!$AM$5:$AM$504,"Clash",'Comms Calendar'!$AE$5:$AE$504,"<>Cancelled") -> 0 | Q31: =COUNTIFS('Comms Calendar'!$AI$5:$AI$504,$B31,'Comms Calendar'!$AN$5:$AN$504,"Blackout",'Comms Calendar'!$AE$5:$AE$504,"<>Cancelled") -> 0
B33: Red = needs attention. Orange total = busy week (6+ comms) — check audiences aren't being overloaded.

Sheet Dashboard
B1: Alignment Dashboard
B2: ="As of "&TEXT(TODAY(),"dd mmm yyyy")&" · excludes cancelled comms" -> As of 08 Oct 2026 · excludes cancelled comms
B4: Headline numbers
B5: Comms planned (all dates) | C5: =COUNTIFS('Comms Calendar'!$O$5:$O$504,"<>",'Comms Calendar'!$AE$5:$AE$504,"<>Cancelled") -> 15
B6: Launching next 7 days | C6: =COUNTIFS('Comms Calendar'!$O$5:$O$504,">="&TODAY(),'Comms Calendar'!$O$5:$O$504,"<"&TODAY()+7,'Comms Calendar'!$AE$5:$AE$504,"<>Cancelled") -> 3
B7: Launching next 30 days | C7: =COUNTIFS('Comms Calendar'!$O$5:$O$504,">="&TODAY(),'Comms Calendar'!$O$5:$O$504,"<"&TODAY()+30,'Comms Calendar'!$AE$5:$AE$504,"<>Cancelled") -> 10
B8: Ready rate (open comms) | C8: =IFERROR(COUNTIF('Comms Calendar'!$AF$5:$AF$504,"Ready")/(COUNTIF('Comms Calendar'!$AF$5:$AF$504,"Ready")+COUNTIF('Comms Calendar'!$AF$5:$AF$504,"In Progress")+COUNTIF('Comms Calendar'!$AF$5:$AF$504,"At Risk")+COUNTIF('Comms Calendar'!$AF$5:$AF$504,"Overdue")),0) -> 0.33333333
B9: At Risk + Overdue | C9: =COUNTIF('Comms Calendar'!$AF$5:$AF$504,"At Risk")+COUNTIF('Comms Calendar'!$AF$5:$AF$504,"Overdue") -> 2
B10: Waiting on Ops | C10: =COUNTIFS('Comms Calendar'!$AB$5:$AB$504,"Yes",'Comms Calendar'!$AD$5:$AD$504,"<>Yes",'Comms Calendar'!$AE$5:$AE$504,"<>Launched",'Comms Calendar'!$AE$5:$AE$504,"<>Cancelled",'Comms Calendar'!$O$5:$O$504,"<>") -> 8
B11: Frequency cap breaches | C11: =COUNTIFS('Comms Calendar'!$AL$5:$AL$504,"Over cap",'Comms Calendar'!$AE$5:$AE$504,"<>Cancelled") -> 3
B12: Date clashes | C12: =COUNTIFS('Comms Calendar'!$AM$5:$AM$504,"Clash",'Comms Calendar'!$AE$5:$AE$504,"<>Cancelled") -> 2
B13: On blackout dates | C13: =COUNTIFS('Comms Calendar'!$AN$5:$AN$504,"Blackout",'Comms Calendar'!$AE$5:$AE$504,"<>Cancelled") -> 1
B15: Comms by region × channel
B16: Region | C16: Webinar | D16: Email | E16: Social | F16: Event | G16: PR | H16: In-app | I16: Other | J16: Total
B17: AMER | C17: =COUNTIFS('Comms Calendar'!$B$5:$B$504,"AMER",'Comms Calendar'!$AR$5:$AR$504,"Webinar",'Comms Calendar'!$AE$5:$AE$504,"<>Cancelled") -> 1 | D17: =COUNTIFS('Comms Calendar'!$B$5:$B$504,"AMER",'Comms Calendar'!$AR$5:$AR$504,"Email",'Comms Calendar'!$AE$5:$AE$504,"<>Cancelled") -> 4 | E17: =COUNTIFS('Comms Calendar'!$B$5:$B$504,"AMER",'Comms Calendar'!$AR$5:$AR$504,"Social",'Comms Calendar'!$AE$5:$AE$504,"<>Cancelled") -> 0 | F17: =COUNTIFS('Comms Calendar'!$B$5:$B$504,"AMER",'Comms Calendar'!$AR$5:$AR$504,"Event",'Comms Calendar'!$AE$5:$AE$504,"<>Cancelled") -> 0 | G17: =COUNTIFS('Comms Calendar'!$B$5:$B$504,"AMER",'Comms Calendar'!$AR$5:$AR$504,"PR",'Comms Calendar'!$AE$5:$AE$504,"<>Cancelled") -> 0 | H17: =COUNTIFS('Comms Calendar'!$B$5:$B$504,"AMER",'Comms Calendar'!$AR$5:$AR$504,"In-app",'Comms Calendar'!$AE$5:$AE$504,"<>Cancelled") -> 0 | I17: =COUNTIFS('Comms Calendar'!$B$5:$B$504,"AMER",'Comms Calendar'!$O$5:$O$504,"<>",'Comms Calendar'!$AE$5:$AE$504,"<>Cancelled")-SUM(C17:H17) -> 0 | J17: =SUM(C17:I17) -> 5
B18: EMEA | C18: =COUNTIFS('Comms Calendar'!$B$5:$B$504,"EMEA",'Comms Calendar'!$AR$5:$AR$504,"Webinar",'Comms Calendar'!$AE$5:$AE$504,"<>Cancelled") -> 1 | D18: =COUNTIFS('Comms Calendar'!$B$5:$B$504,"EMEA",'Comms Calendar'!$AR$5:$AR$504,"Email",'Comms Calendar'!$AE$5:$AE$504,"<>Cancelled") -> 1 | E18: =COUNTIFS('Comms Calendar'!$B$5:$B$504,"EMEA",'Comms Calendar'!$AR$5:$AR$504,"Social",'Comms Calendar'!$AE$5:$AE$504,"<>Cancelled") -> 0 | F18: =COUNTIFS('Comms Calendar'!$B$5:$B$504,"EMEA",'Comms Calendar'!$AR$5:$AR$504,"Event",'Comms Calendar'!$AE$5:$AE$504,"<>Cancelled") -> 1 | G18: =COUNTIFS('Comms Calendar'!$B$5:$B$504,"EMEA",'Comms Calendar'!$AR$5:$AR$504,"PR",'Comms Calendar'!$AE$5:$AE$504,"<>Cancelled") -> 0 | H18: =COUNTIFS('Comms Calendar'!$B$5:$B$504,"EMEA",'Comms Calendar'!$AR$5:$AR$504,"In-app",'Comms Calendar'!$AE$5:$AE$504,"<>Cancelled") -> 0 | I18: =COUNTIFS('Comms Calendar'!$B$5:$B$504,"EMEA",'Comms Calendar'!$O$5:$O$504,"<>",'Comms Calendar'!$AE$5:$AE$504,"<>Cancelled")-SUM(C18:H18) -> 0 | J18: =SUM(C18:I18) -> 3
B19: APAC | C19: =COUNTIFS('Comms Calendar'!$B$5:$B$504,"APAC",'Comms Calendar'!$AR$5:$AR$504,"Webinar",'Comms Calendar'!$AE$5:$AE$504,"<>Cancelled") -> 1 | D19: =COUNTIFS('Comms Calendar'!$B$5:$B$504,"APAC",'Comms Calendar'!$AR$5:$AR$504,"Email",'Comms Calendar'!$AE$5:$AE$504,"<>Cancelled") -> 1 | E19: =COUNTIFS('Comms Calendar'!$B$5:$B$504,"APAC",'Comms Calendar'!$AR$5:$AR$504,"Social",'Comms Calendar'!$AE$5:$AE$504,"<>Cancelled") -> 0 | F19: =COUNTIFS('Comms Calendar'!$B$5:$B$504,"APAC",'Comms Calendar'!$AR$5:$AR$504,"Event",'Comms Calendar'!$AE$5:$AE$504,"<>Cancelled") -> 0 | G19: =COUNTIFS('Comms Calendar'!$B$5:$B$504,"APAC",'Comms Calendar'!$AR$5:$AR$504,"PR",'Comms Calendar'!$AE$5:$AE$504,"<>Cancelled") -> 0 | H19: =COUNTIFS('Comms Calendar'!$B$5:$B$504,"APAC",'Comms Calendar'!$AR$5:$AR$504,"In-app",'Comms Calendar'!$AE$5:$AE$504,"<>Cancelled") -> 0 | I19: =COUNTIFS('Comms Calendar'!$B$5:$B$504,"APAC",'Comms Calendar'!$O$5:$O$504,"<>",'Comms Calendar'!$AE$5:$AE$504,"<>Cancelled")-SUM(C19:H19) -> 0 | J19: =SUM(C19:I19) -> 2
B20: Global | C20: =COUNTIFS('Comms Calendar'!$B$5:$B$504,"Global",'Comms Calendar'!$AR$5:$AR$504,"Webinar",'Comms Calendar'!$AE$5:$AE$504,"<>Cancelled") -> 0 | D20: =COUNTIFS('Comms Calendar'!$B$5:$B$504,"Global",'Comms Calendar'!$AR$5:$AR$504,"Email",'Comms Calendar'!$AE$5:$AE$504,"<>Cancelled") -> 2 | E20: =COUNTIFS('Comms Calendar'!$B$5:$B$504,"Global",'Comms Calendar'!$AR$5:$AR$504,"Social",'Comms Calendar'!$AE$5:$AE$504,"<>Cancelled") -> 1 | F20: =COUNTIFS('Comms Calendar'!$B$5:$B$504,"Global",'Comms Calendar'!$AR$5:$AR$504,"Event",'Comms Calendar'!$AE$5:$AE$504,"<>Cancelled") -> 0 | G20: =COUNTIFS('Comms Calendar'!$B$5:$B$504,"Global",'Comms Calendar'!$AR$5:$AR$504,"PR",'Comms Calendar'!$AE$5:$AE$504,"<>Cancelled") -> 1 | H20: =COUNTIFS('Comms Calendar'!$B$5:$B$504,"Global",'Comms Calendar'!$AR$5:$AR$504,"In-app",'Comms Calendar'!$AE$5:$AE$504,"<>Cancelled") -> 1 | I20: =COUNTIFS('Comms Calendar'!$B$5:$B$504,"Global",'Comms Calendar'!$O$5:$O$504,"<>",'Comms Calendar'!$AE$5:$AE$504,"<>Cancelled")-SUM(C20:H20) -> 0 | J20: =SUM(C20:I20) -> 5
B21: Total | C21: =SUM(C17:C20) -> 3 | D21: =SUM(D17:D20) -> 8 | E21: =SUM(E17:E20) -> 1 | F21: =SUM(F17:F20) -> 1 | G21: =SUM(G17:G20) -> 1 | H21: =SUM(H17:H20) -> 1 | I21: =SUM(I17:I20) -> 0 | J21: =SUM(C21:I21) -> 15
B23: Readiness by region
B24: Region | C24: Ready | D24: In Progress | E24: At Risk | F24: Overdue | G24: On hold | H24: Launched | I24: Waiting on Ops
B25: AMER | C25: =COUNTIFS('Comms Calendar'!$B$5:$B$504,"AMER",'Comms Calendar'!$AF$5:$AF$504,"Ready") -> 3 | D25: =COUNTIFS('Comms Calendar'!$B$5:$B$504,"AMER",'Comms Calendar'!$AF$5:$AF$504,"In Progress") -> 1 | E25: =COUNTIFS('Comms Calendar'!$B$5:$B$504,"AMER",'Comms Calendar'!$AF$5:$AF$504,"At Risk") -> 1 | F25: =COUNTIFS('Comms Calendar'!$B$5:$B$504,"AMER",'Comms Calendar'!$AF$5:$AF$504,"Overdue") -> 0 | G25: =COUNTIFS('Comms Calendar'!$B$5:$B$504,"AMER",'Comms Calendar'!$AF$5:$AF$504,"On hold") -> 0 | H25: =COUNTIFS('Comms Calendar'!$B$5:$B$504,"AMER",'Comms Calendar'!$AF$5:$AF$504,"Launched") -> 0 | I25: =COUNTIFS('Comms Calendar'!$B$5:$B$504,"AMER",'Comms Calendar'!$AB$5:$AB$504,"Yes",'Comms Calendar'!$AD$5:$AD$504,"<>Yes",'Comms Calendar'!$AE$5:$AE$504,"<>Launched",'Comms Calendar'!$AE$5:$AE$504,"<>Cancelled",'Comms Calendar'!$O$5:$O$504,"<>") -> 2
B26: EMEA | C26: =COUNTIFS('Comms Calendar'!$B$5:$B$504,"EMEA",'Comms Calendar'!$AF$5:$AF$504,"Ready") -> 1 | D26: =COUNTIFS('Comms Calendar'!$B$5:$B$504,"EMEA",'Comms Calendar'!$AF$5:$AF$504,"In Progress") -> 1 | E26: =COUNTIFS('Comms Calendar'!$B$5:$B$504,"EMEA",'Comms Calendar'!$AF$5:$AF$504,"At Risk") -> 1 | F26: =COUNTIFS('Comms Calendar'!$B$5:$B$504,"EMEA",'Comms Calendar'!$AF$5:$AF$504,"Overdue") -> 0 | G26: =COUNTIFS('Comms Calendar'!$B$5:$B$504,"EMEA",'Comms Calendar'!$AF$5:$AF$504,"On hold") -> 0 | H26: =COUNTIFS('Comms Calendar'!$B$5:$B$504,"EMEA",'Comms Calendar'!$AF$5:$AF$504,"Launched") -> 0 | I26: =COUNTIFS('Comms Calendar'!$B$5:$B$504,"EMEA",'Comms Calendar'!$AB$5:$AB$504,"Yes",'Comms Calendar'!$AD$5:$AD$504,"<>Yes",'Comms Calendar'!$AE$5:$AE$504,"<>Launched",'Comms Calendar'!$AE$5:$AE$504,"<>Cancelled",'Comms Calendar'!$O$5:$O$504,"<>") -> 2
B27: APAC | C27: =COUNTIFS('Comms Calendar'!$B$5:$B$504,"APAC",'Comms Calendar'!$AF$5:$AF$504,"Ready") -> 0 | D27: =COUNTIFS('Comms Calendar'!$B$5:$B$504,"APAC",'Comms Calendar'!$AF$5:$AF$504,"In Progress") -> 2 | E27: =COUNTIFS('Comms Calendar'!$B$5:$B$504,"APAC",'Comms Calendar'!$AF$5:$AF$504,"At Risk") -> 0 | F27: =COUNTIFS('Comms Calendar'!$B$5:$B$504,"APAC",'Comms Calendar'!$AF$5:$AF$504,"Overdue") -> 0 | G27: =COUNTIFS('Comms Calendar'!$B$5:$B$504,"APAC",'Comms Calendar'!$AF$5:$AF$504,"On hold") -> 0 | H27: =COUNTIFS('Comms Calendar'!$B$5:$B$504,"APAC",'Comms Calendar'!$AF$5:$AF$504,"Launched") -> 0 | I27: =COUNTIFS('Comms Calendar'!$B$5:$B$504,"APAC",'Comms Calendar'!$AB$5:$AB$504,"Yes",'Comms Calendar'!$AD$5:$AD$504,"<>Yes",'Comms Calendar'!$AE$5:$AE$504,"<>Launched",'Comms Calendar'!$AE$5:$AE$504,"<>Cancelled",'Comms Calendar'!$O$5:$O$504,"<>") -> 2
B28: Global | C28: =COUNTIFS('Comms Calendar'!$B$5:$B$504,"Global",'Comms Calendar'!$AF$5:$AF$504,"Ready") -> 1 | D28: =COUNTIFS('Comms Calendar'!$B$5:$B$504,"Global",'Comms Calendar'!$AF$5:$AF$504,"In Progress") -> 4 | E28: =COUNTIFS('Comms Calendar'!$B$5:$B$504,"Global",'Comms Calendar'!$AF$5:$AF$504,"At Risk") -> 0 | F28: =COUNTIFS('Comms Calendar'!$B$5:$B$504,"Global",'Comms Calendar'!$AF$5:$AF$504,"Overdue") -> 0 | G28: =COUNTIFS('Comms Calendar'!$B$5:$B$504,"Global",'Comms Calendar'!$AF$5:$AF$504,"On hold") -> 0 | H28: =COUNTIFS('Comms Calendar'!$B$5:$B$504,"Global",'Comms Calendar'!$AF$5:$AF$504,"Launched") -> 0 | I28: =COUNTIFS('Comms Calendar'!$B$5:$B$504,"Global",'Comms Calendar'!$AB$5:$AB$504,"Yes",'Comms Calendar'!$AD$5:$AD$504,"<>Yes",'Comms Calendar'!$AE$5:$AE$504,"<>Launched",'Comms Calendar'!$AE$5:$AE$504,"<>Cancelled",'Comms Calendar'!$O$5:$O$504,"<>") -> 2
B29: Total | C29: =SUM(C25:C28) -> 5 | D29: =SUM(D25:D28) -> 8 | E29: =SUM(E25:E28) -> 2 | F29: =SUM(F25:F28) -> 0 | G29: =SUM(G25:G28) -> 0 | H29: =SUM(H25:H28) -> 0 | I29: =SUM(I25:I28) -> 8
B31: Comms by region × month (next 6 months)
B32: Region | C32: =DATE(YEAR(TODAY()),MONTH(TODAY()),1) -> 46296 | D32: =EDATE(C32,1) -> 46327 | E32: =EDATE(D32,1) -> 46357 | F32: =EDATE(E32,1) -> 46388 | G32: =EDATE(F32,1) -> 46419 | H32: =EDATE(G32,1) -> 46447
B33: AMER | C33: =COUNTIFS('Comms Calendar'!$B$5:$B$504,"AMER",'Comms Calendar'!$AJ$5:$AJ$504,C$32,'Comms Calendar'!$AE$5:$AE$504,"<>Cancelled") -> 4 | D33: =COUNTIFS('Comms Calendar'!$B$5:$B$504,"AMER",'Comms Calendar'!$AJ$5:$AJ$504,D$32,'Comms Calendar'!$AE$5:$AE$504,"<>Cancelled") -> 1 | E33: =COUNTIFS('Comms Calendar'!$B$5:$B$504,"AMER",'Comms Calendar'!$AJ$5:$AJ$504,E$32,'Comms Calendar'!$AE$5:$AE$504,"<>Cancelled") -> 0 | F33: =COUNTIFS('Comms Calendar'!$B$5:$B$504,"AMER",'Comms Calendar'!$AJ$5:$AJ$504,F$32,'Comms Calendar'!$AE$5:$AE$504,"<>Cancelled") -> 0 | G33: =COUNTIFS('Comms Calendar'!$B$5:$B$504,"AMER",'Comms Calendar'!$AJ$5:$AJ$504,G$32,'Comms Calendar'!$AE$5:$AE$504,"<>Cancelled") -> 0 | H33: =COUNTIFS('Comms Calendar'!$B$5:$B$504,"AMER",'Comms Calendar'!$AJ$5:$AJ$504,H$32,'Comms Calendar'!$AE$5:$AE$504,"<>Cancelled") -> 0
B34: EMEA | C34: =COUNTIFS('Comms Calendar'!$B$5:$B$504,"EMEA",'Comms Calendar'!$AJ$5:$AJ$504,C$32,'Comms Calendar'!$AE$5:$AE$504,"<>Cancelled") -> 2 | D34: =COUNTIFS('Comms Calendar'!$B$5:$B$504,"EMEA",'Comms Calendar'!$AJ$5:$AJ$504,D$32,'Comms Calendar'!$AE$5:$AE$504,"<>Cancelled") -> 1 | E34: =COUNTIFS('Comms Calendar'!$B$5:$B$504,"EMEA",'Comms Calendar'!$AJ$5:$AJ$504,E$32,'Comms Calendar'!$AE$5:$AE$504,"<>Cancelled") -> 0 | F34: =COUNTIFS('Comms Calendar'!$B$5:$B$504,"EMEA",'Comms Calendar'!$AJ$5:$AJ$504,F$32,'Comms Calendar'!$AE$5:$AE$504,"<>Cancelled") -> 0 | G34: =COUNTIFS('Comms Calendar'!$B$5:$B$504,"EMEA",'Comms Calendar'!$AJ$5:$AJ$504,G$32,'Comms Calendar'!$AE$5:$AE$504,"<>Cancelled") -> 0 | H34: =COUNTIFS('Comms Calendar'!$B$5:$B$504,"EMEA",'Comms Calendar'!$AJ$5:$AJ$504,H$32,'Comms Calendar'!$AE$5:$AE$504,"<>Cancelled") -> 0
B35: APAC | C35: =COUNTIFS('Comms Calendar'!$B$5:$B$504,"APAC",'Comms Calendar'!$AJ$5:$AJ$504,C$32,'Comms Calendar'!$AE$5:$AE$504,"<>Cancelled") -> 1 | D35: =COUNTIFS('Comms Calendar'!$B$5:$B$504,"APAC",'Comms Calendar'!$AJ$5:$AJ$504,D$32,'Comms Calendar'!$AE$5:$AE$504,"<>Cancelled") -> 1 | E35: =COUNTIFS('Comms Calendar'!$B$5:$B$504,"APAC",'Comms Calendar'!$AJ$5:$AJ$504,E$32,'Comms Calendar'!$AE$5:$AE$504,"<>Cancelled") -> 0 | F35: =COUNTIFS('Comms Calendar'!$B$5:$B$504,"APAC",'Comms Calendar'!$AJ$5:$AJ$504,F$32,'Comms Calendar'!$AE$5:$AE$504,"<>Cancelled") -> 0 | G35: =COUNTIFS('Comms Calendar'!$B$5:$B$504,"APAC",'Comms Calendar'!$AJ$5:$AJ$504,G$32,'Comms Calendar'!$AE$5:$AE$504,"<>Cancelled") -> 0 | H35: =COUNTIFS('Comms Calendar'!$B$5:$B$504,"APAC",'Comms Calendar'!$AJ$5:$AJ$504,H$32,'Comms Calendar'!$AE$5:$AE$504,"<>Cancelled") -> 0
B36: Global | C36: =COUNTIFS('Comms Calendar'!$B$5:$B$504,"Global",'Comms Calendar'!$AJ$5:$AJ$504,C$32,'Comms Calendar'!$AE$5:$AE$504,"<>Cancelled") -> 2 | D36: =COUNTIFS('Comms Calendar'!$B$5:$B$504,"Global",'Comms Calendar'!$AJ$5:$AJ$504,D$32,'Comms Calendar'!$AE$5:$AE$504,"<>Cancelled") -> 2 | E36: =COUNTIFS('Comms Calendar'!$B$5:$B$504,"Global",'Comms Calendar'!$AJ$5:$AJ$504,E$32,'Comms Calendar'!$AE$5:$AE$504,"<>Cancelled") -> 1 | F36: =COUNTIFS('Comms Calendar'!$B$5:$B$504,"Global",'Comms Calendar'!$AJ$5:$AJ$504,F$32,'Comms Calendar'!$AE$5:$AE$504,"<>Cancelled") -> 0 | G36: =COUNTIFS('Comms Calendar'!$B$5:$B$504,"Global",'Comms Calendar'!$AJ$5:$AJ$504,G$32,'Comms Calendar'!$AE$5:$AE$504,"<>Cancelled") -> 0 | H36: =COUNTIFS('Comms Calendar'!$B$5:$B$504,"Global",'Comms Calendar'!$AJ$5:$AJ$504,H$32,'Comms Calendar'!$AE$5:$AE$504,"<>Cancelled") -> 0
B37: Total | C37: =SUM(C33:C36) -> 9 | D37: =SUM(D33:D36) -> 5 | E37: =SUM(E33:E36) -> 1 | F37: =SUM(F33:F36) -> 0 | G37: =SUM(G33:G36) -> 0 | H37: =SUM(H33:H36) -> 0

Sheet Audience Lists
A1: Audience & List Registry
A2: Single source of truth for segment & list names. Use these exact names in the calendar so frequency and clash checks work. Marketing Ops owns list hygiene.
A4: List / Segment Name | B4: Region | C4: Audience Type | D4: Description / Criteria | E4: Source System | F4: Approx. Size | G4: List Owner | H4: Last Refreshed | I4: Consent Basis | J4: Standard Suppressions | K4: Notes
A5: AMER Customers - Active | B5: AMER | C5: Customer | D5: Paying accounts, all active contacts | E5: CRM | F5: 5200 | G5: Marketing Ops | H5: 46296 | I5: Customer relationship | J5: Unsubscribed; Bounced
A6: AMER Champions | B6: AMER | C6: Customer | D6: Advocates / NPS 9-10 | E6: CRM | F6: 350 | G6: Marketing Ops | H6: 46280 | I6: Customer relationship | J6: Unsubscribed
A7: AMER Prospects - Engaged 90d | B7: AMER | C7: Prospect | D7: Opened/clicked/visited in last 90 days | E7: MAP | F7: 6400 | G7: Marketing Ops | H7: 46296 | I7: Opt-in / legitimate interest | J7: Customers; Open opps; Unsubscribed
A8: EMEA Customers + Engaged Prospects | B8: EMEA | C8: Customer + Prospect | D8: Combined segment for EMEA programs | E8: CRM + MAP | F8: 9100 | G8: Marketing Ops | H8: 46296 | I8: GDPR: explicit consent required | J8: No consent; Unsubscribed | K8: Check consent per country
A9: EMEA Strategic Accounts | B9: EMEA | C9: Customer | D9: Top 50 accounts, exec contacts | E9: CRM | F9: 120 | G9: Head of Mkt EMEA | H9: 46295 | I9: Customer relationship | K9: Hand-curated with Sales
A10: APAC Customers + Engaged Prospects | B10: APAC | C10: Customer + Prospect | D10: Combined segment for APAC programs | E10: CRM + MAP | F10: 3000 | G10: Marketing Ops | H10: 46296 | I10: Opt-in (check AU Spam Act, JP APPI) | J10: Unsubscribed
A11: APAC Prospects - Engaged 90d | B11: APAC | C11: Prospect | D11: Engaged in last 90 days | E11: MAP | F11: 2100 | G11: Marketing Ops | H11: 46296 | I11: Opt-in | J11: Customers; Open opps
A12: All Customers | B12: Global | C12: Customer | D12: Every active customer contact worldwide | E12: CRM | F12: 21000 | G12: Marketing Ops | H12: 46296 | I12: Customer relationship | J12: Unsubscribed; Bounced

Sheet Owners & RACI
A1: Owners, RACI & Ways of Working
A3: Who's who
A4: Role | B4: Name | C4: Region / Scope | D4: Email | E4: Backup | F4: Owns in this calendar
A5: Head of Marketing (Global) | C5: Global | F5: Final say on the calendar, global launches, conflicts between regions
A6: Head of Mkt AMER | C6: AMER | F6: AMER plan, webinars, campaigns; approves AMER rows
A7: Head of Mkt EMEA | C7: EMEA | F7: EMEA plan, webinars, campaigns; approves EMEA rows
A8: APAC Marketing Lead | B8: TBC | C8: APAC | F8: APAC plan - owner to be confirmed
A9: Dean (Digital) | B9: Dean | C9: Global - Digital | F9: Email, newsletter, social, web; channel calendar & cadence
A10: Field Marketing | C10: All regions | F10: Webinars & events logistics, speakers, registrations
A11: Marketing Ops | C11: Global | F11: Lists, suppressions, builds, QA, sends, tracking; Ops tickets
A12: Product Marketing | C12: Global | F12: Launch messaging, release notes, in-app
A13: Customer Success | C13: All regions | F13: Customer notices; heads-up to CSMs before customer comms
A16: RACI (R = Responsible · A = Accountable · C = Consulted · I = Informed)
A17: Activity | B17: Head of Mkt (Global) | C17: Head of Mkt AMER | D17: Head of Mkt EMEA | E17: APAC Mkt Lead | F17: Dean (Digital) | G17: Field Marketing | H17: Marketing Ops | I17: Product Mktg | J17: Customer Success
A18: Calendar governance & final conflict resolution | B18: A | C18: R | D18: R | E18: R | F18: R | G18: C | H18: C | I18: I | J18: I
A19: Regional comms plan (AMER / EMEA / APAC) | B19: A | C19: R | D19: R | E19: R | F19: C | G19: C | H19: C | I19: C | J19: I
A20: Webinars (content, speakers, run of show) | B20: A | C20: R | D20: R | E20: R | F20: C | G20: R | H20: C | I20: C | J20: I
A21: Email campaigns & newsletter | B21: A | C21: C | D21: C | E21: C | F21: R | G21: I | H21: R | I21: C | J21: I
A22: Social media | B22: A | C22: C | D22: C | E22: C | F22: R | G22: I | H22: I | I22: C | J22: I
A23: Customer notices / customer-impacting comms | B23: A | C23: C | D23: C | E23: C | F23: C | G23: I | H23: R | I23: C | J23: R
A24: Audience definition & list selection | B24: I | C24: A | D24: A | E24: A | F24: R | G24: C | H24: R | I24: I | J24: C
A25: List pulls, suppressions, builds & QA | B25: I | C25: I | D25: I | E25: I | F25: C | G25: I | H25: A/R | I25: I | J25: I
A26: Send / launch execution | B26: I | C26: I | D26: I | E26: I | F26: A | G26: R | H26: R | I26: I | J26: I
A27: Approval of row before content lock | B27: A | C27: R | D27: R | E27: R | F27: C | G27: I | H27: I | I27: C | J27: C
A28: Product launch comms | B28: A | C28: C | D28: C | E28: C | F28: R | G28: C | H28: R | I28: R | J28: I
A29: Post-launch results & learnings | B29: A | C29: R | D29: R | E29: R | F29: R | G29: R | H29: R | I29: C | J29: I
A30: Proposed split — review and adjust together in the first sync.
A32: Ways of working (proposed)
A33: Ritual / Rule | B33: When | C33: Who | D33: What happens
A34: Weekly comms sync | B34: Every Monday, 30 min | C34: All owners + Marketing Ops | D34: Walk Week View for next 2 weeks: clear red flags, confirm Ops readiness, agree moves.
A35: Monthly regional planning | B35: Last week of the month | C35: Regional Heads + Dean (Digital) + Field | D35: Add next month's rows; check Month View for overload per region.
A36: Quarterly calendar review | B36: 2 weeks before quarter start | C36: Head of Marketing + all owners | D36: Lock flagship moments (launches, webinars, events) and global blackout dates.
A37: Adding a comm | B37: As soon as it's known | C37: Row owner | D37: Add a row with at least Region, Channel, Segment, Launch Date, Owner, Status = Planned.
A38: Ops request | B38: No later than 'Brief Due By' | C38: Row owner -> Marketing Ops | D38: Set 'Ops Involved? = Yes', raise a ticket, paste the ticket # in the row.
A39: Content lock | B39: Content-lock days before launch (see Rules) | C39: Row owner + Approver | D39: After lock, changes need Head of Marketing OK and go in the Change Log.
A40: Customer comms heads-up | B40: 5 business days before send | C40: Row owner -> Customer Success | D40: CS informed of anything reaching customers so CSMs aren't surprised.

Sheet Rules & Guardrails
A1: Rules & Guardrails
A2: Yellow cells are settings — change them and every check in the calendar updates.
A3: Max touches per segment, per region, per week | C3: 2 | D3: Proposed default. Drives the 'Frequency Flag' column. Agree the final number with the regional Heads of Marketing.
A4: Content lock (business days before launch) | C4: 5 | D4: Proposed default. After this point, changes need Head of Marketing sign-off (log them in the Change Log).
A5: At-risk window (days before launch) | C5: 7 | D5: Proposed default. A comm that is not fully ready inside this window is marked 'At Risk'.
A7: Channels — group & brief lead time | F7: Blackout / sensitive dates
A8: Channel | B8: Channel Group | C8: Brief Lead Time (business days) | D8: Typical Owning Team | F8: Date | G8: Region | H8: Reason
A9: Webinar | B9: Webinar | C9: 30 | D9: Field Marketing | F9: 46352 | G9: AMER | H9: US Thanksgiving
A10: Email - Webinar Invite / Reminder | B10: Email | C10: 10 | D10: Digital | F10: 46353 | G10: AMER | H10: Black Friday - inbox saturation
A11: Email - Newsletter | B11: Email | C11: 10 | D11: Digital | F11: 46380 | G11: Global | H11: Christmas Eve
A12: Email - Campaign / Nurture | B12: Email | C12: 10 | D12: Digital | F12: 46381 | G12: Global | H12: Christmas Day
A13: Email - Customer Notice | B13: Email | C13: 15 | D13: Customer Success | F13: 46382 | G13: EMEA | H13: Boxing Day
A14: Social - LinkedIn | B14: Social | C14: 3 | D14: Digital | F14: 46387 | G14: Global | H14: New Year's Eve
A15: Social - X | B15: Social | C15: 3 | D15: Digital | F15: 46388 | G15: Global | H15: New Year's Day
A16: Social - Other | B16: Social | C16: 3 | D16: Digital | F16: 46435 | G16: APAC | H16: Lunar New Year
A17: Event - In-person | B17: Event | C17: 40 | D17: Field Marketing | F17: 46436 | G17: APAC | H17: Lunar New Year
A18: Event - Virtual | B18: Event | C18: 25 | D18: Field Marketing
A19: Blog / Website | B19: Web | C19: 5 | D19: Content
A20: Press Release / PR | B20: PR | C20: 15 | D20: Comms / PR
A21: In-app / Product Message | B21: In-app | C21: 10 | D21: Product Marketing
A22: Customer Community | B22: Community | C22: 5 | D22: Customer Success
A23: Paid Media | B23: Paid | C23: 10 | D23: Digital
A24: Partner Comms | B24: Partner | C24: 10 | D24: Regional Marketing
A25: Lead times are proposed defaults (blue = editable) — confirm with Marketing Ops.
F61: Add each region's public holidays, quiet periods, earnings dates, etc.

Sheet Change Log
A1: Change Log
A2: Log any change to a comm after content lock, or any date move that affects another region/team.
A4: Date | B4: Comm ID | C4: What Changed | D4: Old Value | E4: New Value | F4: Reason | G4: Changed By | H4: Approved By | I4: Teams Notified?
A5: 46303 | B5: AM-002 | C5: Launch date | D5: 13 Oct | E5: 16 Oct (proposed) | F5: Clashes with AM-001 to same segment | G5: Customer Success | H5: Head of Mkt AMER | I5: No

Sheet Dropdowns
A1: Region | B1: Audience Type | C1: Team | D1: Owner | E1: Content Status | F1: Yes / No | G1: Overall Status | H1: Time Zone | I1: Frequency | J1: Language | K1: Region Filter
A2: AMER | B2: Customer | C2: Digital | D2: Head of Marketing (Global) | E2: Not started | F2: Yes | G2: Planned | H2: ET | I2: One-off | J2: EN | K2: All
A3: EMEA | B3: Prospect | C3: Field Marketing | D3: Head of Mkt AMER | E3: Drafting | F3: No | G3: In production | H3: CT | I3: Daily | J3: FR | K3: AMER
A4: APAC | B4: Customer + Prospect | C4: Marketing Ops | D4: Head of Mkt EMEA | E4: In review | F4: N/A | G4: Scheduled | H4: PT | I4: Weekly | J4: DE | K4: EMEA
A5: Global | B5: Partner | C5: Product Marketing | D5: APAC Marketing Lead | E5: Approved | G5: Launched | H5: GMT/BST | I5: Bi-weekly | J5: ES | K5: APAC
B6: Internal | C6: Content | D6: Dean (Digital) | G6: On hold | H6: CET | I6: Monthly | J6: IT | K6: Global
C7: Comms / PR | D7: Field Marketing | G7: Cancelled | H7: GST (Dubai) | I7: Quarterly | J7: NL
C8: Customer Success | D8: Marketing Ops | H8: IST | I8: Sequence (multi-touch) | J8: PT
C9: Regional Marketing | D9: Product Marketing | H9: SGT | J9: JA
D10: Customer Success | H10: JST | J10: ZH
H11: AEST | J11: KO
J12: AR
J13: Multi
A15: Edit these lists to change the dropdown options across the workbook.
